{"0150000":{"zip_code":"0150000","pref_kanji":"\u79cb\u7530\u770c","city_kanji":"\u7531\u5229\u672c\u8358\u5e02","town_kanji":"\u4ee5\u4e0b\u306b\u63b2\u8f09\u304c\u306a\u3044\u5834\u5408","pref_roman":"AKITA KEN","city_roman":"YURIHONJO SHI","town_roman":"IKANIKEISAIGANAIBAAI","code":"05210","old_zip_code":"015  ","pref_kana":"\uff71\uff77\uff80\uff79\uff9d","city_kana":"\uff95\uff98\uff8e\uff9d\uff7c\uff9e\uff6e\uff73\uff7c","town_kana":"\uff72\uff76\uff86\uff79\uff72\uff7b\uff72\uff76\uff9e\uff85\uff72\uff8a\uff9e\uff71\uff72"},"0150023":{"zip_code":"0150023","pref_kanji":"\u79cb\u7530\u770c","city_kanji":"\u7531\u5229\u672c\u8358\u5e02","town_kanji":"\u8d64\u7530","pref_roman":"AKITA KEN","city_roman":"YURIHONJO SHI","town_roman":"AKATA","code":"05210","old_zip_code":"015  ","pref_kana":"\uff71\uff77\uff80\uff79\uff9d","city_kana":"\uff95\uff98\uff8e\uff9d\uff7c\uff9e\uff6e\uff73\uff7c","town_kana":"\uff71\uff76\uff80"},"0150836":{"zip_code":"0150836","pref_kanji":"\u79cb\u7530\u770c","city_kanji":"\u7531\u5229\u672c\u8358\u5e02","town_kanji":"\u8d64\u6cbc\u4e0b","pref_roman":"AKITA KEN","city_roman":"YURIHONJO SHI","town_roman":"AKANUMASHITA","code":"05210","old_zip_code":"015  ","pref_kana":"\uff71\uff77\uff80\uff79\uff9d","city_kana":"\uff95\uff98\uff8e\uff9d\uff7c\uff9e\uff6e\uff73\uff7c","town_kana":"\uff71\uff76\uff87\uff8f\uff7c\uff80"},"0150079":{"zip_code":"0150079","pref_kanji":"\u79cb\u7530\u770c","city_kanji":"\u7531\u5229\u672c\u8358\u5e02","town_kanji":"\u8d64\u6cbc\u4e0b\u9053","pref_roman":"AKITA KEN","city_roman":"YURIHONJO SHI","town_roman":"AKANUMASHITAMICHI","code":"05210","old_zip_code":"015  ","pref_kana":"\uff71\uff77\uff80\uff79\uff9d","city_kana":"\uff95\uff98\uff8e\uff9d\uff7c\uff9e\uff6e\uff73\uff7c","town_kana":"\uff71\uff76\uff87\uff8f\uff7c\uff80\uff90\uff81"},"0150071":{"zip_code":"0150071","pref_kanji":"\u79cb\u7530\u770c","city_kanji":"\u7531\u5229\u672c\u8358\u5e02","town_kanji":"\u8d64\u6cbc\u753a","pref_roman":"AKITA KEN","city_roman":"YURIHONJO SHI","town_roman":"AKANUMAMACHI","code":"05210","old_zip_code":"015  ","pref_kana":"\uff71\uff77\uff80\uff79\uff9d","city_kana":"\uff95\uff98\uff8e\uff9d\uff7c\uff9e\uff6e\uff73\uff7c","town_kana":"\uff71\uff76\uff87\uff8f\uff8f\uff81"},"0150034":{"zip_code":"0150034","pref_kanji":"\u79cb\u7530\u770c","city_kanji":"\u7531\u5229\u672c\u8358\u5e02","town_kanji":"\u82a6\u5ddd","pref_roman":"AKITA KEN","city_roman":"YURIHONJO SHI","town_roman":"ASHIKAWA","code":"05210","old_zip_code":"015  ","pref_kana":"\uff71\uff77\uff80\uff79\uff9d","city_kana":"\uff95\uff98\uff8e\uff9d\uff7c\uff9e\uff6e\uff73\uff7c","town_kana":"\uff71\uff7c\uff76\uff9c"},"0150084":{"zip_code":"0150084","pref_kanji":"\u79cb\u7530\u770c","city_kanji":"\u7531\u5229\u672c\u8358\u5e02","town_kanji":"\u9b8e\u702c","pref_roman":"AKITA KEN","city_roman":"YURIHONJO SHI","town_roman":"AYUSE","code":"05210","old_zip_code":"015  ","pref_kana":"\uff71\uff77\uff80\uff79\uff9d","city_kana":"\uff95\uff98\uff8e\uff9d\uff7c\uff9e\uff6e\uff73\uff7c","town_kana":"\uff71\uff95\uff7e"},"0150065":{"zip_code":"0150065","pref_kanji":"\u79cb\u7530\u770c","city_kanji":"\u7531\u5229\u672c\u8358\u5e02","town_kanji":"\u8352\u753a","pref_roman":"AKITA KEN","city_roman":"YURIHONJO SHI","town_roman":"ARAMACHI","code":"05210","old_zip_code":"015  ","pref_kana":"\uff71\uff77\uff80\uff79\uff9d","city_kana":"\uff95\uff98\uff8e\uff9d\uff7c\uff9e\uff6e\uff73\uff7c","town_kana":"\uff71\uff97\uff8f\uff81"},"0150892":{"zip_code":"0150892","pref_kanji":"\u79cb\u7530\u770c","city_kanji":"\u7531\u5229\u672c\u8358\u5e02","town_kanji":"\u87fb\u5c71","pref_roman":"AKITA KEN","city_roman":"YURIHONJO SHI","town_roman":"ARIYAMA","code":"05210","old_zip_code":"015  ","pref_kana":"\uff71\uff77\uff80\uff79\uff9d","city_kana":"\uff95\uff98\uff8e\uff9d\uff7c\uff9e\uff6e\uff73\uff7c","town_kana":"\uff71\uff98\uff94\uff8f"},"0150301":{"zip_code":"0150301","pref_kanji":"\u79cb\u7530\u770c","city_kanji":"\u7531\u5229\u672c\u8358\u5e02","town_kanji":"\u98ef\u6ca2","pref_roman":"AKITA KEN","city_roman":"YURIHONJO SHI","town_roman":"IIZAWA","code":"05210","old_zip_code":"01503","pref_kana":"\uff71\uff77\uff80\uff79\uff9d","city_kana":"\uff95\uff98\uff8e\uff9d\uff7c\uff9e\uff6e\uff73\uff7c","town_kana":"\uff72\uff72\uff7b\uff9e\uff9c"},"0150311":{"zip_code":"0150311","pref_kanji":"\u79cb\u7530\u770c","city_kanji":"\u7531\u5229\u672c\u8358\u5e02","town_kanji":"\u4e94\u5341\u571f","pref_roman":"AKITA KEN","city_roman":"YURIHONJO SHI","town_roman":"IKAZUCHI","code":"05210","old_zip_code":"01503","pref_kana":"\uff71\uff77\uff80\uff79\uff9d","city_kana":"\uff95\uff98\uff8e\uff9d\uff7c\uff9e\uff6e\uff73\uff7c","town_kana":"\uff72\uff76\uff82\uff9e\uff81"},"0150012":{"zip_code":"0150012","pref_kanji":"\u79cb\u7530\u770c","city_kanji":"\u7531\u5229\u672c\u8358\u5e02","town_kanji":"\u77f3\u8107\uff08\u7530\u5c3b\uff09","pref_roman":"AKITA KEN","city_roman":"YURIHONJO SHI","town_roman":"ISHIWAKI (TAJIRI)","code":"05210","old_zip_code":"015  ","pref_kana":"\uff71\uff77\uff80\uff79\uff9d","city_kana":"\uff95\uff98\uff8e\uff9d\uff7c\uff9e\uff6e\uff73\uff7c","town_kana":"\uff72\uff7c\uff9c\uff77(\uff80\uff7c\uff9e\uff98)"},"0150013":{"zip_code":"0150013","pref_kanji":"\u79cb\u7530\u770c","city_kanji":"\u7531\u5229\u672c\u8358\u5e02","town_kanji":"\u77f3\u8107\uff08\u7530\u5c3b\u91ce\uff09","pref_roman":"AKITA KEN","city_roman":"YURIHONJO SHI","town_roman":"ISHIWAKI (TAJIRINO)","code":"05210","old_zip_code":"015  ","pref_kana":"\uff71\uff77\uff80\uff79\uff9d","city_kana":"\uff95\uff98\uff8e\uff9d\uff7c\uff9e\uff6e\uff73\uff7c","town_kana":"\uff72\uff7c\uff9c\uff77(\uff80\uff7c\uff9e\uff98\uff89)"},"0150014":{"zip_code":"0150014","pref_kanji":"\u79cb\u7530\u770c","city_kanji":"\u7531\u5229\u672c\u8358\u5e02","town_kanji":"\u77f3\u8107\uff08\u5c71\u30ce\u795e\uff09","pref_roman":"AKITA KEN","city_roman":"YURIHONJO SHI","town_roman":"ISHIWAKI (YAMANOKAMI)","code":"05210","old_zip_code":"015  ","pref_kana":"\uff71\uff77\uff80\uff79\uff9d","city_kana":"\uff95\uff98\uff8e\uff9d\uff7c\uff9e\uff6e\uff73\uff7c","town_kana":"\uff72\uff7c\uff9c\uff77(\uff94\uff8f\uff89\uff76\uff90)"},"0150011":{"zip_code":"0150011","pref_kanji":"\u79cb\u7530\u770c","city_kanji":"\u7531\u5229\u672c\u8358\u5e02","town_kanji":"\u77f3\u8107\uff08\u305d\u306e\u4ed6\uff09","pref_roman":"AKITA KEN","city_roman":"YURIHONJO SHI","town_roman":"ISHIWAKI(SONOTA)","code":"05210","old_zip_code":"015  ","pref_kana":"\uff71\uff77\uff80\uff79\uff9d","city_kana":"\uff95\uff98\uff8e\uff9d\uff7c\uff9e\uff6e\uff73\uff7c","town_kana":"\uff72\uff7c\uff9c\uff77(\uff7f\uff89\uff80)"},"0150823":{"zip_code":"0150823","pref_kanji":"\u79cb\u7530\u770c","city_kanji":"\u7531\u5229\u672c\u8358\u5e02","town_kanji":"\u548c\u6cc9\u753a","pref_roman":"AKITA KEN","city_roman":"YURIHONJO SHI","town_roman":"IZUMIMACHI","code":"05210","old_zip_code":"015  ","pref_kana":"\uff71\uff77\uff80\uff79\uff9d","city_kana":"\uff95\uff98\uff8e\uff9d\uff7c\uff9e\uff6e\uff73\uff7c","town_kana":"\uff72\uff7d\uff9e\uff90\uff8f\uff81"},"0150852":{"zip_code":"0150852","pref_kanji":"\u79cb\u7530\u770c","city_kanji":"\u7531\u5229\u672c\u8358\u5e02","town_kanji":"\u4e00\u756a\u5830","pref_roman":"AKITA KEN","city_roman":"YURIHONJO SHI","town_roman":"ICHIBANZEKI","code":"05210","old_zip_code":"015  ","pref_kana":"\uff71\uff77\uff80\uff79\uff9d","city_kana":"\uff95\uff98\uff8e\uff9d\uff7c\uff9e\uff6e\uff73\uff7c","town_kana":"\uff72\uff81\uff8a\uff9e\uff9d\uff7e\uff9e\uff77"},"0150876":{"zip_code":"0150876","pref_kanji":"\u79cb\u7530\u770c","city_kanji":"\u7531\u5229\u672c\u8358\u5e02","town_kanji":"\u4e95\u6238\u5c3b","pref_roman":"AKITA KEN","city_roman":"YURIHONJO SHI","town_roman":"IDOJIRI","code":"05210","old_zip_code":"015  ","pref_kana":"\uff71\uff77\uff80\uff79\uff9d","city_kana":"\uff95\uff98\uff8e\uff9d\uff7c\uff9e\uff6e\uff73\uff7c","town_kana":"\uff72\uff84\uff9e\uff7c\uff9e\uff98"},"0150834":{"zip_code":"0150834","pref_kanji":"\u79cb\u7530\u770c","city_kanji":"\u7531\u5229\u672c\u8358\u5e02","town_kanji":"\u5ca9\u6e15\u4e0b","pref_roman":"AKITA KEN","city_roman":"YURIHONJO SHI","town_roman":"IWABUCHISHITA","code":"05210","old_zip_code":"015  ","pref_kana":"\uff71\uff77\uff80\uff79\uff9d","city_kana":"\uff95\uff98\uff8e\uff9d\uff7c\uff9e\uff6e\uff73\uff7c","town_kana":"\uff72\uff9c\uff8c\uff9e\uff81\uff7c\uff80"},"0150814":{"zip_code":"0150814","pref_kanji":"\u79cb\u7530\u770c","city_kanji":"\u7531\u5229\u672c\u8358\u5e02","town_kanji":"\u5f8c\u753a","pref_roman":"AKITA KEN","city_roman":"YURIHONJO SHI","town_roman":"USHIROMACHI","code":"05210","old_zip_code":"015  ","pref_kana":"\uff71\uff77\uff80\uff79\uff9d","city_kana":"\uff95\uff98\uff8e\uff9d\uff7c\uff9e\uff6e\uff73\uff7c","town_kana":"\uff73\uff7c\uff9b\uff8f\uff81"},"0150022":{"zip_code":"0150022","pref_kanji":"\u79cb\u7530\u770c","city_kanji":"\u7531\u5229\u672c\u8358\u5e02","town_kanji":"\u5185\u9ed2\u702c","pref_roman":"AKITA KEN","city_roman":"YURIHONJO SHI","town_roman":"UCHIKUROSE","code":"05210","old_zip_code":"015  ","pref_kana":"\uff71\uff77\uff80\uff79\uff9d","city_kana":"\uff95\uff98\uff8e\uff9d\uff7c\uff9e\uff6e\uff73\uff7c","town_kana":"\uff73\uff81\uff78\uff9b\uff7e"},"0150024":{"zip_code":"0150024","pref_kanji":"\u79cb\u7530\u770c","city_kanji":"\u7531\u5229\u672c\u8358\u5e02","town_kanji":"\u5185\u8d8a","pref_roman":"AKITA KEN","city_roman":"YURIHONJO SHI","town_roman":"UTETSU","code":"05210","old_zip_code":"015  ","pref_kana":"\uff71\uff77\uff80\uff79\uff9d","city_kana":"\uff95\uff98\uff8e\uff9d\uff7c\uff9e\uff6e\uff73\uff7c","town_kana":"\uff73\uff83\uff82"},"0150042":{"zip_code":"0150042","pref_kanji":"\u79cb\u7530\u770c","city_kanji":"\u7531\u5229\u672c\u8358\u5e02","town_kanji":"\u57cb\u7530","pref_roman":"AKITA KEN","city_roman":"YURIHONJO SHI","town_roman":"UMEDA","code":"05210","old_zip_code":"015  ","pref_kana":"\uff71\uff77\uff80\uff79\uff9d","city_kana":"\uff95\uff98\uff8e\uff9d\uff7c\uff9e\uff6e\uff73\uff7c","town_kana":"\uff73\uff92\uff80\uff9e"},"0150072":{"zip_code":"0150072","pref_kanji":"\u79cb\u7530\u770c","city_kanji":"\u7531\u5229\u672c\u8358\u5e02","town_kanji":"\u88cf\u5c3e\u5d0e\u753a","pref_roman":"AKITA KEN","city_roman":"YURIHONJO SHI","town_roman":"URAOZAKIMACHI","code":"05210","old_zip_code":"015  ","pref_kana":"\uff71\uff77\uff80\uff79\uff9d","city_kana":"\uff95\uff98\uff8e\uff9d\uff7c\uff9e\uff6e\uff73\uff7c","town_kana":"\uff73\uff97\uff75\uff7b\uff9e\uff77\uff8f\uff81"},"0150094":{"zip_code":"0150094","pref_kanji":"\u79cb\u7530\u770c","city_kanji":"\u7531\u5229\u672c\u8358\u5e02","town_kanji":"\u4e0a\u91ce","pref_roman":"AKITA KEN","city_roman":"YURIHONJO SHI","town_roman":"UWANO","code":"05210","old_zip_code":"015  ","pref_kana":"\uff71\uff77\uff80\uff79\uff9d","city_kana":"\uff95\uff98\uff8e\uff9d\uff7c\uff9e\uff6e\uff73\uff7c","town_kana":"\uff73\uff9c\uff89"},"0150856":{"zip_code":"0150856","pref_kanji":"\u79cb\u7530\u770c","city_kanji":"\u7531\u5229\u672c\u8358\u5e02","town_kanji":"\u5186\u6b63\u8107","pref_roman":"AKITA KEN","city_roman":"YURIHONJO SHI","town_roman":"ENSHOWAKI","code":"05210","old_zip_code":"015  ","pref_kana":"\uff71\uff77\uff80\uff79\uff9d","city_kana":"\uff95\uff98\uff8e\uff9d\uff7c\uff9e\uff6e\uff73\uff7c","town_kana":"\uff74\uff9d\uff7c\uff6e\uff73\uff9c\uff77"},"0150864":{"zip_code":"0150864","pref_kanji":"\u79cb\u7530\u770c","city_kanji":"\u7531\u5229\u672c\u8358\u5e02","town_kanji":"\u5927\u936c\u753a","pref_roman":"AKITA KEN","city_roman":"YURIHONJO SHI","town_roman":"OKUWAMACHI","code":"05210","old_zip_code":"015  ","pref_kana":"\uff71\uff77\uff80\uff79\uff9d","city_kana":"\uff95\uff98\uff8e\uff9d\uff7c\uff9e\uff6e\uff73\uff7c","town_kana":"\uff75\uff75\uff78\uff9c\uff8f\uff81"},"0150093":{"zip_code":"0150093","pref_kanji":"\u79cb\u7530\u770c","city_kanji":"\u7531\u5229\u672c\u8358\u5e02","town_kanji":"\u5927\u6ca2","pref_roman":"AKITA KEN","city_roman":"YURIHONJO SHI","town_roman":"OSAWA","code":"05210","old_zip_code":"015  ","pref_kana":"\uff71\uff77\uff80\uff79\uff9d","city_kana":"\uff95\uff98\uff8e\uff9d\uff7c\uff9e\uff6e\uff73\uff7c","town_kana":"\uff75\uff75\uff7b\uff9c"},"0150868":{"zip_code":"0150868","pref_kanji":"\u79cb\u7530\u770c","city_kanji":"\u7531\u5229\u672c\u8358\u5e02","town_kanji":"\u5927\u5824\u4e0b","pref_roman":"AKITA KEN","city_roman":"YURIHONJO SHI","town_roman":"OZUTSUMISHITA","code":"05210","old_zip_code":"015  ","pref_kana":"\uff71\uff77\uff80\uff79\uff9d","city_kana":"\uff95\uff98\uff8e\uff9d\uff7c\uff9e\uff6e\uff73\uff7c","town_kana":"\uff75\uff75\uff82\uff9e\uff82\uff90\uff7c\uff80"},"0150062":{"zip_code":"0150062","pref_kanji":"\u79cb\u7530\u770c","city_kanji":"\u7531\u5229\u672c\u8358\u5e02","town_kanji":"\u5927\u4e2d\u30ce\u6ca2","pref_roman":"AKITA KEN","city_roman":"YURIHONJO SHI","town_roman":"ONAKANOSAWA","code":"05210","old_zip_code":"015  ","pref_kana":"\uff71\uff77\uff80\uff79\uff9d","city_kana":"\uff95\uff98\uff8e\uff9d\uff7c\uff9e\uff6e\uff73\uff7c","town_kana":"\uff75\uff75\uff85\uff76\uff89\uff7b\uff9c"},"0150816":{"zip_code":"0150816","pref_kanji":"\u79cb\u7530\u770c","city_kanji":"\u7531\u5229\u672c\u8358\u5e02","town_kanji":"\u5927\u753a","pref_roman":"AKITA KEN","city_roman":"YURIHONJO SHI","town_roman":"OMACHI","code":"05210","old_zip_code":"015  ","pref_kana":"\uff71\uff77\uff80\uff79\uff9d","city_kana":"\uff95\uff98\uff8e\uff9d\uff7c\uff9e\uff6e\uff73\uff7c","town_kana":"\uff75\uff75\uff8f\uff81"},"0150312":{"zip_code":"0150312","pref_kanji":"\u79cb\u7530\u770c","city_kanji":"\u7531\u5229\u672c\u8358\u5e02","town_kanji":"\u5927\u6c34\u53e3","pref_roman":"AKITA KEN","city_roman":"YURIHONJO SHI","town_roman":"OMINAKUCHI","code":"05210","old_zip_code":"01503","pref_kana":"\uff71\uff77\uff80\uff79\uff9d","city_kana":"\uff95\uff98\uff8e\uff9d\uff7c\uff9e\uff6e\uff73\uff7c","town_kana":"\uff75\uff75\uff90\uff85\uff78\uff81"},"0150091":{"zip_code":"0150091","pref_kanji":"\u79cb\u7530\u770c","city_kanji":"\u7531\u5229\u672c\u8358\u5e02","town_kanji":"\u5927\u7c17","pref_roman":"AKITA KEN","city_roman":"YURIHONJO SHI","town_roman":"OYANA","code":"05210","old_zip_code":"015  ","pref_kana":"\uff71\uff77\uff80\uff79\uff9d","city_kana":"\uff95\uff98\uff8e\uff9d\uff7c\uff9e\uff6e\uff73\uff7c","town_kana":"\uff75\uff75\uff94\uff85"},"0150021":{"zip_code":"0150021","pref_kanji":"\u79cb\u7530\u770c","city_kanji":"\u7531\u5229\u672c\u8358\u5e02","town_kanji":"\u5927\u6d66","pref_roman":"AKITA KEN","city_roman":"YURIHONJO SHI","town_roman":"ORA","code":"05210","old_zip_code":"015  ","pref_kana":"\uff71\uff77\uff80\uff79\uff9d","city_kana":"\uff95\uff98\uff8e\uff9d\uff7c\uff9e\uff6e\uff73\uff7c","town_kana":"\uff75\uff75\uff97"},"0150811":{"zip_code":"0150811","pref_kanji":"\u79cb\u7530\u770c","city_kanji":"\u7531\u5229\u672c\u8358\u5e02","town_kanji":"\u6876\u5c4b\u753a","pref_roman":"AKITA KEN","city_roman":"YURIHONJO SHI","town_roman":"OKEYAMACHI","code":"05210","old_zip_code":"015  ","pref_kana":"\uff71\uff77\uff80\uff79\uff9d","city_kana":"\uff95\uff98\uff8e\uff9d\uff7c\uff9e\uff6e\uff73\uff7c","town_kana":"\uff75\uff79\uff94\uff8f\uff81"},"0150871":{"zip_code":"0150871","pref_kanji":"\u79cb\u7530\u770c","city_kanji":"\u7531\u5229\u672c\u8358\u5e02","town_kanji":"\u5c3e\u5d0e","pref_roman":"AKITA KEN","city_roman":"YURIHONJO SHI","town_roman":"OZAKI","code":"05210","old_zip_code":"015  ","pref_kana":"\uff71\uff77\uff80\uff79\uff9d","city_kana":"\uff95\uff98\uff8e\uff9d\uff7c\uff9e\uff6e\uff73\uff7c","town_kana":"\uff75\uff7b\uff9e\uff77"},"0150802":{"zip_code":"0150802","pref_kanji":"\u79cb\u7530\u770c","city_kanji":"\u7531\u5229\u672c\u8358\u5e02","town_kanji":"\u8868\u5c3e\u5d0e\u753a","pref_roman":"AKITA KEN","city_roman":"YURIHONJO SHI","town_roman":"OMOTEOZAKIMACHI","code":"05210","old_zip_code":"015  ","pref_kana":"\uff71\uff77\uff80\uff79\uff9d","city_kana":"\uff95\uff98\uff8e\uff9d\uff7c\uff9e\uff6e\uff73\uff7c","town_kana":"\uff75\uff93\uff83\uff75\uff7b\uff9e\uff77\uff8f\uff81"},"0150035":{"zip_code":"0150035","pref_kanji":"\u79cb\u7530\u770c","city_kanji":"\u7531\u5229\u672c\u8358\u5e02","town_kanji":"\u89aa\u5ddd","pref_roman":"AKITA KEN","city_roman":"YURIHONJO SHI","town_roman":"OYAKAWA","code":"05210","old_zip_code":"015  ","pref_kana":"\uff71\uff77\uff80\uff79\uff9d","city_kana":"\uff95\uff98\uff8e\uff9d\uff7c\uff9e\uff6e\uff73\uff7c","town_kana":"\uff75\uff94\uff76\uff9c"},"0150812":{"zip_code":"0150812","pref_kanji":"\u79cb\u7530\u770c","city_kanji":"\u7531\u5229\u672c\u8358\u5e02","town_kanji":"\u935b\u6cbb\u753a","pref_roman":"AKITA KEN","city_roman":"YURIHONJO SHI","town_roman":"KAJIMACHI","code":"05210","old_zip_code":"015  ","pref_kana":"\uff71\uff77\uff80\uff79\uff9d","city_kana":"\uff95\uff98\uff8e\uff9d\uff7c\uff9e\uff6e\uff73\uff7c","town_kana":"\uff76\uff7c\uff9e\uff8f\uff81"},"0150826":{"zip_code":"0150826","pref_kanji":"\u79cb\u7530\u770c","city_kanji":"\u7531\u5229\u672c\u8358\u5e02","town_kanji":"\u7247\u753a","pref_roman":"AKITA KEN","city_roman":"YURIHONJO SHI","town_roman":"KATAMACHI","code":"05210","old_zip_code":"015  ","pref_kana":"\uff71\uff77\uff80\uff79\uff9d","city_kana":"\uff95\uff98\uff8e\uff9d\uff7c\uff9e\uff6e\uff73\uff7c","town_kana":"\uff76\uff80\uff8f\uff81"},"0150321":{"zip_code":"0150321","pref_kanji":"\u79cb\u7530\u770c","city_kanji":"\u7531\u5229\u672c\u8358\u5e02","town_kanji":"\u87f9\u6ca2","pref_roman":"AKITA KEN","city_roman":"YURIHONJO SHI","town_roman":"KANIZAWA","code":"05210","old_zip_code":"01503","pref_kana":"\uff71\uff77\uff80\uff79\uff9d","city_kana":"\uff95\uff98\uff8e\uff9d\uff7c\uff9e\uff6e\uff73\uff7c","town_kana":"\uff76\uff86\uff7b\uff9e\uff9c"},"0150066":{"zip_code":"0150066","pref_kanji":"\u79cb\u7530\u770c","city_kanji":"\u7531\u5229\u672c\u8358\u5e02","town_kanji":"\u91d1\u5c71","pref_roman":"AKITA KEN","city_roman":"YURIHONJO SHI","town_roman":"KANEYAMA","code":"05210","old_zip_code":"015  ","pref_kana":"\uff71\uff77\uff80\uff79\uff9d","city_kana":"\uff95\uff98\uff8e\uff9d\uff7c\uff9e\uff6e\uff73\uff7c","town_kana":"\uff76\uff88\uff94\uff8f"},"0150854":{"zip_code":"0150854","pref_kanji":"\u79cb\u7530\u770c","city_kanji":"\u7531\u5229\u672c\u8358\u5e02","town_kanji":"\u4e0a\u5927\u91ce","pref_roman":"AKITA KEN","city_roman":"YURIHONJO SHI","town_roman":"KAMIONO","code":"05210","old_zip_code":"015  ","pref_kana":"\uff71\uff77\uff80\uff79\uff9d","city_kana":"\uff95\uff98\uff8e\uff9d\uff7c\uff9e\uff6e\uff73\uff7c","town_kana":"\uff76\uff90\uff75\uff75\uff89"},"0150085":{"zip_code":"0150085","pref_kanji":"\u79cb\u7530\u770c","city_kanji":"\u7531\u5229\u672c\u8358\u5e02","town_kanji":"\u70cf\u5ddd","pref_roman":"AKITA KEN","city_roman":"YURIHONJO SHI","town_roman":"KARASUKAWA","code":"05210","old_zip_code":"015  ","pref_kana":"\uff71\uff77\uff80\uff79\uff9d","city_kana":"\uff95\uff98\uff8e\uff9d\uff7c\uff9e\uff6e\uff73\uff7c","town_kana":"\uff76\uff97\uff7d\uff76\uff9c"},"0150051":{"zip_code":"0150051","pref_kanji":"\u79cb\u7530\u770c","city_kanji":"\u7531\u5229\u672c\u8358\u5e02","town_kanji":"\u5ddd\u53e3","pref_roman":"AKITA KEN","city_roman":"YURIHONJO SHI","town_roman":"KAWAGUCHI","code":"05210","old_zip_code":"015  ","pref_kana":"\uff71\uff77\uff80\uff79\uff9d","city_kana":"\uff95\uff98\uff8e\uff9d\uff7c\uff9e\uff6e\uff73\uff7c","town_kana":"\uff76\uff9c\uff78\uff9e\uff81"},"0150331":{"zip_code":"0150331","pref_kanji":"\u79cb\u7530\u770c","city_kanji":"\u7531\u5229\u672c\u8358\u5e02","town_kanji":"\u5ddd\u897f","pref_roman":"AKITA KEN","city_roman":"YURIHONJO SHI","town_roman":"KAWANISHI","code":"05210","old_zip_code":"01503","pref_kana":"\uff71\uff77\uff80\uff79\uff9d","city_kana":"\uff95\uff98\uff8e\uff9d\uff7c\uff9e\uff6e\uff73\uff7c","town_kana":"\uff76\uff9c\uff86\uff7c"},"0150872":{"zip_code":"0150872","pref_kanji":"\u79cb\u7530\u770c","city_kanji":"\u7531\u5229\u672c\u8358\u5e02","town_kanji":"\u74e6\u8c37\u5730","pref_roman":"AKITA KEN","city_roman":"YURIHONJO SHI","town_roman":"KAWARAYACHI","code":"05210","old_zip_code":"015  ","pref_kana":"\uff71\uff77\uff80\uff79\uff9d","city_kana":"\uff95\uff98\uff8e\uff9d\uff7c\uff9e\uff6e\uff73\uff7c","town_kana":"\uff76\uff9c\uff97\uff94\uff81"},"0150825":{"zip_code":"0150825","pref_kanji":"\u79cb\u7530\u770c","city_kanji":"\u7531\u5229\u672c\u8358\u5e02","town_kanji":"\u89b3\u97f3\u753a","pref_roman":"AKITA KEN","city_roman":"YURIHONJO SHI","town_roman":"KANNOMMACHI","code":"05210","old_zip_code":"015  ","pref_kana":"\uff71\uff77\uff80\uff79\uff9d","city_kana":"\uff95\uff98\uff8e\uff9d\uff7c\uff9e\uff6e\uff73\uff7c","town_kana":"\uff76\uff9d\uff89\uff9d\uff8f\uff81"},"0150878":{"zip_code":"0150878","pref_kanji":"\u79cb\u7530\u770c","city_kanji":"\u7531\u5229\u672c\u8358\u5e02","town_kanji":"\u89b3\u97f3\u68ee","pref_roman":"AKITA KEN","city_roman":"YURIHONJO SHI","town_roman":"KANNOMMORI","code":"05210","old_zip_code":"015  ","pref_kana":"\uff71\uff77\uff80\uff79\uff9d","city_kana":"\uff95\uff98\uff8e\uff9d\uff7c\uff9e\uff6e\uff73\uff7c","town_kana":"\uff76\uff9d\uff89\uff9d\uff93\uff98"},"0150831":{"zip_code":"0150831","pref_kanji":"\u79cb\u7530\u770c","city_kanji":"\u7531\u5229\u672c\u8358\u5e02","town_kanji":"\u5317\u88cf\u5730","pref_roman":"AKITA KEN","city_roman":"YURIHONJO SHI","town_roman":"KITAURAJI","code":"05210","old_zip_code":"015  ","pref_kana":"\uff71\uff77\uff80\uff79\uff9d","city_kana":"\uff95\uff98\uff8e\uff9d\uff7c\uff9e\uff6e\uff73\uff7c","town_kana":"\uff77\uff80\uff73\uff97\uff7c\uff9e"},"0150069":{"zip_code":"0150069","pref_kanji":"\u79cb\u7530\u770c","city_kanji":"\u7531\u5229\u672c\u8358\u5e02","town_kanji":"\u5317\u30ce\u80a1","pref_roman":"AKITA KEN","city_roman":"YURIHONJO SHI","town_roman":"KITANOMATA","code":"05210","old_zip_code":"015  ","pref_kana":"\uff71\uff77\uff80\uff79\uff9d","city_kana":"\uff95\uff98\uff8e\uff9d\uff7c\uff9e\uff6e\uff73\uff7c","town_kana":"\uff77\uff80\uff89\uff8f\uff80"},"0150884":{"zip_code":"0150884","pref_kanji":"\u79cb\u7530\u770c","city_kanji":"\u7531\u5229\u672c\u8358\u5e02","town_kanji":"\u72d0\u68ee","pref_roman":"AKITA KEN","city_roman":"YURIHONJO SHI","town_roman":"KITSUNEMORI","code":"05210","old_zip_code":"015  ","pref_kana":"\uff71\uff77\uff80\uff79\uff9d","city_kana":"\uff95\uff98\uff8e\uff9d\uff7c\uff9e\uff6e\uff73\uff7c","town_kana":"\uff77\uff82\uff88\uff93\uff98"},"0150874":{"zip_code":"0150874","pref_kanji":"\u79cb\u7530\u770c","city_kanji":"\u7531\u5229\u672c\u8358\u5e02","town_kanji":"\u7d66\u4eba\u753a","pref_roman":"AKITA KEN","city_roman":"YURIHONJO SHI","town_roman":"KYUJINCHO","code":"05210","old_zip_code":"015  ","pref_kana":"\uff71\uff77\uff80\uff79\uff9d","city_kana":"\uff95\uff98\uff8e\uff9d\uff7c\uff9e\uff6e\uff73\uff7c","town_kana":"\uff77\uff6d\uff73\uff7c\uff9e\uff9d\uff81\uff6e\uff73"},"0150881":{"zip_code":"0150881","pref_kanji":"\u79cb\u7530\u770c","city_kanji":"\u7531\u5229\u672c\u8358\u5e02","town_kanji":"\u5207\u901a","pref_roman":"AKITA KEN","city_roman":"YURIHONJO SHI","town_roman":"KIRIDOSHI","code":"05210","old_zip_code":"015  ","pref_kana":"\uff71\uff77\uff80\uff79\uff9d","city_kana":"\uff95\uff98\uff8e\uff9d\uff7c\uff9e\uff6e\uff73\uff7c","town_kana":"\uff77\uff98\uff84\uff9e\uff75\uff7c"},"0150045":{"zip_code":"0150045","pref_kanji":"\u79cb\u7530\u770c","city_kanji":"\u7531\u5229\u672c\u8358\u5e02","town_kanji":"\u845b\u6cd5","pref_roman":"AKITA KEN","city_roman":"YURIHONJO SHI","town_roman":"KUZUNORI","code":"05210","old_zip_code":"015  ","pref_kana":"\uff71\uff77\uff80\uff79\uff9d","city_kana":"\uff95\uff98\uff8e\uff9d\uff7c\uff9e\uff6e\uff73\uff7c","town_kana":"\uff78\uff7d\uff9e\uff89\uff98"},"0150302":{"zip_code":"0150302","pref_kanji":"\u79cb\u7530\u770c","city_kanji":"\u7531\u5229\u672c\u8358\u5e02","town_kanji":"\u4e45\u4fdd\u7530","pref_roman":"AKITA KEN","city_roman":"YURIHONJO SHI","town_roman":"KUBOTA","code":"05210","old_zip_code":"01503","pref_kana":"\uff71\uff77\uff80\uff79\uff9d","city_kana":"\uff95\uff98\uff8e\uff9d\uff7c\uff9e\uff6e\uff73\uff7c","town_kana":"\uff78\uff8e\uff9e\uff80"},"0150361":{"zip_code":"0150361","pref_kanji":"\u79cb\u7530\u770c","city_kanji":"\u7531\u5229\u672c\u8358\u5e02","town_kanji":"\u9ed2\u6ca2","pref_roman":"AKITA KEN","city_roman":"YURIHONJO SHI","town_roman":"KUROSAWA","code":"05210","old_zip_code":"01503","pref_kana":"\uff71\uff77\uff80\uff79\uff9d","city_kana":"\uff95\uff98\uff8e\uff9d\uff7c\uff9e\uff6e\uff73\uff7c","town_kana":"\uff78\uff9b\uff7b\uff9c"},"0150883":{"zip_code":"0150883","pref_kanji":"\u79cb\u7530\u770c","city_kanji":"\u7531\u5229\u672c\u8358\u5e02","town_kanji":"\u4e0b\u5730\u30b1\u6ca2","pref_roman":"AKITA KEN","city_roman":"YURIHONJO SHI","town_roman":"GECHIGASAWA","code":"05210","old_zip_code":"015  ","pref_kana":"\uff71\uff77\uff80\uff79\uff9d","city_kana":"\uff95\uff98\uff8e\uff9d\uff7c\uff9e\uff6e\uff73\uff7c","town_kana":"\uff79\uff9e\uff81\uff76\uff9e\uff7b\uff9c"},"0150313":{"zip_code":"0150313","pref_kanji":"\u79cb\u7530\u770c","city_kanji":"\u7531\u5229\u672c\u8358\u5e02","town_kanji":"\u5c0f\u83c5\u91ce","pref_roman":"AKITA KEN","city_roman":"YURIHONJO SHI","town_roman":"KOSUGANO","code":"05210","old_zip_code":"01503","pref_kana":"\uff71\uff77\uff80\uff79\uff9d","city_kana":"\uff95\uff98\uff8e\uff9d\uff7c\uff9e\uff6e\uff73\uff7c","town_kana":"\uff7a\uff7d\uff76\uff9e\uff89"},"0150862":{"zip_code":"0150862","pref_kanji":"\u79cb\u7530\u770c","city_kanji":"\u7531\u5229\u672c\u8358\u5e02","town_kanji":"\u5c0f\u4eba\u753a","pref_roman":"AKITA KEN","city_roman":"YURIHONJO SHI","town_roman":"KOBITOMACHI","code":"05210","old_zip_code":"015  ","pref_kana":"\uff71\uff77\uff80\uff79\uff9d","city_kana":"\uff95\uff98\uff8e\uff9d\uff7c\uff9e\uff6e\uff73\uff7c","town_kana":"\uff7a\uff8b\uff9e\uff84\uff8f\uff81"},"0150891":{"zip_code":"0150891","pref_kanji":"\u79cb\u7530\u770c","city_kanji":"\u7531\u5229\u672c\u8358\u5e02","town_kanji":"\u5c0f\u9632\u30b1\u6ca2","pref_roman":"AKITA KEN","city_roman":"YURIHONJO SHI","town_roman":"KOBOGASAWA","code":"05210","old_zip_code":"015  ","pref_kana":"\uff71\uff77\uff80\uff79\uff9d","city_kana":"\uff95\uff98\uff8e\uff9d\uff7c\uff9e\uff6e\uff73\uff7c","town_kana":"\uff7a\uff8e\uff9e\uff73\uff76\uff9e\uff7b\uff9c"},"0150861":{"zip_code":"0150861","pref_kanji":"\u79cb\u7530\u770c","city_kanji":"\u7531\u5229\u672c\u8358\u5e02","town_kanji":"\u5fa1\u9580","pref_roman":"AKITA KEN","city_roman":"YURIHONJO SHI","town_roman":"GOMON","code":"05210","old_zip_code":"015  ","pref_kana":"\uff71\uff77\uff80\uff79\uff9d","city_kana":"\uff95\uff98\uff8e\uff9d\uff7c\uff9e\uff6e\uff73\uff7c","town_kana":"\uff7a\uff9e\uff93\uff9d"},"0150887":{"zip_code":"0150887","pref_kanji":"\u79cb\u7530\u770c","city_kanji":"\u7531\u5229\u672c\u8358\u5e02","town_kanji":"\u4eca\u91ce\u8c37\u5730","pref_roman":"AKITA KEN","city_roman":"YURIHONJO SHI","town_roman":"KONNOYACHI","code":"05210","old_zip_code":"015  ","pref_kana":"\uff71\uff77\uff80\uff79\uff9d","city_kana":"\uff95\uff98\uff8e\uff9d\uff7c\uff9e\uff6e\uff73\uff7c","town_kana":"\uff7a\uff9d\uff89\uff94\uff81"},"0150821":{"zip_code":"0150821","pref_kanji":"\u79cb\u7530\u770c","city_kanji":"\u7531\u5229\u672c\u8358\u5e02","town_kanji":"\u80b4\u753a","pref_roman":"AKITA KEN","city_roman":"YURIHONJO SHI","town_roman":"SAKANAMACHI","code":"05210","old_zip_code":"015  ","pref_kana":"\uff71\uff77\uff80\uff79\uff9d","city_kana":"\uff95\uff98\uff8e\uff9d\uff7c\uff9e\uff6e\uff73\uff7c","town_kana":"\uff7b\uff76\uff85\uff8f\uff81"},"0150074":{"zip_code":"0150074","pref_kanji":"\u79cb\u7530\u770c","city_kanji":"\u7531\u5229\u672c\u8358\u5e02","town_kanji":"\u685c\u5c0f\u8def","pref_roman":"AKITA KEN","city_roman":"YURIHONJO SHI","town_roman":"SAKURAKOJI","code":"05210","old_zip_code":"015  ","pref_kana":"\uff71\uff77\uff80\uff79\uff9d","city_kana":"\uff95\uff98\uff8e\uff9d\uff7c\uff9e\uff6e\uff73\uff7c","town_kana":"\uff7b\uff78\uff97\uff7a\uff73\uff7c\uff9e"},"0150073":{"zip_code":"0150073","pref_kanji":"\u79cb\u7530\u770c","city_kanji":"\u7531\u5229\u672c\u8358\u5e02","town_kanji":"\u7b39\u9053","pref_roman":"AKITA KEN","city_roman":"YURIHONJO SHI","town_roman":"SASAMICHI","code":"05210","old_zip_code":"015  ","pref_kana":"\uff71\uff77\uff80\uff79\uff9d","city_kana":"\uff95\uff98\uff8e\uff9d\uff7c\uff9e\uff6e\uff73\uff7c","town_kana":"\uff7b\uff7b\uff90\uff81"},"0150889":{"zip_code":"0150889","pref_kanji":"\u79cb\u7530\u770c","city_kanji":"\u7531\u5229\u672c\u8358\u5e02","town_kanji":"\u7802\u7cd6\u7551","pref_roman":"AKITA KEN","city_roman":"YURIHONJO SHI","town_roman":"SATOBATAKE","code":"05210","old_zip_code":"015  ","pref_kana":"\uff71\uff77\uff80\uff79\uff9d","city_kana":"\uff95\uff98\uff8e\uff9d\uff7c\uff9e\uff6e\uff73\uff7c","town_kana":"\uff7b\uff84\uff73\uff8a\uff9e\uff80\uff79"},"0150067":{"zip_code":"0150067","pref_kanji":"\u79cb\u7530\u770c","city_kanji":"\u7531\u5229\u672c\u8358\u5e02","town_kanji":"\u4e09\u6761","pref_roman":"AKITA KEN","city_roman":"YURIHONJO SHI","town_roman":"SANJO","code":"05210","old_zip_code":"015  ","pref_kana":"\uff71\uff77\uff80\uff79\uff9d","city_kana":"\uff95\uff98\uff8e\uff9d\uff7c\uff9e\uff6e\uff73\uff7c","town_kana":"\uff7b\uff9d\uff7c\uff9e\uff6e\uff73"},"0150841":{"zip_code":"0150841","pref_kanji":"\u79cb\u7530\u770c","city_kanji":"\u7531\u5229\u672c\u8358\u5e02","town_kanji":"\u4e0b\u5927\u91ce","pref_roman":"AKITA KEN","city_roman":"YURIHONJO SHI","town_roman":"SHIMOONO","code":"05210","old_zip_code":"015  ","pref_kana":"\uff71\uff77\uff80\uff79\uff9d","city_kana":"\uff95\uff98\uff8e\uff9d\uff7c\uff9e\uff6e\uff73\uff7c","town_kana":"\uff7c\uff93\uff75\uff75\uff89"},"0150832":{"zip_code":"0150832","pref_kanji":"\u79cb\u7530\u770c","city_kanji":"\u7531\u5229\u672c\u8358\u5e02","town_kanji":"\u4e0b\u5ddd\u539f\u4e2d\u5cf6","pref_roman":"AKITA KEN","city_roman":"YURIHONJO SHI","town_roman":"SHIMOKAWAHARANAKAJIMA","code":"05210","old_zip_code":"015  ","pref_kana":"\uff71\uff77\uff80\uff79\uff9d","city_kana":"\uff95\uff98\uff8e\uff9d\uff7c\uff9e\uff6e\uff73\uff7c","town_kana":"\uff7c\uff93\uff76\uff9c\uff8a\uff97\uff85\uff76\uff7c\uff9e\uff8f"},"0150322":{"zip_code":"0150322","pref_kanji":"\u79cb\u7530\u770c","city_kanji":"\u7531\u5229\u672c\u8358\u5e02","town_kanji":"\u65b0\u4e0a\u6761","pref_roman":"AKITA KEN","city_roman":"YURIHONJO SHI","town_roman":"SHINKAMIJO","code":"05210","old_zip_code":"01503","pref_kana":"\uff71\uff77\uff80\uff79\uff9d","city_kana":"\uff95\uff98\uff8e\uff9d\uff7c\uff9e\uff6e\uff73\uff7c","town_kana":"\uff7c\uff9d\uff76\uff90\uff7c\uff9e\uff6e\uff73"},"0150303":{"zip_code":"0150303","pref_kanji":"\u79cb\u7530\u770c","city_kanji":"\u7531\u5229\u672c\u8358\u5e02","town_kanji":"\u9673\u30b1\u68ee","pref_roman":"AKITA KEN","city_roman":"YURIHONJO SHI","town_roman":"JINGAMORI","code":"05210","old_zip_code":"01503","pref_kana":"\uff71\uff77\uff80\uff79\uff9d","city_kana":"\uff95\uff98\uff8e\uff9d\uff7c\uff9e\uff6e\uff73\uff7c","town_kana":"\uff7c\uff9e\uff9d\uff76\uff9e\uff93\uff98"},"0150888":{"zip_code":"0150888","pref_kanji":"\u79cb\u7530\u770c","city_kanji":"\u7531\u5229\u672c\u8358\u5e02","town_kanji":"\u65b0\u7d44\u753a","pref_roman":"AKITA KEN","city_roman":"YURIHONJO SHI","town_roman":"SHINKUMICHO","code":"05210","old_zip_code":"015  ","pref_kana":"\uff71\uff77\uff80\uff79\uff9d","city_kana":"\uff95\uff98\uff8e\uff9d\uff7c\uff9e\uff6e\uff73\uff7c","town_kana":"\uff7c\uff9d\uff78\uff90\uff81\uff6e\uff73"},"0150033":{"zip_code":"0150033","pref_kanji":"\u79cb\u7530\u770c","city_kanji":"\u7531\u5229\u672c\u8358\u5e02","town_kanji":"\u795e\u6ca2","pref_roman":"AKITA KEN","city_roman":"YURIHONJO SHI","town_roman":"SHINNOSAWA","code":"05210","old_zip_code":"015  ","pref_kana":"\uff71\uff77\uff80\uff79\uff9d","city_kana":"\uff95\uff98\uff8e\uff9d\uff7c\uff9e\uff6e\uff73\uff7c","town_kana":"\uff7c\uff9d\uff89\uff7b\uff9c"},"0150869":{"zip_code":"0150869","pref_kanji":"\u79cb\u7530\u770c","city_kanji":"\u7531\u5229\u672c\u8358\u5e02","town_kanji":"\u9663\u5834\u5cb1","pref_roman":"AKITA KEN","city_roman":"YURIHONJO SHI","town_roman":"JIMBADAI","code":"05210","old_zip_code":"015  ","pref_kana":"\uff71\uff77\uff80\uff79\uff9d","city_kana":"\uff95\uff98\uff8e\uff9d\uff7c\uff9e\uff6e\uff73\uff7c","town_kana":"\uff7c\uff9e\uff9d\uff8a\uff9e\uff80\uff9e\uff72"},"0150833":{"zip_code":"0150833","pref_kanji":"\u79cb\u7530\u770c","city_kanji":"\u7531\u5229\u672c\u8358\u5e02","town_kanji":"\u5de3\u7d44","pref_roman":"AKITA KEN","city_roman":"YURIHONJO SHI","town_roman":"SUGUMI","code":"05210","old_zip_code":"015  ","pref_kana":"\uff71\uff77\uff80\uff79\uff9d","city_kana":"\uff95\uff98\uff8e\uff9d\uff7c\uff9e\uff6e\uff73\uff7c","town_kana":"\uff7d\uff78\uff9e\uff90"},"0150875":{"zip_code":"0150875","pref_kanji":"\u79cb\u7530\u770c","city_kanji":"\u7531\u5229\u672c\u8358\u5e02","town_kanji":"\u7802\u5b50\u4e0b","pref_roman":"AKITA KEN","city_roman":"YURIHONJO SHI","town_roman":"SUNAGOSHITA","code":"05210","old_zip_code":"015  ","pref_kana":"\uff71\uff77\uff80\uff79\uff9d","city_kana":"\uff95\uff98\uff8e\uff9d\uff7c\uff9e\uff6e\uff73\uff7c","town_kana":"\uff7d\uff85\uff7a\uff9e\uff7c\uff80"},"0150351":{"zip_code":"0150351","pref_kanji":"\u79cb\u7530\u770c","city_kanji":"\u7531\u5229\u672c\u8358\u5e02","town_kanji":"\u5830\u53e3","pref_roman":"AKITA KEN","city_roman":"YURIHONJO SHI","town_roman":"SEKIGUCHI","code":"05210","old_zip_code":"01503","pref_kana":"\uff71\uff77\uff80\uff79\uff9d","city_kana":"\uff95\uff98\uff8e\uff9d\uff7c\uff9e\uff6e\uff73\uff7c","town_kana":"\uff7e\uff77\uff78\uff9e\uff81"},"0150840":{"zip_code":"0150840","pref_kanji":"\u79cb\u7530\u770c","city_kanji":"\u7531\u5229\u672c\u8358\u5e02","town_kanji":"\u702c\u8d8a\u5834","pref_roman":"AKITA KEN","city_roman":"YURIHONJO SHI","town_roman":"SEGOSHIBA","code":"05210","old_zip_code":"015  ","pref_kana":"\uff71\uff77\uff80\uff79\uff9d","city_kana":"\uff95\uff98\uff8e\uff9d\uff7c\uff9e\uff6e\uff73\uff7c","town_kana":"\uff7e\uff7a\uff9e\uff7c\uff8a\uff9e"},"0150867":{"zip_code":"0150867","pref_kanji":"\u79cb\u7530\u770c","city_kanji":"\u7531\u5229\u672c\u8358\u5e02","town_kanji":"\u5343\u5208","pref_roman":"AKITA KEN","city_roman":"YURIHONJO SHI","town_roman":"SENGARI","code":"05210","old_zip_code":"015  ","pref_kana":"\uff71\uff77\uff80\uff79\uff9d","city_kana":"\uff95\uff98\uff8e\uff9d\uff7c\uff9e\uff6e\uff73\uff7c","town_kana":"\uff7e\uff9d\uff76\uff9e\uff98"},"0150081":{"zip_code":"0150081","pref_kanji":"\u79cb\u7530\u770c","city_kanji":"\u7531\u5229\u672c\u8358\u5e02","town_kanji":"\u96ea\u8eca\u753a","pref_roman":"AKITA KEN","city_roman":"YURIHONJO SHI","town_roman":"SORIMACHI","code":"05210","old_zip_code":"015  ","pref_kana":"\uff71\uff77\uff80\uff79\uff9d","city_kana":"\uff95\uff98\uff8e\uff9d\uff7c\uff9e\uff6e\uff73\uff7c","town_kana":"\uff7f\uff98\uff8f\uff81"},"0150808":{"zip_code":"0150808","pref_kanji":"\u79cb\u7530\u770c","city_kanji":"\u7531\u5229\u672c\u8358\u5e02","town_kanji":"\u5927\u9580","pref_roman":"AKITA KEN","city_roman":"YURIHONJO SHI","town_roman":"DAIMON","code":"05210","old_zip_code":"015  ","pref_kana":"\uff71\uff77\uff80\uff79\uff9d","city_kana":"\uff95\uff98\uff8e\uff9d\uff7c\uff9e\uff6e\uff73\uff7c","town_kana":"\uff80\uff9e\uff72\uff93\uff9d"},"0150083":{"zip_code":"0150083","pref_kanji":"\u79cb\u7530\u770c","city_kanji":"\u7531\u5229\u672c\u8358\u5e02","town_kanji":"\u6edd\u30ce\u6ca2","pref_roman":"AKITA KEN","city_roman":"YURIHONJO SHI","town_roman":"TAKINOSAWA","code":"05210","old_zip_code":"015  ","pref_kana":"\uff71\uff77\uff80\uff79\uff9d","city_kana":"\uff95\uff98\uff8e\uff9d\uff7c\uff9e\uff6e\uff73\uff7c","town_kana":"\uff80\uff77\uff89\uff7b\uff9c"},"0150086":{"zip_code":"0150086","pref_kanji":"\u79cb\u7530\u770c","city_kanji":"\u7531\u5229\u672c\u8358\u5e02","town_kanji":"\u8218","pref_roman":"AKITA KEN","city_roman":"YURIHONJO SHI","town_roman":"TATE","code":"05210","old_zip_code":"015  ","pref_kana":"\uff71\uff77\uff80\uff79\uff9d","city_kana":"\uff95\uff98\uff8e\uff9d\uff7c\uff9e\uff6e\uff73\uff7c","town_kana":"\uff80\uff83"},"0150063":{"zip_code":"0150063","pref_kanji":"\u79cb\u7530\u770c","city_kanji":"\u7531\u5229\u672c\u8358\u5e02","town_kanji":"\u8218\u524d","pref_roman":"AKITA KEN","city_roman":"YURIHONJO SHI","town_roman":"TATEMAE","code":"05210","old_zip_code":"015  ","pref_kana":"\uff71\uff77\uff80\uff79\uff9d","city_kana":"\uff95\uff98\uff8e\uff9d\uff7c\uff9e\uff6e\uff73\uff7c","town_kana":"\uff80\uff83\uff8f\uff74"},"0150804":{"zip_code":"0150804","pref_kanji":"\u79cb\u7530\u770c","city_kanji":"\u7531\u5229\u672c\u8358\u5e02","town_kanji":"\u8c37\u5c71\u5c0f\u8def","pref_roman":"AKITA KEN","city_roman":"YURIHONJO SHI","town_roman":"TANIYAMAKOJI","code":"05210","old_zip_code":"015  ","pref_kana":"\uff71\uff77\uff80\uff79\uff9d","city_kana":"\uff95\uff98\uff8e\uff9d\uff7c\uff9e\uff6e\uff73\uff7c","town_kana":"\uff80\uff86\uff94\uff8f\uff7a\uff73\uff7c\uff9e"},"0150822":{"zip_code":"0150822","pref_kanji":"\u79cb\u7530\u770c","city_kanji":"\u7531\u5229\u672c\u8358\u5e02","town_kanji":"\u7530\u753a","pref_roman":"AKITA KEN","city_roman":"YURIHONJO SHI","town_roman":"TAMACHI","code":"05210","old_zip_code":"015  ","pref_kana":"\uff71\uff77\uff80\uff79\uff9d","city_kana":"\uff95\uff98\uff8e\uff9d\uff7c\uff9e\uff6e\uff73\uff7c","town_kana":"\uff80\uff8f\uff81"},"0150044":{"zip_code":"0150044","pref_kanji":"\u79cb\u7530\u770c","city_kanji":"\u7531\u5229\u672c\u8358\u5e02","town_kanji":"\u7389\u30ce\u6c60","pref_roman":"AKITA KEN","city_roman":"YURIHONJO SHI","town_roman":"TAMANOIKE","code":"05210","old_zip_code":"015  ","pref_kana":"\uff71\uff77\uff80\uff79\uff9d","city_kana":"\uff95\uff98\uff8e\uff9d\uff7c\uff9e\uff6e\uff73\uff7c","town_kana":"\uff80\uff8f\uff89\uff72\uff79"},"0150504":{"zip_code":"0150504","pref_kanji":"\u79cb\u7530\u770c","city_kanji":"\u7531\u5229\u672c\u8358\u5e02","town_kanji":"\u9ce5\u6d77\u753a\u4e0a\u5ddd\u5185","pref_roman":"AKITA KEN","city_roman":"YURIHONJO SHI","town_roman":"CHOKAIMACHI KAMIKAWAUCHI","code":"05210","old_zip_code":"01505","pref_kana":"\uff71\uff77\uff80\uff79\uff9d","city_kana":"\uff95\uff98\uff8e\uff9d\uff7c\uff9e\uff6e\uff73\uff7c","town_kana":"\uff81\uff6e\uff73\uff76\uff72\uff8f\uff81\uff76\uff90\uff76\uff9c\uff73\uff81"},"0150721":{"zip_code":"0150721","pref_kanji":"\u79cb\u7530\u770c","city_kanji":"\u7531\u5229\u672c\u8358\u5e02","town_kanji":"\u9ce5\u6d77\u753a\u4e0a\u7b39\u5b50","pref_roman":"AKITA KEN","city_roman":"YURIHONJO SHI","town_roman":"CHOKAIMACHI KAMIJINEGO","code":"05210","old_zip_code":"01507","pref_kana":"\uff71\uff77\uff80\uff79\uff9d","city_kana":"\uff95\uff98\uff8e\uff9d\uff7c\uff9e\uff6e\uff73\uff7c","town_kana":"\uff81\uff6e\uff73\uff76\uff72\uff8f\uff81\uff76\uff90\uff7c\uff9e\uff88\uff7a\uff9e"},"0150515":{"zip_code":"0150515","pref_kanji":"\u79cb\u7530\u770c","city_kanji":"\u7531\u5229\u672c\u8358\u5e02","town_kanji":"\u9ce5\u6d77\u753a\u4e0a\u76f4\u6839","pref_roman":"AKITA KEN","city_roman":"YURIHONJO SHI","town_roman":"CHOKAIMACHI KAMIHITANE","code":"05210","old_zip_code":"01505","pref_kana":"\uff71\uff77\uff80\uff79\uff9d","city_kana":"\uff95\uff98\uff8e\uff9d\uff7c\uff9e\uff6e\uff73\uff7c","town_kana":"\uff81\uff6e\uff73\uff76\uff72\uff8f\uff81\uff76\uff90\uff8b\uff80\uff88"},"0150503":{"zip_code":"0150503","pref_kanji":"\u79cb\u7530\u770c","city_kanji":"\u7531\u5229\u672c\u8358\u5e02","town_kanji":"\u9ce5\u6d77\u753a\u6817\u6ca2","pref_roman":"AKITA KEN","city_roman":"YURIHONJO SHI","town_roman":"CHOKAIMACHI KURISAWA","code":"05210","old_zip_code":"01505","pref_kana":"\uff71\uff77\uff80\uff79\uff9d","city_kana":"\uff95\uff98\uff8e\uff9d\uff7c\uff9e\uff6e\uff73\uff7c","town_kana":"\uff81\uff6e\uff73\uff76\uff72\uff8f\uff81\uff78\uff98\uff7b\uff9c"},"0150505":{"zip_code":"0150505","pref_kanji":"\u79cb\u7530\u770c","city_kanji":"\u7531\u5229\u672c\u8358\u5e02","town_kanji":"\u9ce5\u6d77\u753a\u5c0f\u5ddd","pref_roman":"AKITA KEN","city_roman":"YURIHONJO SHI","town_roman":"CHOKAIMACHI KOGAWA","code":"05210","old_zip_code":"01505","pref_kana":"\uff71\uff77\uff80\uff79\uff9d","city_kana":"\uff95\uff98\uff8e\uff9d\uff7c\uff9e\uff6e\uff73\uff7c","town_kana":"\uff81\uff6e\uff73\uff76\uff72\uff8f\uff81\uff7a\uff76\uff9e\uff9c"},"0150511":{"zip_code":"0150511","pref_kanji":"\u79cb\u7530\u770c","city_kanji":"\u7531\u5229\u672c\u8358\u5e02","town_kanji":"\u9ce5\u6d77\u753a\u6208\u4e4b\u795e","pref_roman":"AKITA KEN","city_roman":"YURIHONJO SHI","town_roman":"CHOKAIMACHI SAINOKAMI","code":"05210","old_zip_code":"01505","pref_kana":"\uff71\uff77\uff80\uff79\uff9d","city_kana":"\uff95\uff98\uff8e\uff9d\uff7c\uff9e\uff6e\uff73\uff7c","town_kana":"\uff81\uff6e\uff73\uff76\uff72\uff8f\uff81\uff7b\uff72\uff89\uff76\uff90"},"0150512":{"zip_code":"0150512","pref_kanji":"\u79cb\u7530\u770c","city_kanji":"\u7531\u5229\u672c\u8358\u5e02","town_kanji":"\u9ce5\u6d77\u753a\u733f\u5009","pref_roman":"AKITA KEN","city_roman":"YURIHONJO SHI","town_roman":"CHOKAIMACHI SARUKURA","code":"05210","old_zip_code":"01505","pref_kana":"\uff71\uff77\uff80\uff79\uff9d","city_kana":"\uff95\uff98\uff8e\uff9d\uff7c\uff9e\uff6e\uff73\uff7c","town_kana":"\uff81\uff6e\uff73\uff76\uff72\uff8f\uff81\uff7b\uff99\uff78\uff97"},"0150502":{"zip_code":"0150502","pref_kanji":"\u79cb\u7530\u770c","city_kanji":"\u7531\u5229\u672c\u8358\u5e02","town_kanji":"\u9ce5\u6d77\u753a\u4e0b\u5ddd\u5185","pref_roman":"AKITA KEN","city_roman":"YURIHONJO SHI","town_roman":"CHOKAIMACHI SHIMOKAWAUCHI","code":"05210","old_zip_code":"01505","pref_kana":"\uff71\uff77\uff80\uff79\uff9d","city_kana":"\uff95\uff98\uff8e\uff9d\uff7c\uff9e\uff6e\uff73\uff7c","town_kana":"\uff81\uff6e\uff73\uff76\uff72\uff8f\uff81\uff7c\uff93\uff76\uff9c\uff73\uff81"},"0150722":{"zip_code":"0150722","pref_kanji":"\u79cb\u7530\u770c","city_kanji":"\u7531\u5229\u672c\u8358\u5e02","town_kanji":"\u9ce5\u6d77\u753a\u4e0b\u7b39\u5b50","pref_roman":"AKITA KEN","city_roman":"YURIHONJO SHI","town_roman":"CHOKAIMACHI SHIMOJINEGO","code":"05210","old_zip_code":"01507","pref_kana":"\uff71\uff77\uff80\uff79\uff9d","city_kana":"\uff95\uff98\uff8e\uff9d\uff7c\uff9e\uff6e\uff73\uff7c","town_kana":"\uff81\uff6e\uff73\uff76\uff72\uff8f\uff81\uff7c\uff93\uff7c\uff9e\uff88\uff7a\uff9e"},"0150513":{"zip_code":"0150513","pref_kanji":"\u79cb\u7530\u770c","city_kanji":"\u7531\u5229\u672c\u8358\u5e02","town_kanji":"\u9ce5\u6d77\u753a\u4e0b\u76f4\u6839","pref_roman":"AKITA KEN","city_roman":"YURIHONJO SHI","town_roman":"CHOKAIMACHI SHIMOHITANE","code":"05210","old_zip_code":"01505","pref_kana":"\uff71\uff77\uff80\uff79\uff9d","city_kana":"\uff95\uff98\uff8e\uff9d\uff7c\uff9e\uff6e\uff73\uff7c","town_kana":"\uff81\uff6e\uff73\uff76\uff72\uff8f\uff81\uff7c\uff93\uff8b\uff80\uff88"},"0150514":{"zip_code":"0150514","pref_kanji":"\u79cb\u7530\u770c","city_kanji":"\u7531\u5229\u672c\u8358\u5e02","town_kanji":"\u9ce5\u6d77\u753a\u4e2d\u76f4\u6839","pref_roman":"AKITA KEN","city_roman":"YURIHONJO SHI","town_roman":"CHOKAIMACHI NAKAHITANE","code":"05210","old_zip_code":"01505","pref_kana":"\uff71\uff77\uff80\uff79\uff9d","city_kana":"\uff95\uff98\uff8e\uff9d\uff7c\uff9e\uff6e\uff73\uff7c","town_kana":"\uff81\uff6e\uff73\uff76\uff72\uff8f\uff81\uff85\uff76\uff8b\uff80\uff88"},"0150501":{"zip_code":"0150501","pref_kanji":"\u79cb\u7530\u770c","city_kanji":"\u7531\u5229\u672c\u8358\u5e02","town_kanji":"\u9ce5\u6d77\u753a\u4f0f\u898b","pref_roman":"AKITA KEN","city_roman":"YURIHONJO SHI","town_roman":"CHOKAIMACHI FUSHIMI","code":"05210","old_zip_code":"01505","pref_kana":"\uff71\uff77\uff80\uff79\uff9d","city_kana":"\uff95\uff98\uff8e\uff9d\uff7c\uff9e\uff6e\uff73\uff7c","town_kana":"\uff81\uff6e\uff73\uff76\uff72\uff8f\uff81\uff8c\uff7c\uff90"},"0150516":{"zip_code":"0150516","pref_kanji":"\u79cb\u7530\u770c","city_kanji":"\u7531\u5229\u672c\u8358\u5e02","town_kanji":"\u9ce5\u6d77\u753a\u767e\u5b85","pref_roman":"AKITA KEN","city_roman":"YURIHONJO SHI","town_roman":"CHOKAIMACHI MOMOYAKE","code":"05210","old_zip_code":"01505","pref_kana":"\uff71\uff77\uff80\uff79\uff9d","city_kana":"\uff95\uff98\uff8e\uff9d\uff7c\uff9e\uff6e\uff73\uff7c","town_kana":"\uff81\uff6e\uff73\uff76\uff72\uff8f\uff81\uff93\uff93\uff94\uff79"},"0150886":{"zip_code":"0150886","pref_kanji":"\u79cb\u7530\u770c","city_kanji":"\u7531\u5229\u672c\u8358\u5e02","town_kanji":"\u8abf\u7df4\u5834","pref_roman":"AKITA KEN","city_roman":"YURIHONJO SHI","town_roman":"CHOREMBA","code":"05210","old_zip_code":"015  ","pref_kana":"\uff71\uff77\uff80\uff79\uff9d","city_kana":"\uff95\uff98\uff8e\uff9d\uff7c\uff9e\uff6e\uff73\uff7c","town_kana":"\uff81\uff6e\uff73\uff9a\uff9d\uff8a\uff9e"},"0150323":{"zip_code":"0150323","pref_kanji":"\u79cb\u7530\u770c","city_kanji":"\u7531\u5229\u672c\u8358\u5e02","town_kanji":"\u571f\u5009","pref_roman":"AKITA KEN","city_roman":"YURIHONJO SHI","town_roman":"TSUCHIKURA","code":"05210","old_zip_code":"01503","pref_kana":"\uff71\uff77\uff80\uff79\uff9d","city_kana":"\uff95\uff98\uff8e\uff9d\uff7c\uff9e\uff6e\uff73\uff7c","town_kana":"\uff82\uff81\uff78\uff97"},"0150054":{"zip_code":"0150054","pref_kanji":"\u79cb\u7530\u770c","city_kanji":"\u7531\u5229\u672c\u8358\u5e02","town_kanji":"\u571f\u8c37\uff08\u8c37\u5730\uff09","pref_roman":"AKITA KEN","city_roman":"YURIHONJO SHI","town_roman":"TSUCHIYA (YACHI)","code":"05210","old_zip_code":"015  ","pref_kana":"\uff71\uff77\uff80\uff79\uff9d","city_kana":"\uff95\uff98\uff8e\uff9d\uff7c\uff9e\uff6e\uff73\uff7c","town_kana":"\uff82\uff81\uff94(\uff94\uff81)"},"0150055":{"zip_code":"0150055","pref_kanji":"\u79cb\u7530\u770c","city_kanji":"\u7531\u5229\u672c\u8358\u5e02","town_kanji":"\u571f\u8c37\uff08\u305d\u306e\u4ed6\uff09","pref_roman":"AKITA KEN","city_roman":"YURIHONJO SHI","town_roman":"TSUCHIYA(SONOTA)","code":"05210","old_zip_code":"015  ","pref_kana":"\uff71\uff77\uff80\uff79\uff9d","city_kana":"\uff95\uff98\uff8e\uff9d\uff7c\uff9e\uff6e\uff73\uff7c","town_kana":"\uff82\uff81\uff94(\uff7f\uff89\uff80)"},"0150866":{"zip_code":"0150866","pref_kanji":"\u79cb\u7530\u770c","city_kanji":"\u7531\u5229\u672c\u8358\u5e02","town_kanji":"\u5824\u8107","pref_roman":"AKITA KEN","city_roman":"YURIHONJO SHI","town_roman":"TSUTSUMIWAKI","code":"05210","old_zip_code":"015  ","pref_kana":"\uff71\uff77\uff80\uff79\uff9d","city_kana":"\uff95\uff98\uff8e\uff9d\uff7c\uff9e\uff6e\uff73\uff7c","town_kana":"\uff82\uff82\uff90\uff9c\uff77"},"0150873":{"zip_code":"0150873","pref_kanji":"\u79cb\u7530\u770c","city_kanji":"\u7531\u5229\u672c\u8358\u5e02","town_kanji":"\u9db4\u6cbc","pref_roman":"AKITA KEN","city_roman":"YURIHONJO SHI","town_roman":"TSURUNUMA","code":"05210","old_zip_code":"015  ","pref_kana":"\uff71\uff77\uff80\uff79\uff9d","city_kana":"\uff95\uff98\uff8e\uff9d\uff7c\uff9e\uff6e\uff73\uff7c","town_kana":"\uff82\uff99\uff87\uff8f"},"0150842":{"zip_code":"0150842","pref_kanji":"\u79cb\u7530\u770c","city_kanji":"\u7531\u5229\u672c\u8358\u5e02","town_kanji":"\u51fa\u6238\u4e0a\u91ce","pref_roman":"AKITA KEN","city_roman":"YURIHONJO SHI","town_roman":"DETO UENO","code":"05210","old_zip_code":"015  ","pref_kana":"\uff71\uff77\uff80\uff79\uff9d","city_kana":"\uff95\uff98\uff8e\uff9d\uff7c\uff9e\uff6e\uff73\uff7c","town_kana":"\uff83\uff9e\uff84\uff73\uff74\uff89"},"0150837":{"zip_code":"0150837","pref_kanji":"\u79cb\u7530\u770c","city_kanji":"\u7531\u5229\u672c\u8358\u5e02","town_kanji":"\u51fa\u6238\u753a\uff08\u8d64\u6cbc\u4e0b\u9053\uff09","pref_roman":"AKITA KEN","city_roman":"YURIHONJO SHI","town_roman":"DETOMACHI(AKANUMASHITAMICHI)","code":"05210","old_zip_code":"015  ","pref_kana":"\uff71\uff77\uff80\uff79\uff9d","city_kana":"\uff95\uff98\uff8e\uff9d\uff7c\uff9e\uff6e\uff73\uff7c","town_kana":"\uff83\uff9e\uff84\uff8f\uff81(\uff71\uff76\uff87\uff8f\uff7c\uff80\uff90\uff81)"},"0150857":{"zip_code":"0150857","pref_kanji":"\u79cb\u7530\u770c","city_kanji":"\u7531\u5229\u672c\u8358\u5e02","town_kanji":"\u5bfa\u5f8c","pref_roman":"AKITA KEN","city_roman":"YURIHONJO SHI","town_roman":"TERAUSHIRO","code":"05210","old_zip_code":"015  ","pref_kana":"\uff71\uff77\uff80\uff79\uff9d","city_kana":"\uff95\uff98\uff8e\uff9d\uff7c\uff9e\uff6e\uff73\uff7c","town_kana":"\uff83\uff97\uff73\uff7c\uff9b"},"0150061":{"zip_code":"0150061","pref_kanji":"\u79cb\u7530\u770c","city_kanji":"\u7531\u5229\u672c\u8358\u5e02","town_kanji":"\u4e8c\u5341\u516d\u6728","pref_roman":"AKITA KEN","city_roman":"YURIHONJO SHI","town_roman":"TODOROKI","code":"05210","old_zip_code":"015  ","pref_kana":"\uff71\uff77\uff80\uff79\uff9d","city_kana":"\uff95\uff98\uff8e\uff9d\uff7c\uff9e\uff6e\uff73\uff7c","town_kana":"\uff84\uff84\uff9e\uff9b\uff77"},"0150089":{"zip_code":"0150089","pref_kanji":"\u79cb\u7530\u770c","city_kanji":"\u7531\u5229\u672c\u8358\u5e02","town_kanji":"\u9ce5\u7530\u76ee","pref_roman":"AKITA KEN","city_roman":"YURIHONJO SHI","town_roman":"TORITAME","code":"05210","old_zip_code":"015  ","pref_kana":"\uff71\uff77\uff80\uff79\uff9d","city_kana":"\uff95\uff98\uff8e\uff9d\uff7c\uff9e\uff6e\uff73\uff7c","town_kana":"\uff84\uff98\uff80\uff92"},"0150803":{"zip_code":"0150803","pref_kanji":"\u79cb\u7530\u770c","city_kanji":"\u7531\u5229\u672c\u8358\u5e02","town_kanji":"\u4e2d\u7aea\u753a","pref_roman":"AKITA KEN","city_roman":"YURIHONJO SHI","town_roman":"NAKADATEMACHI","code":"05210","old_zip_code":"015  ","pref_kana":"\uff71\uff77\uff80\uff79\uff9d","city_kana":"\uff95\uff98\uff8e\uff9d\uff7c\uff9e\uff6e\uff73\uff7c","town_kana":"\uff85\uff76\uff80\uff9e\uff83\uff8f\uff81"},"0150851":{"zip_code":"0150851","pref_kanji":"\u79cb\u7530\u770c","city_kanji":"\u7531\u5229\u672c\u8358\u5e02","town_kanji":"\u4e2d\u68b5\u5929","pref_roman":"AKITA KEN","city_roman":"YURIHONJO SHI","town_roman":"NAKABONTEN","code":"05210","old_zip_code":"015  ","pref_kana":"\uff71\uff77\uff80\uff79\uff9d","city_kana":"\uff95\uff98\uff8e\uff9d\uff7c\uff9e\uff6e\uff73\uff7c","town_kana":"\uff85\uff76\uff8e\uff9e\uff9d\uff83\uff9d"},"0150817":{"zip_code":"0150817","pref_kanji":"\u79cb\u7530\u770c","city_kanji":"\u7531\u5229\u672c\u8358\u5e02","town_kanji":"\u4e2d\u753a","pref_roman":"AKITA KEN","city_roman":"YURIHONJO SHI","town_roman":"NAKAMACHI","code":"05210","old_zip_code":"015  ","pref_kana":"\uff71\uff77\uff80\uff79\uff9d","city_kana":"\uff95\uff98\uff8e\uff9d\uff7c\uff9e\uff6e\uff73\uff7c","town_kana":"\uff85\uff76\uff8f\uff81"},"0150807":{"zip_code":"0150807","pref_kanji":"\u79cb\u7530\u770c","city_kanji":"\u7531\u5229\u672c\u8358\u5e02","town_kanji":"\u4e2d\u6a2a\u753a","pref_roman":"AKITA KEN","city_roman":"YURIHONJO SHI","town_roman":"NAKAYOKOMACHI","code":"05210","old_zip_code":"015  ","pref_kana":"\uff71\uff77\uff80\uff79\uff9d","city_kana":"\uff95\uff98\uff8e\uff9d\uff7c\uff9e\uff6e\uff73\uff7c","town_kana":"\uff85\uff76\uff96\uff7a\uff8f\uff81"},"0150865":{"zip_code":"0150865","pref_kanji":"\u79cb\u7530\u770c","city_kanji":"\u7531\u5229\u672c\u8358\u5e02","town_kanji":"\u897f\u5927\u936c\u753a","pref_roman":"AKITA KEN","city_roman":"YURIHONJO SHI","town_roman":"NISHIOKUWAMACHI","code":"05210","old_zip_code":"015  ","pref_kana":"\uff71\uff77\uff80\uff79\uff9d","city_kana":"\uff95\uff98\uff8e\uff9d\uff7c\uff9e\uff6e\uff73\uff7c","town_kana":"\uff86\uff7c\uff75\uff75\uff78\uff9c\uff8f\uff81"},"0150882":{"zip_code":"0150882","pref_kanji":"\u79cb\u7530\u770c","city_kanji":"\u7531\u5229\u672c\u8358\u5e02","town_kanji":"\u897f\u5c0f\u4eba\u753a","pref_roman":"AKITA KEN","city_roman":"YURIHONJO SHI","town_roman":"NISHIKOBITOMACHI","code":"05210","old_zip_code":"015  ","pref_kana":"\uff71\uff77\uff80\uff79\uff9d","city_kana":"\uff95\uff98\uff8e\uff9d\uff7c\uff9e\uff6e\uff73\uff7c","town_kana":"\uff86\uff7c\uff7a\uff8b\uff9e\uff84\uff8f\uff81"},"0150352":{"zip_code":"0150352","pref_kanji":"\u79cb\u7530\u770c","city_kanji":"\u7531\u5229\u672c\u8358\u5e02","town_kanji":"\u897f\u6ca2","pref_roman":"AKITA KEN","city_roman":"YURIHONJO SHI","town_roman":"NISHISAWA","code":"05210","old_zip_code":"01503","pref_kana":"\uff71\uff77\uff80\uff79\uff9d","city_kana":"\uff95\uff98\uff8e\uff9d\uff7c\uff9e\uff6e\uff73\uff7c","town_kana":"\uff86\uff7c\uff7b\uff9c"},"0150858":{"zip_code":"0150858","pref_kanji":"\u79cb\u7530\u770c","city_kanji":"\u7531\u5229\u672c\u8358\u5e02","town_kanji":"\u897f\u68b5\u5929","pref_roman":"AKITA KEN","city_roman":"YURIHONJO SHI","town_roman":"NISHIBONTEN","code":"05210","old_zip_code":"015  ","pref_kana":"\uff71\uff77\uff80\uff79\uff9d","city_kana":"\uff95\uff98\uff8e\uff9d\uff7c\uff9e\uff6e\uff73\uff7c","town_kana":"\uff86\uff7c\uff8e\uff9e\uff9d\uff83\uff9d"},"0150855":{"zip_code":"0150855","pref_kanji":"\u79cb\u7530\u770c","city_kanji":"\u7531\u5229\u672c\u8358\u5e02","town_kanji":"\u4e8c\u756a\u5830","pref_roman":"AKITA KEN","city_roman":"YURIHONJO SHI","town_roman":"NIBANZEKI","code":"05210","old_zip_code":"015  ","pref_kana":"\uff71\uff77\uff80\uff79\uff9d","city_kana":"\uff95\uff98\uff8e\uff9d\uff7c\uff9e\uff6e\uff73\uff7c","town_kana":"\uff86\uff8a\uff9e\uff9d\uff7e\uff9e\uff77"},"0150877":{"zip_code":"0150877","pref_kanji":"\u79cb\u7530\u770c","city_kanji":"\u7531\u5229\u672c\u8358\u5e02","town_kanji":"\u6fe1\u6d5c\u5317","pref_roman":"AKITA KEN","city_roman":"YURIHONJO SHI","town_roman":"NUREHAMAKITA","code":"05210","old_zip_code":"015  ","pref_kana":"\uff71\uff77\uff80\uff79\uff9d","city_kana":"\uff95\uff98\uff8e\uff9d\uff7c\uff9e\uff6e\uff73\uff7c","town_kana":"\uff87\uff9a\uff8a\uff8f\uff77\uff80"},"0150052":{"zip_code":"0150052","pref_kanji":"\u79cb\u7530\u770c","city_kanji":"\u7531\u5229\u672c\u8358\u5e02","town_kanji":"\u7551\u8c37","pref_roman":"AKITA KEN","city_roman":"YURIHONJO SHI","town_roman":"HATAYA","code":"05210","old_zip_code":"015  ","pref_kana":"\uff71\uff77\uff80\uff79\uff9d","city_kana":"\uff95\uff98\uff8e\uff9d\uff7c\uff9e\uff6e\uff73\uff7c","town_kana":"\uff8a\uff80\uff94"},"0150835":{"zip_code":"0150835","pref_kanji":"\u79cb\u7530\u770c","city_kanji":"\u7531\u5229\u672c\u8358\u5e02","town_kanji":"\u516b\u5e61\u4e0b","pref_roman":"AKITA KEN","city_roman":"YURIHONJO SHI","town_roman":"HACHIMANSHITA","code":"05210","old_zip_code":"015  ","pref_kana":"\uff71\uff77\uff80\uff79\uff9d","city_kana":"\uff95\uff98\uff8e\uff9d\uff7c\uff9e\uff6e\uff73\uff7c","town_kana":"\uff8a\uff81\uff8f\uff9d\uff7c\uff80"},"0150075":{"zip_code":"0150075","pref_kanji":"\u79cb\u7530\u770c","city_kanji":"\u7531\u5229\u672c\u8358\u5e02","town_kanji":"\u82b1\u7551\u753a","pref_roman":"AKITA KEN","city_roman":"YURIHONJO SHI","town_roman":"HANABATAMACHI","code":"05210","old_zip_code":"015  ","pref_kana":"\uff71\uff77\uff80\uff79\uff9d","city_kana":"\uff95\uff98\uff8e\uff9d\uff7c\uff9e\uff6e\uff73\uff7c","town_kana":"\uff8a\uff85\uff8a\uff9e\uff80\uff8f\uff81"},"0150031":{"zip_code":"0150031","pref_kanji":"\u79cb\u7530\u770c","city_kanji":"\u7531\u5229\u672c\u8358\u5e02","town_kanji":"\u6d5c\u4e09\u5ddd","pref_roman":"AKITA KEN","city_roman":"YURIHONJO SHI","town_roman":"HAMASANKAWA","code":"05210","old_zip_code":"015  ","pref_kana":"\uff71\uff77\uff80\uff79\uff9d","city_kana":"\uff95\uff98\uff8e\uff9d\uff7c\uff9e\uff6e\uff73\uff7c","town_kana":"\uff8a\uff8f\uff7b\uff9d\uff76\uff9c"},"0150827":{"zip_code":"0150827","pref_kanji":"\u79cb\u7530\u770c","city_kanji":"\u7531\u5229\u672c\u8358\u5e02","town_kanji":"\u6d5c\u30ce\u753a","pref_roman":"AKITA KEN","city_roman":"YURIHONJO SHI","town_roman":"HAMANOMACHI","code":"05210","old_zip_code":"015  ","pref_kana":"\uff71\uff77\uff80\uff79\uff9d","city_kana":"\uff95\uff98\uff8e\uff9d\uff7c\uff9e\uff6e\uff73\uff7c","town_kana":"\uff8a\uff8f\uff89\uff8f\uff81"},"0150362":{"zip_code":"0150362","pref_kanji":"\u79cb\u7530\u770c","city_kanji":"\u7531\u5229\u672c\u8358\u5e02","town_kanji":"\u6771\u9b8e\u5ddd","pref_roman":"AKITA KEN","city_roman":"YURIHONJO SHI","town_roman":"HIGASHIAYUKAWA","code":"05210","old_zip_code":"01503","pref_kana":"\uff71\uff77\uff80\uff79\uff9d","city_kana":"\uff95\uff98\uff8e\uff9d\uff7c\uff9e\uff6e\uff73\uff7c","town_kana":"\uff8b\uff76\uff9e\uff7c\uff71\uff95\uff76\uff9c"},"0150314":{"zip_code":"0150314","pref_kanji":"\u79cb\u7530\u770c","city_kanji":"\u7531\u5229\u672c\u8358\u5e02","town_kanji":"\u6771\u4e2d\u6ca2","pref_roman":"AKITA KEN","city_roman":"YURIHONJO SHI","town_roman":"HIGASHINAKAZAWA","code":"05210","old_zip_code":"01503","pref_kana":"\uff71\uff77\uff80\uff79\uff9d","city_kana":"\uff95\uff98\uff8e\uff9d\uff7c\uff9e\uff6e\uff73\uff7c","town_kana":"\uff8b\uff76\uff9e\uff7c\uff85\uff76\uff7b\uff9e\uff9c"},"0150843":{"zip_code":"0150843","pref_kanji":"\u79cb\u7530\u770c","city_kanji":"\u7531\u5229\u672c\u8358\u5e02","town_kanji":"\u6771\u68b5\u5929","pref_roman":"AKITA KEN","city_roman":"YURIHONJO SHI","town_roman":"HIGASHIBONTEN","code":"05210","old_zip_code":"015  ","pref_kana":"\uff71\uff77\uff80\uff79\uff9d","city_kana":"\uff95\uff98\uff8e\uff9d\uff7c\uff9e\uff6e\uff73\uff7c","town_kana":"\uff8b\uff76\uff9e\uff7c\uff8e\uff9e\uff9d\uff83\uff9d"},"0150076":{"zip_code":"0150076","pref_kanji":"\u79cb\u7530\u770c","city_kanji":"\u7531\u5229\u672c\u8358\u5e02","town_kanji":"\u6771\u753a","pref_roman":"AKITA KEN","city_roman":"YURIHONJO SHI","town_roman":"HIGASHIMACHI","code":"05210","old_zip_code":"015  ","pref_kana":"\uff71\uff77\uff80\uff79\uff9d","city_kana":"\uff95\uff98\uff8e\uff9d\uff7c\uff9e\uff6e\uff73\uff7c","town_kana":"\uff8b\uff76\uff9e\uff7c\uff8f\uff81"},"0150211":{"zip_code":"0150211","pref_kanji":"\u79cb\u7530\u770c","city_kanji":"\u7531\u5229\u672c\u8358\u5e02","town_kanji":"\u6771\u7531\u5229\u8001\u65b9","pref_roman":"AKITA KEN","city_roman":"YURIHONJO SHI","town_roman":"HIGASHIYURI OIKATA","code":"05210","old_zip_code":"01502","pref_kana":"\uff71\uff77\uff80\uff79\uff9d","city_kana":"\uff95\uff98\uff8e\uff9d\uff7c\uff9e\uff6e\uff73\uff7c","town_kana":"\uff8b\uff76\uff9e\uff7c\uff95\uff98\uff75\uff72\uff76\uff80"},"0150202":{"zip_code":"0150202","pref_kanji":"\u79cb\u7530\u770c","city_kanji":"\u7531\u5229\u672c\u8358\u5e02","town_kanji":"\u6771\u7531\u5229\u8535","pref_roman":"AKITA KEN","city_roman":"YURIHONJO SHI","town_roman":"HIGASHIYURI KURA","code":"05210","old_zip_code":"01502","pref_kana":"\uff71\uff77\uff80\uff79\uff9d","city_kana":"\uff95\uff98\uff8e\uff9d\uff7c\uff9e\uff6e\uff73\uff7c","town_kana":"\uff8b\uff76\uff9e\uff7c\uff95\uff98\uff78\uff97"},"0150231":{"zip_code":"0150231","pref_kanji":"\u79cb\u7530\u770c","city_kanji":"\u7531\u5229\u672c\u8358\u5e02","town_kanji":"\u6771\u7531\u5229\u9ed2\u6e15","pref_roman":"AKITA KEN","city_roman":"YURIHONJO SHI","town_roman":"HIGASHIYURI KUROBUCHI","code":"05210","old_zip_code":"01502","pref_kana":"\uff71\uff77\uff80\uff79\uff9d","city_kana":"\uff95\uff98\uff8e\uff9d\uff7c\uff9e\uff6e\uff73\uff7c","town_kana":"\uff8b\uff76\uff9e\uff7c\uff95\uff98\uff78\uff9b\uff8c\uff9e\uff81"},"0150241":{"zip_code":"0150241","pref_kanji":"\u79cb\u7530\u770c","city_kanji":"\u7531\u5229\u672c\u8358\u5e02","town_kanji":"\u6771\u7531\u5229\u5bbf","pref_roman":"AKITA KEN","city_roman":"YURIHONJO SHI","town_roman":"HIGASHIYURI SHUKU","code":"05210","old_zip_code":"01502","pref_kana":"\uff71\uff77\uff80\uff79\uff9d","city_kana":"\uff95\uff98\uff8e\uff9d\uff7c\uff9e\uff6e\uff73\uff7c","town_kana":"\uff8b\uff76\uff9e\uff7c\uff95\uff98\uff7c\uff6d\uff78"},"0150242":{"zip_code":"0150242","pref_kanji":"\u79cb\u7530\u770c","city_kanji":"\u7531\u5229\u672c\u8358\u5e02","town_kanji":"\u6771\u7531\u5229\u6749\u68ee","pref_roman":"AKITA KEN","city_roman":"YURIHONJO SHI","town_roman":"HIGASHIYURI SUGIMORI","code":"05210","old_zip_code":"01502","pref_kana":"\uff71\uff77\uff80\uff79\uff9d","city_kana":"\uff95\uff98\uff8e\uff9d\uff7c\uff9e\uff6e\uff73\uff7c","town_kana":"\uff8b\uff76\uff9e\uff7c\uff95\uff98\uff7d\uff77\uff9e\uff93\uff98"},"0150232":{"zip_code":"0150232","pref_kanji":"\u79cb\u7530\u770c","city_kanji":"\u7531\u5229\u672c\u8358\u5e02","town_kanji":"\u6771\u7531\u5229\u7530\u4ee3","pref_roman":"AKITA KEN","city_roman":"YURIHONJO SHI","town_roman":"HIGASHIYURI TASHIRO","code":"05210","old_zip_code":"01502","pref_kana":"\uff71\uff77\uff80\uff79\uff9d","city_kana":"\uff95\uff98\uff8e\uff9d\uff7c\uff9e\uff6e\uff73\uff7c","town_kana":"\uff8b\uff76\uff9e\uff7c\uff95\uff98\uff80\uff7c\uff9b"},"0150221":{"zip_code":"0150221","pref_kanji":"\u79cb\u7530\u770c","city_kanji":"\u7531\u5229\u672c\u8358\u5e02","town_kanji":"\u6771\u7531\u5229\u8218\u5408","pref_roman":"AKITA KEN","city_roman":"YURIHONJO SHI","town_roman":"HIGASHIYURI TATEAI","code":"05210","old_zip_code":"01502","pref_kana":"\uff71\uff77\uff80\uff79\uff9d","city_kana":"\uff95\uff98\uff8e\uff9d\uff7c\uff9e\uff6e\uff73\uff7c","town_kana":"\uff8b\uff76\uff9e\uff7c\uff95\uff98\uff80\uff83\uff71\uff72"},"0150201":{"zip_code":"0150201","pref_kanji":"\u79cb\u7530\u770c","city_kanji":"\u7531\u5229\u672c\u8358\u5e02","town_kanji":"\u6771\u7531\u5229\u6cd5\u5185","pref_roman":"AKITA KEN","city_roman":"YURIHONJO SHI","town_roman":"HIGASHIYURI HONAI","code":"05210","old_zip_code":"01502","pref_kana":"\uff71\uff77\uff80\uff79\uff9d","city_kana":"\uff95\uff98\uff8e\uff9d\uff7c\uff9e\uff6e\uff73\uff7c","town_kana":"\uff8b\uff76\uff9e\uff7c\uff95\uff98\uff8e\uff73\uff85\uff72"},"0150813":{"zip_code":"0150813","pref_kanji":"\u79cb\u7530\u770c","city_kanji":"\u7531\u5229\u672c\u8358\u5e02","town_kanji":"\u65e5\u5f79\u753a","pref_roman":"AKITA KEN","city_roman":"YURIHONJO SHI","town_roman":"HIKIJIMACHI","code":"05210","old_zip_code":"015  ","pref_kana":"\uff71\uff77\uff80\uff79\uff9d","city_kana":"\uff95\uff98\uff8e\uff9d\uff7c\uff9e\uff6e\uff73\uff7c","town_kana":"\uff8b\uff77\uff7c\uff9e\uff8f\uff81"},"0150353":{"zip_code":"0150353","pref_kanji":"\u79cb\u7530\u770c","city_kanji":"\u7531\u5229\u672c\u8358\u5e02","town_kanji":"\u5e73\u77f3","pref_roman":"AKITA KEN","city_roman":"YURIHONJO SHI","town_roman":"HIRAISHI","code":"05210","old_zip_code":"01503","pref_kana":"\uff71\uff77\uff80\uff79\uff9d","city_kana":"\uff95\uff98\uff8e\uff9d\uff7c\uff9e\uff6e\uff73\uff7c","town_kana":"\uff8b\uff97\uff72\uff7c"},"0150053":{"zip_code":"0150053","pref_kanji":"\u79cb\u7530\u770c","city_kanji":"\u7531\u5229\u672c\u8358\u5e02","town_kanji":"\u798f\u5c71","pref_roman":"AKITA KEN","city_roman":"YURIHONJO SHI","town_roman":"FUKUYAMA","code":"05210","old_zip_code":"015  ","pref_kana":"\uff71\uff77\uff80\uff79\uff9d","city_kana":"\uff95\uff98\uff8e\uff9d\uff7c\uff9e\uff6e\uff73\uff7c","town_kana":"\uff8c\uff78\uff94\uff8f"},"0150047":{"zip_code":"0150047","pref_kanji":"\u79cb\u7530\u770c","city_kanji":"\u7531\u5229\u672c\u8358\u5e02","town_kanji":"\u85e4\u5d0e","pref_roman":"AKITA KEN","city_roman":"YURIHONJO SHI","town_roman":"FUJISAKI","code":"05210","old_zip_code":"015  ","pref_kana":"\uff71\uff77\uff80\uff79\uff9d","city_kana":"\uff95\uff98\uff8e\uff9d\uff7c\uff9e\uff6e\uff73\uff7c","town_kana":"\uff8c\uff7c\uff9e\uff7b\uff77"},"0150046":{"zip_code":"0150046","pref_kanji":"\u79cb\u7530\u770c","city_kanji":"\u7531\u5229\u672c\u8358\u5e02","town_kanji":"\u8239\u5ca1","pref_roman":"AKITA KEN","city_roman":"YURIHONJO SHI","town_roman":"FUNAOKA","code":"05210","old_zip_code":"015  ","pref_kana":"\uff71\uff77\uff80\uff79\uff9d","city_kana":"\uff95\uff98\uff8e\uff9d\uff7c\uff9e\uff6e\uff73\uff7c","town_kana":"\uff8c\uff85\uff75\uff76"},"0150890":{"zip_code":"0150890","pref_kanji":"\u79cb\u7530\u770c","city_kanji":"\u7531\u5229\u672c\u8358\u5e02","town_kanji":"\u8239\u30b1\u53f0","pref_roman":"AKITA KEN","city_roman":"YURIHONJO SHI","town_roman":"FUNAGADAI","code":"05210","old_zip_code":"015  ","pref_kana":"\uff71\uff77\uff80\uff79\uff9d","city_kana":"\uff95\uff98\uff8e\uff9d\uff7c\uff9e\uff6e\uff73\uff7c","town_kana":"\uff8c\uff85\uff76\uff9e\uff80\uff9e\uff72"},"0150863":{"zip_code":"0150863","pref_kanji":"\u79cb\u7530\u770c","city_kanji":"\u7531\u5229\u672c\u8358\u5e02","town_kanji":"\u4e0d\u623b\u6ca2","pref_roman":"AKITA KEN","city_roman":"YURIHONJO SHI","town_roman":"FUMODORISAWA","code":"05210","old_zip_code":"015  ","pref_kana":"\uff71\uff77\uff80\uff79\uff9d","city_kana":"\uff95\uff98\uff8e\uff9d\uff7c\uff9e\uff6e\uff73\uff7c","town_kana":"\uff8c\uff93\uff84\uff9e\uff98\uff7b\uff9c"},"0150839":{"zip_code":"0150839","pref_kanji":"\u79cb\u7530\u770c","city_kanji":"\u7531\u5229\u672c\u8358\u5e02","town_kanji":"\u53e4\u5ddd\u7aef","pref_roman":"AKITA KEN","city_roman":"YURIHONJO SHI","town_roman":"FURUKAWABATA","code":"05210","old_zip_code":"015  ","pref_kana":"\uff71\uff77\uff80\uff79\uff9d","city_kana":"\uff95\uff98\uff8e\uff9d\uff7c\uff9e\uff6e\uff73\uff7c","town_kana":"\uff8c\uff99\uff76\uff9c\uff8a\uff9e\uff80"},"0150824":{"zip_code":"0150824","pref_kanji":"\u79cb\u7530\u770c","city_kanji":"\u7531\u5229\u672c\u8358\u5e02","town_kanji":"\u53e4\u96ea\u753a","pref_roman":"AKITA KEN","city_roman":"YURIHONJO SHI","town_roman":"FURUYUKIMACHI","code":"05210","old_zip_code":"015  ","pref_kana":"\uff71\uff77\uff80\uff79\uff9d","city_kana":"\uff95\uff98\uff8e\uff9d\uff7c\uff9e\uff6e\uff73\uff7c","town_kana":"\uff8c\uff99\uff95\uff77\uff8f\uff81"},"0150809":{"zip_code":"0150809","pref_kanji":"\u79cb\u7530\u770c","city_kanji":"\u7531\u5229\u672c\u8358\u5e02","town_kanji":"\u672c\u8358","pref_roman":"AKITA KEN","city_roman":"YURIHONJO SHI","town_roman":"HONJO","code":"05210","old_zip_code":"015  ","pref_kana":"\uff71\uff77\uff80\uff79\uff9d","city_kana":"\uff95\uff98\uff8e\uff9d\uff7c\uff9e\uff6e\uff73\uff7c","town_kana":"\uff8e\uff9d\uff7c\uff9e\uff6e\uff73"},"0150077":{"zip_code":"0150077","pref_kanji":"\u79cb\u7530\u770c","city_kanji":"\u7531\u5229\u672c\u8358\u5e02","town_kanji":"\u672c\u7530\u4ef2\u753a","pref_roman":"AKITA KEN","city_roman":"YURIHONJO SHI","town_roman":"HONTANAKAMACHI","code":"05210","old_zip_code":"015  ","pref_kana":"\uff71\uff77\uff80\uff79\uff9d","city_kana":"\uff95\uff98\uff8e\uff9d\uff7c\uff9e\uff6e\uff73\uff7c","town_kana":"\uff8e\uff9d\uff80\uff85\uff76\uff8f\uff81"},"0150838":{"zip_code":"0150838","pref_kanji":"\u79cb\u7530\u770c","city_kanji":"\u7531\u5229\u672c\u8358\u5e02","town_kanji":"\u68b5\u5929\u8c37\u5730","pref_roman":"AKITA KEN","city_roman":"YURIHONJO SHI","town_roman":"BONTENYACHI","code":"05210","old_zip_code":"015  ","pref_kana":"\uff71\uff77\uff80\uff79\uff9d","city_kana":"\uff95\uff98\uff8e\uff9d\uff7c\uff9e\uff6e\uff73\uff7c","town_kana":"\uff8e\uff9e\uff9d\uff83\uff9d\uff94\uff81"},"0150341":{"zip_code":"0150341","pref_kanji":"\u79cb\u7530\u770c","city_kanji":"\u7531\u5229\u672c\u8358\u5e02","town_kanji":"\u524d\u90f7","pref_roman":"AKITA KEN","city_roman":"YURIHONJO SHI","town_roman":"MAEGO","code":"05210","old_zip_code":"01503","pref_kana":"\uff71\uff77\uff80\uff79\uff9d","city_kana":"\uff95\uff98\uff8e\uff9d\uff7c\uff9e\uff6e\uff73\uff7c","town_kana":"\uff8f\uff74\uff7a\uff9e\uff73"},"0150304":{"zip_code":"0150304","pref_kanji":"\u79cb\u7530\u770c","city_kanji":"\u7531\u5229\u672c\u8358\u5e02","town_kanji":"\u66f2\u6ca2","pref_roman":"AKITA KEN","city_roman":"YURIHONJO SHI","town_roman":"MAGARISAWA","code":"05210","old_zip_code":"01503","pref_kana":"\uff71\uff77\uff80\uff79\uff9d","city_kana":"\uff95\uff98\uff8e\uff9d\uff7c\uff9e\uff6e\uff73\uff7c","town_kana":"\uff8f\uff76\uff9e\uff98\uff7b\uff9c"},"0150363":{"zip_code":"0150363","pref_kanji":"\u79cb\u7530\u770c","city_kanji":"\u7531\u5229\u672c\u8358\u5e02","town_kanji":"\u753a\u6751","pref_roman":"AKITA KEN","city_roman":"YURIHONJO SHI","town_roman":"MACHIMURA","code":"05210","old_zip_code":"01503","pref_kana":"\uff71\uff77\uff80\uff79\uff9d","city_kana":"\uff95\uff98\uff8e\uff9d\uff7c\uff9e\uff6e\uff73\uff7c","town_kana":"\uff8f\uff81\uff91\uff97"},"0150853":{"zip_code":"0150853","pref_kanji":"\u79cb\u7530\u770c","city_kanji":"\u7531\u5229\u672c\u8358\u5e02","town_kanji":"\u677e\u8857\u9053","pref_roman":"AKITA KEN","city_roman":"YURIHONJO SHI","town_roman":"MATSUKAIDO","code":"05210","old_zip_code":"015  ","pref_kana":"\uff71\uff77\uff80\uff79\uff9d","city_kana":"\uff95\uff98\uff8e\uff9d\uff7c\uff9e\uff6e\uff73\uff7c","town_kana":"\uff8f\uff82\uff76\uff72\uff84\uff9e\uff73"},"0150032":{"zip_code":"0150032","pref_kanji":"\u79cb\u7530\u770c","city_kanji":"\u7531\u5229\u672c\u8358\u5e02","town_kanji":"\u677e\u30b1\u5d0e","pref_roman":"AKITA KEN","city_roman":"YURIHONJO SHI","town_roman":"MATSUGASAKI","code":"05210","old_zip_code":"015  ","pref_kana":"\uff71\uff77\uff80\uff79\uff9d","city_kana":"\uff95\uff98\uff8e\uff9d\uff7c\uff9e\uff6e\uff73\uff7c","town_kana":"\uff8f\uff82\uff76\uff9e\uff7b\uff77"},"0150064":{"zip_code":"0150064","pref_kanji":"\u79cb\u7530\u770c","city_kanji":"\u7531\u5229\u672c\u8358\u5e02","town_kanji":"\u4e07\u9858\u5bfa","pref_roman":"AKITA KEN","city_roman":"YURIHONJO SHI","town_roman":"MANGANJI","code":"05210","old_zip_code":"015  ","pref_kana":"\uff71\uff77\uff80\uff79\uff9d","city_kana":"\uff95\uff98\uff8e\uff9d\uff7c\uff9e\uff6e\uff73\uff7c","town_kana":"\uff8f\uff9d\uff76\uff9e\uff9d\uff7c\uff9e"},"0150801":{"zip_code":"0150801","pref_kanji":"\u79cb\u7530\u770c","city_kanji":"\u7531\u5229\u672c\u8358\u5e02","town_kanji":"\u7f8e\u5009\u753a","pref_roman":"AKITA KEN","city_roman":"YURIHONJO SHI","town_roman":"MIKURAMACHI","code":"05210","old_zip_code":"015  ","pref_kana":"\uff71\uff77\uff80\uff79\uff9d","city_kana":"\uff95\uff98\uff8e\uff9d\uff7c\uff9e\uff6e\uff73\uff7c","town_kana":"\uff90\uff78\uff97\uff8f\uff81"},"0150885":{"zip_code":"0150885","pref_kanji":"\u79cb\u7530\u770c","city_kanji":"\u7531\u5229\u672c\u8358\u5e02","town_kanji":"\u6c34\u6797","pref_roman":"AKITA KEN","city_roman":"YURIHONJO SHI","town_roman":"MIZUBAYASHI","code":"05210","old_zip_code":"015  ","pref_kana":"\uff71\uff77\uff80\uff79\uff9d","city_kana":"\uff95\uff98\uff8e\uff9d\uff7c\uff9e\uff6e\uff73\uff7c","town_kana":"\uff90\uff7d\uff9e\uff8a\uff9e\uff94\uff7c"},"0150068":{"zip_code":"0150068","pref_kanji":"\u79cb\u7530\u770c","city_kanji":"\u7531\u5229\u672c\u8358\u5e02","town_kanji":"\u5357\u30ce\u80a1","pref_roman":"AKITA KEN","city_roman":"YURIHONJO SHI","town_roman":"MINAMINOMATA","code":"05210","old_zip_code":"015  ","pref_kana":"\uff71\uff77\uff80\uff79\uff9d","city_kana":"\uff95\uff98\uff8e\uff9d\uff7c\uff9e\uff6e\uff73\uff7c","town_kana":"\uff90\uff85\uff90\uff89\uff8f\uff80"},"0150364":{"zip_code":"0150364","pref_kanji":"\u79cb\u7530\u770c","city_kanji":"\u7531\u5229\u672c\u8358\u5e02","town_kanji":"\u5357\u798f\u7530","pref_roman":"AKITA KEN","city_roman":"YURIHONJO SHI","town_roman":"MINAMIFUKUDA","code":"05210","old_zip_code":"01503","pref_kana":"\uff71\uff77\uff80\uff79\uff9d","city_kana":"\uff95\uff98\uff8e\uff9d\uff7c\uff9e\uff6e\uff73\uff7c","town_kana":"\uff90\uff85\uff90\uff8c\uff78\uff80\uff9e"},"0150043":{"zip_code":"0150043","pref_kanji":"\u79cb\u7530\u770c","city_kanji":"\u7531\u5229\u672c\u8358\u5e02","town_kanji":"\u5bae\u5185","pref_roman":"AKITA KEN","city_roman":"YURIHONJO SHI","town_roman":"MIYAUCHI","code":"05210","old_zip_code":"015  ","pref_kana":"\uff71\uff77\uff80\uff79\uff9d","city_kana":"\uff95\uff98\uff8e\uff9d\uff7c\uff9e\uff6e\uff73\uff7c","town_kana":"\uff90\uff94\uff73\uff81"},"0150082":{"zip_code":"0150082","pref_kanji":"\u79cb\u7530\u770c","city_kanji":"\u7531\u5229\u672c\u8358\u5e02","town_kanji":"\u5bae\u6ca2","pref_roman":"AKITA KEN","city_roman":"YURIHONJO SHI","town_roman":"MIYAZAWA","code":"05210","old_zip_code":"015  ","pref_kana":"\uff71\uff77\uff80\uff79\uff9d","city_kana":"\uff95\uff98\uff8e\uff9d\uff7c\uff9e\uff6e\uff73\uff7c","town_kana":"\uff90\uff94\uff7b\uff9e\uff9c"},"0150332":{"zip_code":"0150332","pref_kanji":"\u79cb\u7530\u770c","city_kanji":"\u7531\u5229\u672c\u8358\u5e02","town_kanji":"\u68ee\u5b50","pref_roman":"AKITA KEN","city_roman":"YURIHONJO SHI","town_roman":"MORIKO","code":"05210","old_zip_code":"01503","pref_kana":"\uff71\uff77\uff80\uff79\uff9d","city_kana":"\uff95\uff98\uff8e\uff9d\uff7c\uff9e\uff6e\uff73\uff7c","town_kana":"\uff93\uff98\uff7a"},"0150088":{"zip_code":"0150088","pref_kanji":"\u79cb\u7530\u770c","city_kanji":"\u7531\u5229\u672c\u8358\u5e02","town_kanji":"\u67f3\u751f","pref_roman":"AKITA KEN","city_roman":"YURIHONJO SHI","town_roman":"YAGYU","code":"05210","old_zip_code":"015  ","pref_kana":"\uff71\uff77\uff80\uff79\uff9d","city_kana":"\uff95\uff98\uff8e\uff9d\uff7c\uff9e\uff6e\uff73\uff7c","town_kana":"\uff94\uff77\uff9e\uff6d\uff73"},"0150041":{"zip_code":"0150041","pref_kanji":"\u79cb\u7530\u770c","city_kanji":"\u7531\u5229\u672c\u8358\u5e02","town_kanji":"\u85ac\u5e2b\u5802","pref_roman":"AKITA KEN","city_roman":"YURIHONJO SHI","town_roman":"YAKUSHIDO","code":"05210","old_zip_code":"015  ","pref_kana":"\uff71\uff77\uff80\uff79\uff9d","city_kana":"\uff95\uff98\uff8e\uff9d\uff7c\uff9e\uff6e\uff73\uff7c","town_kana":"\uff94\uff78\uff7c\uff84\uff9e\uff73"},"0150418":{"zip_code":"0150418","pref_kanji":"\u79cb\u7530\u770c","city_kanji":"\u7531\u5229\u672c\u8358\u5e02","town_kanji":"\u77e2\u5cf6\u753a\u8352\u6ca2","pref_roman":"AKITA KEN","city_roman":"YURIHONJO SHI","town_roman":"YASHIMAMACHI ARASAWA","code":"05210","old_zip_code":"01504","pref_kana":"\uff71\uff77\uff80\uff79\uff9d","city_kana":"\uff95\uff98\uff8e\uff9d\uff7c\uff9e\uff6e\uff73\uff7c","town_kana":"\uff94\uff7c\uff8f\uff8f\uff81\uff71\uff97\uff7b\uff9c"},"0150412":{"zip_code":"0150412","pref_kanji":"\u79cb\u7530\u770c","city_kanji":"\u7531\u5229\u672c\u8358\u5e02","town_kanji":"\u77e2\u5cf6\u753a\u5ddd\u8fba","pref_roman":"AKITA KEN","city_roman":"YURIHONJO SHI","town_roman":"YASHIMAMACHI KAWABE","code":"05210","old_zip_code":"01504","pref_kana":"\uff71\uff77\uff80\uff79\uff9d","city_kana":"\uff95\uff98\uff8e\uff9d\uff7c\uff9e\uff6e\uff73\uff7c","town_kana":"\uff94\uff7c\uff8f\uff8f\uff81\uff76\uff9c\uff8d\uff9e"},"0150413":{"zip_code":"0150413","pref_kanji":"\u79cb\u7530\u770c","city_kanji":"\u7531\u5229\u672c\u8358\u5e02","town_kanji":"\u77e2\u5cf6\u753a\u6728\u5728","pref_roman":"AKITA KEN","city_roman":"YURIHONJO SHI","town_roman":"YASHIMAMACHI KISARA","code":"05210","old_zip_code":"01504","pref_kana":"\uff71\uff77\uff80\uff79\uff9d","city_kana":"\uff95\uff98\uff8e\uff9d\uff7c\uff9e\uff6e\uff73\uff7c","town_kana":"\uff94\uff7c\uff8f\uff8f\uff81\uff77\uff7b\uff97"},"0150416":{"zip_code":"0150416","pref_kanji":"\u79cb\u7530\u770c","city_kanji":"\u7531\u5229\u672c\u8358\u5e02","town_kanji":"\u77e2\u5cf6\u753a\u5742\u4e4b\u4e0b","pref_roman":"AKITA KEN","city_roman":"YURIHONJO SHI","town_roman":"YASHIMAMACHI SAKANOSHITA","code":"05210","old_zip_code":"01504","pref_kana":"\uff71\uff77\uff80\uff79\uff9d","city_kana":"\uff95\uff98\uff8e\uff9d\uff7c\uff9e\uff6e\uff73\uff7c","town_kana":"\uff94\uff7c\uff8f\uff8f\uff81\uff7b\uff76\uff89\uff7c\uff80"},"0150411":{"zip_code":"0150411","pref_kanji":"\u79cb\u7530\u770c","city_kanji":"\u7531\u5229\u672c\u8358\u5e02","town_kanji":"\u77e2\u5cf6\u753a\u57ce\u5185","pref_roman":"AKITA KEN","city_roman":"YURIHONJO SHI","town_roman":"YASHIMAMACHI JONAI","code":"05210","old_zip_code":"01504","pref_kana":"\uff71\uff77\uff80\uff79\uff9d","city_kana":"\uff95\uff98\uff8e\uff9d\uff7c\uff9e\uff6e\uff73\uff7c","town_kana":"\uff94\uff7c\uff8f\uff8f\uff81\uff7c\uff9e\uff6e\uff73\uff85\uff72"},"0150415":{"zip_code":"0150415","pref_kanji":"\u79cb\u7530\u770c","city_kanji":"\u7531\u5229\u672c\u8358\u5e02","town_kanji":"\u77e2\u5cf6\u753a\u65b0\u8358","pref_roman":"AKITA KEN","city_roman":"YURIHONJO SHI","town_roman":"YASHIMAMACHI SHINJO","code":"05210","old_zip_code":"01504","pref_kana":"\uff71\uff77\uff80\uff79\uff9d","city_kana":"\uff95\uff98\uff8e\uff9d\uff7c\uff9e\uff6e\uff73\uff7c","town_kana":"\uff94\uff7c\uff8f\uff8f\uff81\uff7c\uff9d\uff7c\uff9e\uff6e\uff73"},"0150414":{"zip_code":"0150414","pref_kanji":"\u79cb\u7530\u770c","city_kanji":"\u7531\u5229\u672c\u8358\u5e02","town_kanji":"\u77e2\u5cf6\u753a\u7acb\u77f3","pref_roman":"AKITA KEN","city_roman":"YURIHONJO SHI","town_roman":"YASHIMAMACHI TATEISHI","code":"05210","old_zip_code":"01504","pref_kana":"\uff71\uff77\uff80\uff79\uff9d","city_kana":"\uff95\uff98\uff8e\uff9d\uff7c\uff9e\uff6e\uff73\uff7c","town_kana":"\uff94\uff7c\uff8f\uff8f\uff81\uff80\uff83\uff72\uff7c"},"0150403":{"zip_code":"0150403","pref_kanji":"\u79cb\u7530\u770c","city_kanji":"\u7531\u5229\u672c\u8358\u5e02","town_kanji":"\u77e2\u5cf6\u753a\u8218\u753a","pref_roman":"AKITA KEN","city_roman":"YURIHONJO SHI","town_roman":"YASHIMAMACHI TATEMACHI","code":"05210","old_zip_code":"01504","pref_kana":"\uff71\uff77\uff80\uff79\uff9d","city_kana":"\uff95\uff98\uff8e\uff9d\uff7c\uff9e\uff6e\uff73\uff7c","town_kana":"\uff94\uff7c\uff8f\uff8f\uff81\uff80\uff83\uff8f\uff81"},"0150401":{"zip_code":"0150401","pref_kanji":"\u79cb\u7530\u770c","city_kanji":"\u7531\u5229\u672c\u8358\u5e02","town_kanji":"\u77e2\u5cf6\u753a\u7530\u4e2d\u753a","pref_roman":"AKITA KEN","city_roman":"YURIHONJO SHI","town_roman":"YASHIMAMACHI TANAKAMACHI","code":"05210","old_zip_code":"01504","pref_kana":"\uff71\uff77\uff80\uff79\uff9d","city_kana":"\uff95\uff98\uff8e\uff9d\uff7c\uff9e\uff6e\uff73\uff7c","town_kana":"\uff94\uff7c\uff8f\uff8f\uff81\uff80\uff85\uff76\uff8f\uff81"},"0150404":{"zip_code":"0150404","pref_kanji":"\u79cb\u7530\u770c","city_kanji":"\u7531\u5229\u672c\u8358\u5e02","town_kanji":"\u77e2\u5cf6\u753a\u4e03\u65e5\u753a","pref_roman":"AKITA KEN","city_roman":"YURIHONJO SHI","town_roman":"YASHIMAMACHI NANOKAMACHI","code":"05210","old_zip_code":"01504","pref_kana":"\uff71\uff77\uff80\uff79\uff9d","city_kana":"\uff95\uff98\uff8e\uff9d\uff7c\uff9e\uff6e\uff73\uff7c","town_kana":"\uff94\uff7c\uff8f\uff8f\uff81\uff85\uff89\uff76\uff8f\uff81"},"0150417":{"zip_code":"0150417","pref_kanji":"\u79cb\u7530\u770c","city_kanji":"\u7531\u5229\u672c\u8358\u5e02","town_kanji":"\u77e2\u5cf6\u753a\u5143\u753a","pref_roman":"AKITA KEN","city_roman":"YURIHONJO SHI","town_roman":"YASHIMAMACHI MOTOMACHI","code":"05210","old_zip_code":"01504","pref_kana":"\uff71\uff77\uff80\uff79\uff9d","city_kana":"\uff95\uff98\uff8e\uff9d\uff7c\uff9e\uff6e\uff73\uff7c","town_kana":"\uff94\uff7c\uff8f\uff8f\uff81\uff93\uff84\uff8f\uff81"},"0150402":{"zip_code":"0150402","pref_kanji":"\u79cb\u7530\u770c","city_kanji":"\u7531\u5229\u672c\u8358\u5e02","town_kanji":"\u77e2\u5cf6\u753a\u77e2\u5cf6\u753a","pref_roman":"AKITA KEN","city_roman":"YURIHONJO SHI","town_roman":"YASHIMAMACHI YASHIMAMACHI","code":"05210","old_zip_code":"01504","pref_kana":"\uff71\uff77\uff80\uff79\uff9d","city_kana":"\uff95\uff98\uff8e\uff9d\uff7c\uff9e\uff6e\uff73\uff7c","town_kana":"\uff94\uff7c\uff8f\uff8f\uff81\uff94\uff7c\uff8f\uff8f\uff81"},"0150078":{"zip_code":"0150078","pref_kanji":"\u79cb\u7530\u770c","city_kanji":"\u7531\u5229\u672c\u8358\u5e02","town_kanji":"\u8c37\u5730\u753a","pref_roman":"AKITA KEN","city_roman":"YURIHONJO SHI","town_roman":"YACHIMACHI","code":"05210","old_zip_code":"015  ","pref_kana":"\uff71\uff77\uff80\uff79\uff9d","city_kana":"\uff95\uff98\uff8e\uff9d\uff7c\uff9e\uff6e\uff73\uff7c","town_kana":"\uff94\uff81\uff8f\uff81"},"0150243":{"zip_code":"0150243","pref_kanji":"\u79cb\u7530\u770c","city_kanji":"\u7531\u5229\u672c\u8358\u5e02","town_kanji":"\u5c71\u5185\uff08\u4e09\u30c4\u65b9\u68ee\uff09","pref_roman":"AKITA KEN","city_roman":"YURIHONJO SHI","town_roman":"YAMAUCHI (MITSUKATAMORI)","code":"05210","old_zip_code":"01502","pref_kana":"\uff71\uff77\uff80\uff79\uff9d","city_kana":"\uff95\uff98\uff8e\uff9d\uff7c\uff9e\uff6e\uff73\uff7c","town_kana":"\uff94\uff8f\uff73\uff81(\uff90\uff82\uff76\uff80\uff93\uff98)"},"0150092":{"zip_code":"0150092","pref_kanji":"\u79cb\u7530\u770c","city_kanji":"\u7531\u5229\u672c\u8358\u5e02","town_kanji":"\u5c71\u5185\uff08\u305d\u306e\u4ed6\uff09","pref_roman":"AKITA KEN","city_roman":"YURIHONJO SHI","town_roman":"YAMAUCHI(SONOTA)","code":"05210","old_zip_code":"015  ","pref_kana":"\uff71\uff77\uff80\uff79\uff9d","city_kana":"\uff95\uff98\uff8e\uff9d\uff7c\uff9e\uff6e\uff73\uff7c","town_kana":"\uff94\uff8f\uff73\uff81(\uff7f\uff89\uff80)"},"0150025":{"zip_code":"0150025","pref_kanji":"\u79cb\u7530\u770c","city_kanji":"\u7531\u5229\u672c\u8358\u5e02","town_kanji":"\u5c71\u7530","pref_roman":"AKITA KEN","city_roman":"YURIHONJO SHI","town_roman":"YAMADA","code":"05210","old_zip_code":"015  ","pref_kana":"\uff71\uff77\uff80\uff79\uff9d","city_kana":"\uff95\uff98\uff8e\uff9d\uff7c\uff9e\uff6e\uff73\uff7c","town_kana":"\uff94\uff8f\uff80\uff9e"},"0150333":{"zip_code":"0150333","pref_kanji":"\u79cb\u7530\u770c","city_kanji":"\u7531\u5229\u672c\u8358\u5e02","town_kanji":"\u5c71\u672c","pref_roman":"AKITA KEN","city_roman":"YURIHONJO SHI","town_roman":"YAMAMOTO","code":"05210","old_zip_code":"01503","pref_kana":"\uff71\uff77\uff80\uff79\uff9d","city_kana":"\uff95\uff98\uff8e\uff9d\uff7c\uff9e\uff6e\uff73\uff7c","town_kana":"\uff94\uff8f\uff93\uff84"},"0150087":{"zip_code":"0150087","pref_kanji":"\u79cb\u7530\u770c","city_kanji":"\u7531\u5229\u672c\u8358\u5e02","town_kanji":"\u6e6f\u6ca2","pref_roman":"AKITA KEN","city_roman":"YURIHONJO SHI","town_roman":"YUZAWA","code":"05210","old_zip_code":"015  ","pref_kana":"\uff71\uff77\uff80\uff79\uff9d","city_kana":"\uff95\uff98\uff8e\uff9d\uff7c\uff9e\uff6e\uff73\uff7c","town_kana":"\uff95\uff7b\uff9e\uff9c"},"0150324":{"zip_code":"0150324","pref_kanji":"\u79cb\u7530\u770c","city_kanji":"\u7531\u5229\u672c\u8358\u5e02","town_kanji":"\u5409\u6ca2","pref_roman":"AKITA KEN","city_roman":"YURIHONJO SHI","town_roman":"YOSHIZAWA","code":"05210","old_zip_code":"01503","pref_kana":"\uff71\uff77\uff80\uff79\uff9d","city_kana":"\uff95\uff98\uff8e\uff9d\uff7c\uff9e\uff6e\uff73\uff7c","town_kana":"\uff96\uff7c\uff7b\uff9e\uff9c"},"0150815":{"zip_code":"0150815","pref_kanji":"\u79cb\u7530\u770c","city_kanji":"\u7531\u5229\u672c\u8358\u5e02","town_kanji":"\u731f\u5e2b\u753a","pref_roman":"AKITA KEN","city_roman":"YURIHONJO SHI","town_roman":"RYOSHIMACHI","code":"05210","old_zip_code":"015  ","pref_kana":"\uff71\uff77\uff80\uff79\uff9d","city_kana":"\uff95\uff98\uff8e\uff9d\uff7c\uff9e\uff6e\uff73\uff7c","town_kana":"\uff98\uff6e\uff73\uff7c\uff8f\uff81"}}