{"0900000":{"code":"01208","old_zip_code":"090  ","zip_code":"0900000","pref_kana":"\uff8e\uff6f\uff76\uff72\uff84\uff9e\uff73","city_kana":"\uff77\uff80\uff90\uff7c","town_kana":"\uff72\uff76\uff86\uff79\uff72\uff7b\uff72\uff76\uff9e\uff85\uff72\uff8a\uff9e\uff71\uff72","pref_kanji":"\u5317\u6d77\u9053","city_kanji":"\u5317\u898b\u5e02","town_kanji":"\u4ee5\u4e0b\u306b\u63b2\u8f09\u304c\u306a\u3044\u5834\u5408","pref_roman":"HOKKAIDO","city_roman":"KITAMI SHI","town_roman":"IKANIKEISAIGANAIBAAI"},"0900018":{"code":"01208","old_zip_code":"090  ","zip_code":"0900018","pref_kana":"\uff8e\uff6f\uff76\uff72\uff84\uff9e\uff73","city_kana":"\uff77\uff80\uff90\uff7c","town_kana":"\uff71\uff75\uff8a\uff9e\uff81\uff6e\uff73","pref_kanji":"\u5317\u6d77\u9053","city_kanji":"\u5317\u898b\u5e02","town_kanji":"\u9752\u8449\u753a","pref_roman":"HOKKAIDO","city_roman":"KITAMI SHI","town_roman":"AOBACHO"},"0900011":{"code":"01208","old_zip_code":"090  ","zip_code":"0900011","pref_kana":"\uff8e\uff6f\uff76\uff72\uff84\uff9e\uff73","city_kana":"\uff77\uff80\uff90\uff7c","town_kana":"\uff71\uff79\uff8e\uff9e\uff89\uff81\uff6e\uff73","pref_kanji":"\u5317\u6d77\u9053","city_kanji":"\u5317\u898b\u5e02","town_kanji":"\u66d9\u753a","pref_roman":"HOKKAIDO","city_roman":"KITAMI SHI","town_roman":"AKEBONOCHO"},"0900803":{"code":"01208","old_zip_code":"090  ","zip_code":"0900803","pref_kana":"\uff8e\uff6f\uff76\uff72\uff84\uff9e\uff73","city_kana":"\uff77\uff80\uff90\uff7c","town_kana":"\uff71\uff7b\uff8b\uff8f\uff81","pref_kanji":"\u5317\u6d77\u9053","city_kanji":"\u5317\u898b\u5e02","town_kanji":"\u671d\u65e5\u753a","pref_roman":"HOKKAIDO","city_roman":"KITAMI SHI","town_roman":"ASAHIMACHI"},"0900811":{"code":"01208","old_zip_code":"090  ","zip_code":"0900811","pref_kana":"\uff8e\uff6f\uff76\uff72\uff84\uff9e\uff73","city_kana":"\uff77\uff80\uff90\uff7c","town_kana":"\uff72\uff7d\uff9e\uff90\uff81\uff6e\uff73","pref_kanji":"\u5317\u6d77\u9053","city_kanji":"\u5317\u898b\u5e02","town_kanji":"\u6cc9\u753a","pref_roman":"HOKKAIDO","city_roman":"KITAMI SHI","town_roman":"IZUMICHO"},"0900020":{"code":"01208","old_zip_code":"090  ","zip_code":"0900020","pref_kana":"\uff8e\uff6f\uff76\uff72\uff84\uff9e\uff73","city_kana":"\uff77\uff80\uff90\uff7c","town_kana":"\uff75\uff75\uff84\uff9e\uff75\uff98\uff8b\uff76\uff9e\uff7c","pref_kanji":"\u5317\u6d77\u9053","city_kanji":"\u5317\u898b\u5e02","town_kanji":"\u5927\u901a\u6771","pref_roman":"HOKKAIDO","city_roman":"KITAMI SHI","town_roman":"ODORI HIGASHI"},"0900040":{"code":"01208","old_zip_code":"090  ","zip_code":"0900040","pref_kana":"\uff8e\uff6f\uff76\uff72\uff84\uff9e\uff73","city_kana":"\uff77\uff80\uff90\uff7c","town_kana":"\uff75\uff75\uff84\uff9e\uff75\uff98\uff86\uff7c","pref_kanji":"\u5317\u6d77\u9053","city_kanji":"\u5317\u898b\u5e02","town_kanji":"\u5927\u901a\u897f","pref_roman":"HOKKAIDO","city_roman":"KITAMI SHI","town_roman":"ODORI NISHI"},"0900016":{"code":"01208","old_zip_code":"090  ","zip_code":"0900016","pref_kana":"\uff8e\uff6f\uff76\uff72\uff84\uff9e\uff73","city_kana":"\uff77\uff80\uff90\uff7c","town_kana":"\uff75\uff75\uff8f\uff81","pref_kanji":"\u5317\u6d77\u9053","city_kanji":"\u5317\u898b\u5e02","town_kanji":"\u5927\u753a","pref_roman":"HOKKAIDO","city_roman":"KITAMI SHI","town_roman":"OMACHI"},"0900056":{"code":"01208","old_zip_code":"090  ","zip_code":"0900056","pref_kana":"\uff8e\uff6f\uff76\uff72\uff84\uff9e\uff73","city_kana":"\uff77\uff80\uff90\uff7c","town_kana":"\uff75\uff9b\uff7c\uff8f\uff81","pref_kanji":"\u5317\u6d77\u9053","city_kanji":"\u5317\u898b\u5e02","town_kanji":"\u5378\u753a","pref_roman":"HOKKAIDO","city_roman":"KITAMI SHI","town_roman":"OROSHIMACHI"},"0900066":{"code":"01208","old_zip_code":"090  ","zip_code":"0900066","pref_kana":"\uff8e\uff6f\uff76\uff72\uff84\uff9e\uff73","city_kana":"\uff77\uff80\uff90\uff7c","town_kana":"\uff76\uff79\uff9e\uff82\uff81\uff6e\uff73","pref_kanji":"\u5317\u6d77\u9053","city_kanji":"\u5317\u898b\u5e02","town_kanji":"\u82b1\u6708\u753a","pref_roman":"HOKKAIDO","city_roman":"KITAMI SHI","town_roman":"KAGETSUCHO"},"0900053":{"code":"01208","old_zip_code":"090  ","zip_code":"0900053","pref_kana":"\uff8e\uff6f\uff76\uff72\uff84\uff9e\uff73","city_kana":"\uff77\uff80\uff90\uff7c","town_kana":"\uff76\uff82\uff97\uff8f\uff81","pref_kanji":"\u5317\u6d77\u9053","city_kanji":"\u5317\u898b\u5e02","town_kanji":"\u6842\u753a","pref_roman":"HOKKAIDO","city_roman":"KITAMI SHI","town_roman":"KATSURAMACHI"},"0900006":{"code":"01208","old_zip_code":"090  ","zip_code":"0900006","pref_kana":"\uff8e\uff6f\uff76\uff72\uff84\uff9e\uff73","city_kana":"\uff77\uff80\uff90\uff7c","town_kana":"\uff76\uff90\uff86\uff7a\uff9b","pref_kanji":"\u5317\u6d77\u9053","city_kanji":"\u5317\u898b\u5e02","town_kanji":"\u4e0a\u4ec1\u9803","pref_roman":"HOKKAIDO","city_roman":"KITAMI SHI","town_roman":"KAMINIKORO"},"0900821":{"code":"01208","old_zip_code":"090  ","zip_code":"0900821","pref_kana":"\uff8e\uff6f\uff76\uff72\uff84\uff9e\uff73","city_kana":"\uff77\uff80\uff90\uff7c","town_kana":"\uff76\uff9c\uff7f\uff9e\uff74\uff81\uff6e\uff73","pref_kanji":"\u5317\u6d77\u9053","city_kanji":"\u5317\u898b\u5e02","town_kanji":"\u5ddd\u6cbf\u753a","pref_roman":"HOKKAIDO","city_roman":"KITAMI SHI","town_roman":"KAWAZOECHO"},"0900807":{"code":"01208","old_zip_code":"090  ","zip_code":"0900807","pref_kana":"\uff8e\uff6f\uff76\uff72\uff84\uff9e\uff73","city_kana":"\uff77\uff80\uff90\uff7c","town_kana":"\uff76\uff9c\uff8b\uff76\uff9e\uff7c","pref_kanji":"\u5317\u6d77\u9053","city_kanji":"\u5317\u898b\u5e02","town_kanji":"\u5ddd\u6771","pref_roman":"HOKKAIDO","city_roman":"KITAMI SHI","town_roman":"KAWAHIGASHI"},"0900021":{"code":"01208","old_zip_code":"090  ","zip_code":"0900021","pref_kana":"\uff8e\uff6f\uff76\uff72\uff84\uff9e\uff73","city_kana":"\uff77\uff80\uff90\uff7c","town_kana":"\uff77\uff801\uff7c\uff9e\uff6e\uff73\uff8b\uff76\uff9e\uff7c","pref_kanji":"\u5317\u6d77\u9053","city_kanji":"\u5317\u898b\u5e02","town_kanji":"\u5317\u4e00\u6761\u6771","pref_roman":"HOKKAIDO","city_roman":"KITAMI SHI","town_roman":"KITA1-JOHIGASHI"},"0900041":{"code":"01208","old_zip_code":"090  ","zip_code":"0900041","pref_kana":"\uff8e\uff6f\uff76\uff72\uff84\uff9e\uff73","city_kana":"\uff77\uff80\uff90\uff7c","town_kana":"\uff77\uff801\uff7c\uff9e\uff6e\uff73\uff86\uff7c","pref_kanji":"\u5317\u6d77\u9053","city_kanji":"\u5317\u898b\u5e02","town_kanji":"\u5317\u4e00\u6761\u897f","pref_roman":"HOKKAIDO","city_roman":"KITAMI SHI","town_roman":"KITA1-JONISHI"},"0900022":{"code":"01208","old_zip_code":"090  ","zip_code":"0900022","pref_kana":"\uff8e\uff6f\uff76\uff72\uff84\uff9e\uff73","city_kana":"\uff77\uff80\uff90\uff7c","town_kana":"\uff77\uff802\uff7c\uff9e\uff6e\uff73\uff8b\uff76\uff9e\uff7c","pref_kanji":"\u5317\u6d77\u9053","city_kanji":"\u5317\u898b\u5e02","town_kanji":"\u5317\u4e8c\u6761\u6771","pref_roman":"HOKKAIDO","city_roman":"KITAMI SHI","town_roman":"KITA2-JOHIGASHI"},"0900042":{"code":"01208","old_zip_code":"090  ","zip_code":"0900042","pref_kana":"\uff8e\uff6f\uff76\uff72\uff84\uff9e\uff73","city_kana":"\uff77\uff80\uff90\uff7c","town_kana":"\uff77\uff802\uff7c\uff9e\uff6e\uff73\uff86\uff7c","pref_kanji":"\u5317\u6d77\u9053","city_kanji":"\u5317\u898b\u5e02","town_kanji":"\u5317\u4e8c\u6761\u897f","pref_roman":"HOKKAIDO","city_roman":"KITAMI SHI","town_roman":"KITA2-JONISHI"},"0900023":{"code":"01208","old_zip_code":"090  ","zip_code":"0900023","pref_kana":"\uff8e\uff6f\uff76\uff72\uff84\uff9e\uff73","city_kana":"\uff77\uff80\uff90\uff7c","town_kana":"\uff77\uff803\uff7c\uff9e\uff6e\uff73\uff8b\uff76\uff9e\uff7c","pref_kanji":"\u5317\u6d77\u9053","city_kanji":"\u5317\u898b\u5e02","town_kanji":"\u5317\u4e09\u6761\u6771","pref_roman":"HOKKAIDO","city_roman":"KITAMI SHI","town_roman":"KITA3-JOHIGASHI"},"0900043":{"code":"01208","old_zip_code":"090  ","zip_code":"0900043","pref_kana":"\uff8e\uff6f\uff76\uff72\uff84\uff9e\uff73","city_kana":"\uff77\uff80\uff90\uff7c","town_kana":"\uff77\uff803\uff7c\uff9e\uff6e\uff73\uff86\uff7c","pref_kanji":"\u5317\u6d77\u9053","city_kanji":"\u5317\u898b\u5e02","town_kanji":"\u5317\u4e09\u6761\u897f","pref_roman":"HOKKAIDO","city_roman":"KITAMI SHI","town_roman":"KITA3-JONISHI"},"0900024":{"code":"01208","old_zip_code":"090  ","zip_code":"0900024","pref_kana":"\uff8e\uff6f\uff76\uff72\uff84\uff9e\uff73","city_kana":"\uff77\uff80\uff90\uff7c","town_kana":"\uff77\uff804\uff7c\uff9e\uff6e\uff73\uff8b\uff76\uff9e\uff7c","pref_kanji":"\u5317\u6d77\u9053","city_kanji":"\u5317\u898b\u5e02","town_kanji":"\u5317\u56db\u6761\u6771","pref_roman":"HOKKAIDO","city_roman":"KITAMI SHI","town_roman":"KITA4-JOHIGASHI"},"0900044":{"code":"01208","old_zip_code":"090  ","zip_code":"0900044","pref_kana":"\uff8e\uff6f\uff76\uff72\uff84\uff9e\uff73","city_kana":"\uff77\uff80\uff90\uff7c","town_kana":"\uff77\uff804\uff7c\uff9e\uff6e\uff73\uff86\uff7c","pref_kanji":"\u5317\u6d77\u9053","city_kanji":"\u5317\u898b\u5e02","town_kanji":"\u5317\u56db\u6761\u897f","pref_roman":"HOKKAIDO","city_roman":"KITAMI SHI","town_roman":"KITA4-JONISHI"},"0900025":{"code":"01208","old_zip_code":"090  ","zip_code":"0900025","pref_kana":"\uff8e\uff6f\uff76\uff72\uff84\uff9e\uff73","city_kana":"\uff77\uff80\uff90\uff7c","town_kana":"\uff77\uff805\uff7c\uff9e\uff6e\uff73\uff8b\uff76\uff9e\uff7c","pref_kanji":"\u5317\u6d77\u9053","city_kanji":"\u5317\u898b\u5e02","town_kanji":"\u5317\u4e94\u6761\u6771","pref_roman":"HOKKAIDO","city_roman":"KITAMI SHI","town_roman":"KITA5-JOHIGASHI"},"0900045":{"code":"01208","old_zip_code":"090  ","zip_code":"0900045","pref_kana":"\uff8e\uff6f\uff76\uff72\uff84\uff9e\uff73","city_kana":"\uff77\uff80\uff90\uff7c","town_kana":"\uff77\uff805\uff7c\uff9e\uff6e\uff73\uff86\uff7c","pref_kanji":"\u5317\u6d77\u9053","city_kanji":"\u5317\u898b\u5e02","town_kanji":"\u5317\u4e94\u6761\u897f","pref_roman":"HOKKAIDO","city_roman":"KITAMI SHI","town_roman":"KITA5-JONISHI"},"0900026":{"code":"01208","old_zip_code":"090  ","zip_code":"0900026","pref_kana":"\uff8e\uff6f\uff76\uff72\uff84\uff9e\uff73","city_kana":"\uff77\uff80\uff90\uff7c","town_kana":"\uff77\uff806\uff7c\uff9e\uff6e\uff73\uff8b\uff76\uff9e\uff7c","pref_kanji":"\u5317\u6d77\u9053","city_kanji":"\u5317\u898b\u5e02","town_kanji":"\u5317\u516d\u6761\u6771","pref_roman":"HOKKAIDO","city_roman":"KITAMI SHI","town_roman":"KITA6-JOHIGASHI"},"0900046":{"code":"01208","old_zip_code":"090  ","zip_code":"0900046","pref_kana":"\uff8e\uff6f\uff76\uff72\uff84\uff9e\uff73","city_kana":"\uff77\uff80\uff90\uff7c","town_kana":"\uff77\uff806\uff7c\uff9e\uff6e\uff73\uff86\uff7c","pref_kanji":"\u5317\u6d77\u9053","city_kanji":"\u5317\u898b\u5e02","town_kanji":"\u5317\u516d\u6761\u897f","pref_roman":"HOKKAIDO","city_roman":"KITAMI SHI","town_roman":"KITA6-JONISHI"},"0900027":{"code":"01208","old_zip_code":"090  ","zip_code":"0900027","pref_kana":"\uff8e\uff6f\uff76\uff72\uff84\uff9e\uff73","city_kana":"\uff77\uff80\uff90\uff7c","town_kana":"\uff77\uff807\uff7c\uff9e\uff6e\uff73\uff8b\uff76\uff9e\uff7c","pref_kanji":"\u5317\u6d77\u9053","city_kanji":"\u5317\u898b\u5e02","town_kanji":"\u5317\u4e03\u6761\u6771","pref_roman":"HOKKAIDO","city_roman":"KITAMI SHI","town_roman":"KITA7-JOHIGASHI"},"0900047":{"code":"01208","old_zip_code":"090  ","zip_code":"0900047","pref_kana":"\uff8e\uff6f\uff76\uff72\uff84\uff9e\uff73","city_kana":"\uff77\uff80\uff90\uff7c","town_kana":"\uff77\uff807\uff7c\uff9e\uff6e\uff73\uff86\uff7c","pref_kanji":"\u5317\u6d77\u9053","city_kanji":"\u5317\u898b\u5e02","town_kanji":"\u5317\u4e03\u6761\u897f","pref_roman":"HOKKAIDO","city_roman":"KITAMI SHI","town_roman":"KITA7-JONISHI"},"0900028":{"code":"01208","old_zip_code":"090  ","zip_code":"0900028","pref_kana":"\uff8e\uff6f\uff76\uff72\uff84\uff9e\uff73","city_kana":"\uff77\uff80\uff90\uff7c","town_kana":"\uff77\uff808\uff7c\uff9e\uff6e\uff73\uff8b\uff76\uff9e\uff7c","pref_kanji":"\u5317\u6d77\u9053","city_kanji":"\u5317\u898b\u5e02","town_kanji":"\u5317\u516b\u6761\u6771","pref_roman":"HOKKAIDO","city_roman":"KITAMI SHI","town_roman":"KITA8-JOHIGASHI"},"0900048":{"code":"01208","old_zip_code":"090  ","zip_code":"0900048","pref_kana":"\uff8e\uff6f\uff76\uff72\uff84\uff9e\uff73","city_kana":"\uff77\uff80\uff90\uff7c","town_kana":"\uff77\uff808\uff7c\uff9e\uff6e\uff73\uff86\uff7c","pref_kanji":"\u5317\u6d77\u9053","city_kanji":"\u5317\u898b\u5e02","town_kanji":"\u5317\u516b\u6761\u897f","pref_roman":"HOKKAIDO","city_roman":"KITAMI SHI","town_roman":"KITA8-JONISHI"},"0900029":{"code":"01208","old_zip_code":"090  ","zip_code":"0900029","pref_kana":"\uff8e\uff6f\uff76\uff72\uff84\uff9e\uff73","city_kana":"\uff77\uff80\uff90\uff7c","town_kana":"\uff77\uff809\uff7c\uff9e\uff6e\uff73\uff8b\uff76\uff9e\uff7c","pref_kanji":"\u5317\u6d77\u9053","city_kanji":"\u5317\u898b\u5e02","town_kanji":"\u5317\u4e5d\u6761\u6771","pref_roman":"HOKKAIDO","city_roman":"KITAMI SHI","town_roman":"KITA9-JOHIGASHI"},"0900030":{"code":"01208","old_zip_code":"090  ","zip_code":"0900030","pref_kana":"\uff8e\uff6f\uff76\uff72\uff84\uff9e\uff73","city_kana":"\uff77\uff80\uff90\uff7c","town_kana":"\uff77\uff8010\uff7c\uff9e\uff6e\uff73\uff8b\uff76\uff9e\uff7c","pref_kanji":"\u5317\u6d77\u9053","city_kanji":"\u5317\u898b\u5e02","town_kanji":"\u5317\u5341\u6761\u6771","pref_roman":"HOKKAIDO","city_roman":"KITAMI SHI","town_roman":"KITA10-JOHIGASHI"},"0900031":{"code":"01208","old_zip_code":"090  ","zip_code":"0900031","pref_kana":"\uff8e\uff6f\uff76\uff72\uff84\uff9e\uff73","city_kana":"\uff77\uff80\uff90\uff7c","town_kana":"\uff77\uff8011\uff7c\uff9e\uff6e\uff73\uff8b\uff76\uff9e\uff7c","pref_kanji":"\u5317\u6d77\u9053","city_kanji":"\u5317\u898b\u5e02","town_kanji":"\u5317\u5341\u4e00\u6761\u6771","pref_roman":"HOKKAIDO","city_roman":"KITAMI SHI","town_roman":"KITA11-JOHIGASHI"},"0900063":{"code":"01208","old_zip_code":"090  ","zip_code":"0900063","pref_kana":"\uff8e\uff6f\uff76\uff72\uff84\uff9e\uff73","city_kana":"\uff77\uff80\uff90\uff7c","town_kana":"\uff77\uff96\uff90\uff81\uff6e\uff73","pref_kanji":"\u5317\u6d77\u9053","city_kanji":"\u5317\u898b\u5e02","town_kanji":"\u6e05\u898b\u753a","pref_roman":"HOKKAIDO","city_roman":"KITAMI SHI","town_roman":"KIYOMICHO"},"0900001":{"code":"01208","old_zip_code":"090  ","zip_code":"0900001","pref_kana":"\uff8e\uff6f\uff76\uff72\uff84\uff9e\uff73","city_kana":"\uff77\uff80\uff90\uff7c","town_kana":"\uff7a\uff72\uff7d\uff9e\uff90","pref_kanji":"\u5317\u6d77\u9053","city_kanji":"\u5317\u898b\u5e02","town_kanji":"\u5c0f\u6cc9","pref_roman":"HOKKAIDO","city_roman":"KITAMI SHI","town_roman":"KOIZUMI"},"0900051":{"code":"01208","old_zip_code":"090  ","zip_code":"0900051","pref_kana":"\uff8e\uff6f\uff76\uff72\uff84\uff9e\uff73","city_kana":"\uff77\uff80\uff90\uff7c","town_kana":"\uff7a\uff73\uff74\uff72\uff8b\uff76\uff9e\uff7c\uff8f\uff81","pref_kanji":"\u5317\u6d77\u9053","city_kanji":"\u5317\u898b\u5e02","town_kanji":"\u9ad8\u6804\u6771\u753a","pref_roman":"HOKKAIDO","city_roman":"KITAMI SHI","town_roman":"KOEI HIGASHIMACHI"},"0900058":{"code":"01208","old_zip_code":"090  ","zip_code":"0900058","pref_kana":"\uff8e\uff6f\uff76\uff72\uff84\uff9e\uff73","city_kana":"\uff77\uff80\uff90\uff7c","town_kana":"\uff7a\uff73\uff74\uff72\uff86\uff7c\uff8f\uff81","pref_kanji":"\u5317\u6d77\u9053","city_kanji":"\u5317\u898b\u5e02","town_kanji":"\u9ad8\u6804\u897f\u753a","pref_roman":"HOKKAIDO","city_roman":"KITAMI SHI","town_roman":"KOEI NISHIMACHI"},"0900015":{"code":"01208","old_zip_code":"090  ","zip_code":"0900015","pref_kana":"\uff8e\uff6f\uff76\uff72\uff84\uff9e\uff73","city_kana":"\uff77\uff80\uff90\uff7c","town_kana":"\uff7a\uff73\uff74\uff9d\uff81\uff6e\uff73","pref_kanji":"\u5317\u6d77\u9053","city_kanji":"\u5317\u898b\u5e02","town_kanji":"\u516c\u5712\u753a","pref_roman":"HOKKAIDO","city_roman":"KITAMI SHI","town_roman":"KOENCHO"},"0900835":{"code":"01208","old_zip_code":"090  ","zip_code":"0900835","pref_kana":"\uff8e\uff6f\uff76\uff72\uff84\uff9e\uff73","city_kana":"\uff77\uff80\uff90\uff7c","town_kana":"\uff7a\uff73\uff7e\uff72\uff81\uff6e\uff73","pref_kanji":"\u5317\u6d77\u9053","city_kanji":"\u5317\u898b\u5e02","town_kanji":"\u5149\u897f\u753a","pref_roman":"HOKKAIDO","city_roman":"KITAMI SHI","town_roman":"KOSEICHO"},"0900823":{"code":"01208","old_zip_code":"090  ","zip_code":"0900823","pref_kana":"\uff8e\uff6f\uff76\uff72\uff84\uff9e\uff73","city_kana":"\uff77\uff80\uff90\uff7c","town_kana":"\uff7a\uff73\uff92\uff72\uff81\uff6e\uff73","pref_kanji":"\u5317\u6d77\u9053","city_kanji":"\u5317\u898b\u5e02","town_kanji":"\u5e83\u660e\u753a","pref_roman":"HOKKAIDO","city_roman":"KITAMI SHI","town_roman":"KOMEICHO"},"0900814":{"code":"01208","old_zip_code":"090  ","zip_code":"0900814","pref_kana":"\uff8e\uff6f\uff76\uff72\uff84\uff9e\uff73","city_kana":"\uff77\uff80\uff90\uff7c","town_kana":"\uff7a\uff73\uff96\uff73\uff81\uff6e\uff73","pref_kanji":"\u5317\u6d77\u9053","city_kanji":"\u5317\u898b\u5e02","town_kanji":"\u5149\u8449\u753a","pref_roman":"HOKKAIDO","city_roman":"KITAMI SHI","town_roman":"KOYOCHO"},"0900065":{"code":"01208","old_zip_code":"090  ","zip_code":"0900065","pref_kana":"\uff8e\uff6f\uff76\uff72\uff84\uff9e\uff73","city_kana":"\uff77\uff80\uff90\uff7c","town_kana":"\uff7a\uff84\uff8c\uff9e\uff77\uff81\uff6e\uff73","pref_kanji":"\u5317\u6d77\u9053","city_kanji":"\u5317\u898b\u5e02","town_kanji":"\u5bff\u753a","pref_roman":"HOKKAIDO","city_roman":"KITAMI SHI","town_roman":"KOTOBUKICHO"},"0900036":{"code":"01208","old_zip_code":"090  ","zip_code":"0900036","pref_kana":"\uff8e\uff6f\uff76\uff72\uff84\uff9e\uff73","city_kana":"\uff77\uff80\uff90\uff7c","town_kana":"\uff7b\uff72\uff9c\uff72\uff81\uff6e\uff73","pref_kanji":"\u5317\u6d77\u9053","city_kanji":"\u5317\u898b\u5e02","town_kanji":"\u5e78\u753a","pref_roman":"HOKKAIDO","city_roman":"KITAMI SHI","town_roman":"SAIWAICHO"},"0900832":{"code":"01208","old_zip_code":"090  ","zip_code":"0900832","pref_kana":"\uff8e\uff6f\uff76\uff72\uff84\uff9e\uff73","city_kana":"\uff77\uff80\uff90\uff7c","town_kana":"\uff7b\uff76\uff74\uff8f\uff81","pref_kanji":"\u5317\u6d77\u9053","city_kanji":"\u5317\u898b\u5e02","town_kanji":"\u6804\u753a","pref_roman":"HOKKAIDO","city_roman":"KITAMI SHI","town_roman":"SAKAEMACHI"},"0900804":{"code":"01208","old_zip_code":"090  ","zip_code":"0900804","pref_kana":"\uff8e\uff6f\uff76\uff72\uff84\uff9e\uff73","city_kana":"\uff77\uff80\uff90\uff7c","town_kana":"\uff7b\uff78\uff97\uff8f\uff81","pref_kanji":"\u5317\u6d77\u9053","city_kanji":"\u5317\u898b\u5e02","town_kanji":"\u685c\u753a","pref_roman":"HOKKAIDO","city_roman":"KITAMI SHI","town_roman":"SAKURAMACHI"},"0900019":{"code":"01208","old_zip_code":"090  ","zip_code":"0900019","pref_kana":"\uff8e\uff6f\uff76\uff72\uff84\uff9e\uff73","city_kana":"\uff77\uff80\uff90\uff7c","town_kana":"\uff7b\uff9d\uff97\uff78\uff81\uff6e\uff73","pref_kanji":"\u5317\u6d77\u9053","city_kanji":"\u5317\u898b\u5e02","town_kanji":"\u4e09\u697d\u753a","pref_roman":"HOKKAIDO","city_roman":"KITAMI SHI","town_roman":"SANRAKUCHO"},"0900801":{"code":"01208","old_zip_code":"090  ","zip_code":"0900801","pref_kana":"\uff8e\uff6f\uff76\uff72\uff84\uff9e\uff73","city_kana":"\uff77\uff80\uff90\uff7c","town_kana":"\uff7c\uff6d\uff9d\uff7a\uff73\uff81\uff6e\uff73","pref_kanji":"\u5317\u6d77\u9053","city_kanji":"\u5317\u898b\u5e02","town_kanji":"\u6625\u5149\u753a","pref_roman":"HOKKAIDO","city_roman":"KITAMI SHI","town_roman":"SHUNKOCHO"},"0900002":{"code":"01208","old_zip_code":"090  ","zip_code":"0900002","pref_kana":"\uff8e\uff6f\uff76\uff72\uff84\uff9e\uff73","city_kana":"\uff77\uff80\uff90\uff7c","town_kana":"\uff7c\uff6e\uff73\uff9c","pref_kanji":"\u5317\u6d77\u9053","city_kanji":"\u5317\u898b\u5e02","town_kanji":"\u662d\u548c","pref_roman":"HOKKAIDO","city_roman":"KITAMI SHI","town_roman":"SHOWA"},"0900815":{"code":"01208","old_zip_code":"090  ","zip_code":"0900815","pref_kana":"\uff8e\uff6f\uff76\uff72\uff84\uff9e\uff73","city_kana":"\uff77\uff80\uff90\uff7c","town_kana":"\uff7c\uff9d\uff7e\uff72\uff81\uff6e\uff73","pref_kanji":"\u5317\u6d77\u9053","city_kanji":"\u5317\u898b\u5e02","town_kanji":"\u65b0\u751f\u753a","pref_roman":"HOKKAIDO","city_roman":"KITAMI SHI","town_roman":"SHINSEICHO"},"0900826":{"code":"01208","old_zip_code":"090  ","zip_code":"0900826","pref_kana":"\uff8e\uff6f\uff76\uff72\uff84\uff9e\uff73","city_kana":"\uff77\uff80\uff90\uff7c","town_kana":"\uff7d\uff74\uff8b\uff9b\uff81\uff6e\uff73","pref_kanji":"\u5317\u6d77\u9053","city_kanji":"\u5317\u898b\u5e02","town_kanji":"\u672b\u5e83\u753a","pref_roman":"HOKKAIDO","city_roman":"KITAMI SHI","town_roman":"SUEHIROCHO"},"0900805":{"code":"01208","old_zip_code":"090  ","zip_code":"0900805","pref_kana":"\uff8e\uff6f\uff76\uff72\uff84\uff9e\uff73","city_kana":"\uff77\uff80\uff90\uff7c","town_kana":"\uff7e\uff72\uff79\uff9e\uff82\uff81\uff6e\uff73","pref_kanji":"\u5317\u6d77\u9053","city_kanji":"\u5317\u898b\u5e02","town_kanji":"\u6e05\u6708\u753a","pref_roman":"HOKKAIDO","city_roman":"KITAMI SHI","town_roman":"SEIGETSUCHO"},"0900008":{"code":"01208","old_zip_code":"090  ","zip_code":"0900008","pref_kana":"\uff8e\uff6f\uff76\uff72\uff84\uff9e\uff73","city_kana":"\uff77\uff80\uff90\uff7c","town_kana":"\uff80\uff72\uff7c\uff6e\uff73","pref_kanji":"\u5317\u6d77\u9053","city_kanji":"\u5317\u898b\u5e02","town_kanji":"\u5927\u6b63","pref_roman":"HOKKAIDO","city_roman":"KITAMI SHI","town_roman":"TAISHO"},"0900017":{"code":"01208","old_zip_code":"090  ","zip_code":"0900017","pref_kana":"\uff8e\uff6f\uff76\uff72\uff84\uff9e\uff73","city_kana":"\uff77\uff80\uff90\uff7c","town_kana":"\uff80\uff76\uff7b\uff7a\uff9e\uff81\uff6e\uff73","pref_kanji":"\u5317\u6d77\u9053","city_kanji":"\u5317\u898b\u5e02","town_kanji":"\u9ad8\u7802\u753a","pref_roman":"HOKKAIDO","city_roman":"KITAMI SHI","town_roman":"TAKASAGOCHO"},"0900802":{"code":"01208","old_zip_code":"090  ","zip_code":"0900802","pref_kana":"\uff8e\uff6f\uff76\uff72\uff84\uff9e\uff73","city_kana":"\uff77\uff80\uff90\uff7c","town_kana":"\uff80\uff8a\uff9e\uff80\uff81\uff6e\uff73","pref_kanji":"\u5317\u6d77\u9053","city_kanji":"\u5317\u898b\u5e02","town_kanji":"\u7530\u7aef\u753a","pref_roman":"HOKKAIDO","city_roman":"KITAMI SHI","town_roman":"TABATACHO"},"0900034":{"code":"01208","old_zip_code":"090  ","zip_code":"0900034","pref_kana":"\uff8e\uff6f\uff76\uff72\uff84\uff9e\uff73","city_kana":"\uff77\uff80\uff90\uff7c","town_kana":"\uff81\uff6d\uff73\uff75\uff73\uff81\uff6e\uff73","pref_kanji":"\u5317\u6d77\u9053","city_kanji":"\u5317\u898b\u5e02","town_kanji":"\u4e2d\u592e\u753a","pref_roman":"HOKKAIDO","city_roman":"KITAMI SHI","town_roman":"CHUOCHO"},"0900837":{"code":"01208","old_zip_code":"090  ","zip_code":"0900837","pref_kana":"\uff8e\uff6f\uff76\uff72\uff84\uff9e\uff73","city_kana":"\uff77\uff80\uff90\uff7c","town_kana":"\uff81\uff6d\uff73\uff75\uff73\uff90\uff9c","pref_kanji":"\u5317\u6d77\u9053","city_kanji":"\u5317\u898b\u5e02","town_kanji":"\u4e2d\u592e\u4e09\u8f2a","pref_roman":"HOKKAIDO","city_roman":"KITAMI SHI","town_roman":"CHUOMIWA"},"0900061":{"code":"01208","old_zip_code":"090  ","zip_code":"0900061","pref_kana":"\uff8e\uff6f\uff76\uff72\uff84\uff9e\uff73","city_kana":"\uff77\uff80\uff90\uff7c","town_kana":"\uff84\uff73\uff98\uff6e\uff73\uff81\uff6e\uff73","pref_kanji":"\u5317\u6d77\u9053","city_kanji":"\u5317\u898b\u5e02","town_kanji":"\u6771\u9675\u753a","pref_roman":"HOKKAIDO","city_roman":"KITAMI SHI","town_roman":"TORYOCHO"},"0900817":{"code":"01208","old_zip_code":"090  ","zip_code":"0900817","pref_kana":"\uff8e\uff6f\uff76\uff72\uff84\uff9e\uff73","city_kana":"\uff77\uff80\uff90\uff7c","town_kana":"\uff84\uff77\uff9c\uff81\uff6e\uff73","pref_kanji":"\u5317\u6d77\u9053","city_kanji":"\u5317\u898b\u5e02","town_kanji":"\u5e38\u76e4\u753a","pref_roman":"HOKKAIDO","city_roman":"KITAMI SHI","town_roman":"TOKIWACHO"},"0900833":{"code":"01208","old_zip_code":"090  ","zip_code":"0900833","pref_kana":"\uff8e\uff6f\uff76\uff72\uff84\uff9e\uff73","city_kana":"\uff77\uff80\uff90\uff7c","town_kana":"\uff84\uff9d\uff83\uff9e\uff9d\uff8b\uff76\uff9e\uff7c\uff8f\uff81","pref_kanji":"\u5317\u6d77\u9053","city_kanji":"\u5317\u898b\u5e02","town_kanji":"\u3068\u3093\u7530\u6771\u753a","pref_roman":"HOKKAIDO","city_roman":"KITAMI SHI","town_roman":"TONDEN HIGASHIMACHI"},"0900834":{"code":"01208","old_zip_code":"090  ","zip_code":"0900834","pref_kana":"\uff8e\uff6f\uff76\uff72\uff84\uff9e\uff73","city_kana":"\uff77\uff80\uff90\uff7c","town_kana":"\uff84\uff9d\uff83\uff9e\uff9d\uff86\uff7c\uff8f\uff81","pref_kanji":"\u5317\u6d77\u9053","city_kanji":"\u5317\u898b\u5e02","town_kanji":"\u3068\u3093\u7530\u897f\u753a","pref_roman":"HOKKAIDO","city_roman":"KITAMI SHI","town_roman":"TONDEN NISHIMACHI"},"0900813":{"code":"01208","old_zip_code":"090  ","zip_code":"0900813","pref_kana":"\uff8e\uff6f\uff76\uff72\uff84\uff9e\uff73","city_kana":"\uff77\uff80\uff90\uff7c","town_kana":"\uff85\uff76\uff89\uff7c\uff8f\uff81\uff6e\uff73","pref_kanji":"\u5317\u6d77\u9053","city_kanji":"\u5317\u898b\u5e02","town_kanji":"\u4e2d\u30ce\u5cf6\u753a","pref_roman":"HOKKAIDO","city_roman":"KITAMI SHI","town_roman":"NAKANOSHIMACHO"},"0900012":{"code":"01208","old_zip_code":"090  ","zip_code":"0900012","pref_kana":"\uff8e\uff6f\uff76\uff72\uff84\uff9e\uff73","city_kana":"\uff77\uff80\uff90\uff7c","town_kana":"\uff85\uff90\uff77\uff81\uff6e\uff73","pref_kanji":"\u5317\u6d77\u9053","city_kanji":"\u5317\u898b\u5e02","town_kanji":"\u4e26\u6728\u753a","pref_roman":"HOKKAIDO","city_roman":"KITAMI SHI","town_roman":"NAMIKICHO"},"0900003":{"code":"01208","old_zip_code":"090  ","zip_code":"0900003","pref_kana":"\uff8e\uff6f\uff76\uff72\uff84\uff9e\uff73","city_kana":"\uff77\uff80\uff90\uff7c","town_kana":"\uff86\uff7a\uff9b\uff81\uff6e\uff73","pref_kanji":"\u5317\u6d77\u9053","city_kanji":"\u5317\u898b\u5e02","town_kanji":"\u4ec1\u9803\u753a","pref_roman":"HOKKAIDO","city_roman":"KITAMI SHI","town_roman":"NIKOROCHO"},"0900827":{"code":"01208","old_zip_code":"090  ","zip_code":"0900827","pref_kana":"\uff8e\uff6f\uff76\uff72\uff84\uff9e\uff73","city_kana":"\uff77\uff80\uff90\uff7c","town_kana":"\uff86\uff7c\uff77\uff81\uff6e\uff73","pref_kanji":"\u5317\u6d77\u9053","city_kanji":"\u5317\u898b\u5e02","town_kanji":"\u9326\u753a","pref_roman":"HOKKAIDO","city_roman":"KITAMI SHI","town_roman":"NISHIKICHO"},"0900831":{"code":"01208","old_zip_code":"090  ","zip_code":"0900831","pref_kana":"\uff8e\uff6f\uff76\uff72\uff84\uff9e\uff73","city_kana":"\uff77\uff80\uff90\uff7c","town_kana":"\uff86\uff7c\uff84\uff90\uff81\uff6e\uff73","pref_kanji":"\u5317\u6d77\u9053","city_kanji":"\u5317\u898b\u5e02","town_kanji":"\u897f\u5bcc\u753a","pref_roman":"HOKKAIDO","city_roman":"KITAMI SHI","town_roman":"NISHITOMICHO"},"0900838":{"code":"01208","old_zip_code":"090  ","zip_code":"0900838","pref_kana":"\uff8e\uff6f\uff76\uff72\uff84\uff9e\uff73","city_kana":"\uff77\uff80\uff90\uff7c","town_kana":"\uff86\uff7c\uff90\uff9c","pref_kanji":"\u5317\u6d77\u9053","city_kanji":"\u5317\u898b\u5e02","town_kanji":"\u897f\u4e09\u8f2a","pref_roman":"HOKKAIDO","city_roman":"KITAMI SHI","town_roman":"NISHIMIWA"},"0900013":{"code":"01208","old_zip_code":"090  ","zip_code":"0900013","pref_kana":"\uff8e\uff6f\uff76\uff72\uff84\uff9e\uff73","city_kana":"\uff77\uff80\uff90\uff7c","town_kana":"\uff8a\uff78\uff96\uff73\uff81\uff6e\uff73","pref_kanji":"\u5317\u6d77\u9053","city_kanji":"\u5317\u898b\u5e02","town_kanji":"\u67cf\u967d\u753a","pref_roman":"HOKKAIDO","city_roman":"KITAMI SHI","town_roman":"HAKUYOCHO"},"0900816":{"code":"01208","old_zip_code":"090  ","zip_code":"0900816","pref_kana":"\uff8e\uff6f\uff76\uff72\uff84\uff9e\uff73","city_kana":"\uff77\uff80\uff90\uff7c","town_kana":"\uff8a\uff85\uff7f\uff9e\uff89\uff81\uff6e\uff73","pref_kanji":"\u5317\u6d77\u9053","city_kanji":"\u5317\u898b\u5e02","town_kanji":"\u82b1\u5712\u753a","pref_roman":"HOKKAIDO","city_roman":"KITAMI SHI","town_roman":"HANAZONOCHO"},"0900033":{"code":"01208","old_zip_code":"090  ","zip_code":"0900033","pref_kana":"\uff8e\uff6f\uff76\uff72\uff84\uff9e\uff73","city_kana":"\uff77\uff80\uff90\uff7c","town_kana":"\uff8a\uff9e\uff9d\uff8a\uff9e\uff81\uff6e\uff73","pref_kanji":"\u5317\u6d77\u9053","city_kanji":"\u5317\u898b\u5e02","town_kanji":"\u756a\u5834\u753a","pref_roman":"HOKKAIDO","city_roman":"KITAMI SHI","town_roman":"BAMBACHO"},"0900836":{"code":"01208","old_zip_code":"090  ","zip_code":"0900836","pref_kana":"\uff8e\uff6f\uff76\uff72\uff84\uff9e\uff73","city_kana":"\uff77\uff80\uff90\uff7c","town_kana":"\uff8b\uff76\uff9e\uff7c\uff90\uff9c","pref_kanji":"\u5317\u6d77\u9053","city_kanji":"\u5317\u898b\u5e02","town_kanji":"\u6771\u4e09\u8f2a","pref_roman":"HOKKAIDO","city_roman":"KITAMI SHI","town_roman":"HIGASHIMIWA"},"0900810":{"code":"01208","old_zip_code":"090  ","zip_code":"0900810","pref_kana":"\uff8e\uff6f\uff76\uff72\uff84\uff9e\uff73","city_kana":"\uff77\uff80\uff90\uff7c","town_kana":"\uff8b\uff76\uff98\uff89","pref_kanji":"\u5317\u6d77\u9053","city_kanji":"\u5317\u898b\u5e02","town_kanji":"\u3072\u304b\u308a\u91ce","pref_roman":"HOKKAIDO","city_roman":"KITAMI SHI","town_roman":"HIKARINO"},"0900054":{"code":"01208","old_zip_code":"090  ","zip_code":"0900054","pref_kana":"\uff8e\uff6f\uff76\uff72\uff84\uff9e\uff73","city_kana":"\uff77\uff80\uff90\uff7c","town_kana":"\uff8c\uff80\uff8a\uff9e\uff81\uff6e\uff73","pref_kanji":"\u5317\u6d77\u9053","city_kanji":"\u5317\u898b\u5e02","town_kanji":"\u53cc\u8449\u753a","pref_roman":"HOKKAIDO","city_roman":"KITAMI SHI","town_roman":"FUTABACHO"},"0900014":{"code":"01208","old_zip_code":"090  ","zip_code":"0900014","pref_kana":"\uff8e\uff6f\uff76\uff72\uff84\uff9e\uff73","city_kana":"\uff77\uff80\uff90\uff7c","town_kana":"\uff8c\uff9e\uff9d\uff77\uff6e\uff73\uff81\uff6e\uff73","pref_kanji":"\u5317\u6d77\u9053","city_kanji":"\u5317\u898b\u5e02","town_kanji":"\u6587\u4eac\u753a","pref_roman":"HOKKAIDO","city_roman":"KITAMI SHI","town_roman":"BUNKYOCHO"},"0900822":{"code":"01208","old_zip_code":"090  ","zip_code":"0900822","pref_kana":"\uff8e\uff6f\uff76\uff72\uff84\uff9e\uff73","city_kana":"\uff77\uff80\uff90\uff7c","town_kana":"\uff8e\uff78\uff75\uff73\uff81\uff6e\uff73","pref_kanji":"\u5317\u6d77\u9053","city_kanji":"\u5317\u898b\u5e02","town_kanji":"\u5317\u592e\u753a","pref_roman":"HOKKAIDO","city_roman":"KITAMI SHI","town_roman":"HOKUOCHO"},"0900052":{"code":"01208","old_zip_code":"090  ","zip_code":"0900052","pref_kana":"\uff8e\uff6f\uff76\uff72\uff84\uff9e\uff73","city_kana":"\uff77\uff80\uff90\uff7c","town_kana":"\uff8e\uff78\uff7c\uff9d\uff81\uff6e\uff73","pref_kanji":"\u5317\u6d77\u9053","city_kanji":"\u5317\u898b\u5e02","town_kanji":"\u5317\u9032\u753a","pref_roman":"HOKKAIDO","city_roman":"KITAMI SHI","town_roman":"HOKUSHINCHO"},"0900035":{"code":"01208","old_zip_code":"090  ","zip_code":"0900035","pref_kana":"\uff8e\uff6f\uff76\uff72\uff84\uff9e\uff73","city_kana":"\uff77\uff80\uff90\uff7c","town_kana":"\uff8e\uff78\uff84\uff81\uff6e\uff73","pref_kanji":"\u5317\u6d77\u9053","city_kanji":"\u5317\u898b\u5e02","town_kanji":"\u5317\u6597\u753a","pref_roman":"HOKKAIDO","city_roman":"KITAMI SHI","town_roman":"HOKUTOCHO"},"0900004":{"code":"01208","old_zip_code":"090  ","zip_code":"0900004","pref_kana":"\uff8e\uff6f\uff76\uff72\uff84\uff9e\uff73","city_kana":"\uff77\uff80\uff90\uff7c","town_kana":"\uff8e\uff78\uff96\uff73","pref_kanji":"\u5317\u6d77\u9053","city_kanji":"\u5317\u898b\u5e02","town_kanji":"\u5317\u967d","pref_roman":"HOKKAIDO","city_roman":"KITAMI SHI","town_roman":"HOKUYO"},"0900824":{"code":"01208","old_zip_code":"090  ","zip_code":"0900824","pref_kana":"\uff8e\uff6f\uff76\uff72\uff84\uff9e\uff73","city_kana":"\uff77\uff80\uff90\uff7c","town_kana":"\uff8e\uff6f\uff7a\uff73","pref_kanji":"\u5317\u6d77\u9053","city_kanji":"\u5317\u898b\u5e02","town_kanji":"\u5317\u5149","pref_roman":"HOKKAIDO","city_roman":"KITAMI SHI","town_roman":"HOKKO"},"0900007":{"code":"01208","old_zip_code":"090  ","zip_code":"0900007","pref_kana":"\uff8e\uff6f\uff76\uff72\uff84\uff9e\uff73","city_kana":"\uff77\uff80\uff90\uff7c","town_kana":"\uff90\uff7b\uff84","pref_kanji":"\u5317\u6d77\u9053","city_kanji":"\u5317\u898b\u5e02","town_kanji":"\u7f8e\u91cc","pref_roman":"HOKKAIDO","city_roman":"KITAMI SHI","town_roman":"MISATO"},"0900032":{"code":"01208","old_zip_code":"090  ","zip_code":"0900032","pref_kana":"\uff8e\uff6f\uff76\uff72\uff84\uff9e\uff73","city_kana":"\uff77\uff80\uff90\uff7c","town_kana":"\uff90\uff7d\uff90\uff81\uff6e\uff73","pref_kanji":"\u5317\u6d77\u9053","city_kanji":"\u5317\u898b\u5e02","town_kanji":"\u4e09\u4f4f\u753a","pref_roman":"HOKKAIDO","city_roman":"KITAMI SHI","town_roman":"MISUMICHO"},"0900067":{"code":"01208","old_zip_code":"090  ","zip_code":"0900067","pref_kana":"\uff8e\uff6f\uff76\uff72\uff84\uff9e\uff73","city_kana":"\uff77\uff80\uff90\uff7c","town_kana":"\uff90\uff84\uff9e\uff98\uff76\uff9e\uff75\uff76","pref_kanji":"\u5317\u6d77\u9053","city_kanji":"\u5317\u898b\u5e02","town_kanji":"\u7dd1\u30b1\u4e18","pref_roman":"HOKKAIDO","city_roman":"KITAMI SHI","town_roman":"MIDORIGAOKA"},"0900055":{"code":"01208","old_zip_code":"090  ","zip_code":"0900055","pref_kana":"\uff8e\uff6f\uff76\uff72\uff84\uff9e\uff73","city_kana":"\uff77\uff80\uff90\uff7c","town_kana":"\uff90\uff84\uff9e\uff98\uff8f\uff81","pref_kanji":"\u5317\u6d77\u9053","city_kanji":"\u5317\u898b\u5e02","town_kanji":"\u7dd1\u753a","pref_roman":"HOKKAIDO","city_roman":"KITAMI SHI","town_roman":"MIDORIMACHI"},"0900812":{"code":"01208","old_zip_code":"090  ","zip_code":"0900812","pref_kana":"\uff8e\uff6f\uff76\uff72\uff84\uff9e\uff73","city_kana":"\uff77\uff80\uff90\uff7c","town_kana":"\uff90\uff85\uff90\uff85\uff76\uff8f\uff81","pref_kanji":"\u5317\u6d77\u9053","city_kanji":"\u5317\u898b\u5e02","town_kanji":"\u5357\u4ef2\u753a","pref_roman":"HOKKAIDO","city_roman":"KITAMI SHI","town_roman":"MINAMINAKAMACHI"},"0900806":{"code":"01208","old_zip_code":"090  ","zip_code":"0900806","pref_kana":"\uff8e\uff6f\uff76\uff72\uff84\uff9e\uff73","city_kana":"\uff77\uff80\uff90\uff7c","town_kana":"\uff90\uff85\uff90\uff8f\uff81","pref_kanji":"\u5317\u6d77\u9053","city_kanji":"\u5317\u898b\u5e02","town_kanji":"\u5357\u753a","pref_roman":"HOKKAIDO","city_roman":"KITAMI SHI","town_roman":"MINAMIMACHI"},"0900070":{"code":"01208","old_zip_code":"090  ","zip_code":"0900070","pref_kana":"\uff8e\uff6f\uff76\uff72\uff84\uff9e\uff73","city_kana":"\uff77\uff80\uff90\uff7c","town_kana":"\uff90\uff94\uff8f\uff81\uff6e\uff73\uff86\uff7c","pref_kanji":"\u5317\u6d77\u9053","city_kanji":"\u5317\u898b\u5e02","town_kanji":"\u7f8e\u5c71\u753a\u897f","pref_roman":"HOKKAIDO","city_roman":"KITAMI SHI","town_roman":"MIYAMACHONISHI"},"0900069":{"code":"01208","old_zip_code":"090  ","zip_code":"0900069","pref_kana":"\uff8e\uff6f\uff76\uff72\uff84\uff9e\uff73","city_kana":"\uff77\uff80\uff90\uff7c","town_kana":"\uff90\uff94\uff8f\uff81\uff6e\uff73\uff8b\uff76\uff9e\uff7c","pref_kanji":"\u5317\u6d77\u9053","city_kanji":"\u5317\u898b\u5e02","town_kanji":"\u7f8e\u5c71\u753a\u6771","pref_roman":"HOKKAIDO","city_roman":"KITAMI SHI","town_roman":"MIYAMACHOHIGASHI"},"0900068":{"code":"01208","old_zip_code":"090  ","zip_code":"0900068","pref_kana":"\uff8e\uff6f\uff76\uff72\uff84\uff9e\uff73","city_kana":"\uff77\uff80\uff90\uff7c","town_kana":"\uff90\uff94\uff8f\uff81\uff6e\uff73\uff90\uff85\uff90","pref_kanji":"\u5317\u6d77\u9053","city_kanji":"\u5317\u898b\u5e02","town_kanji":"\u7f8e\u5c71\u753a\u5357","pref_roman":"HOKKAIDO","city_roman":"KITAMI SHI","town_roman":"MIYAMACHOMINAMI"},"0900064":{"code":"01208","old_zip_code":"090  ","zip_code":"0900064","pref_kana":"\uff8e\uff6f\uff76\uff72\uff84\uff9e\uff73","city_kana":"\uff77\uff80\uff90\uff7c","town_kana":"\uff90\uff96\uff7c\uff81\uff6e\uff73","pref_kanji":"\u5317\u6d77\u9053","city_kanji":"\u5317\u898b\u5e02","town_kanji":"\u7f8e\u82b3\u753a","pref_roman":"HOKKAIDO","city_roman":"KITAMI SHI","town_roman":"MIYOSHICHO"},"0900825":{"code":"01208","old_zip_code":"090  ","zip_code":"0900825","pref_kana":"\uff8e\uff6f\uff76\uff72\uff84\uff9e\uff73","city_kana":"\uff77\uff80\uff90\uff7c","town_kana":"\uff91\uff76\uff76\uff9e\uff9c\uff81\uff6e\uff73","pref_kanji":"\u5317\u6d77\u9053","city_kanji":"\u5317\u898b\u5e02","town_kanji":"\u7121\u52a0\u5ddd\u753a","pref_roman":"HOKKAIDO","city_roman":"KITAMI SHI","town_roman":"MUKAGAWACHO"},"0900818":{"code":"01208","old_zip_code":"090  ","zip_code":"0900818","pref_kana":"\uff8e\uff6f\uff76\uff72\uff84\uff9e\uff73","city_kana":"\uff77\uff80\uff90\uff7c","town_kana":"\uff93\uff84\uff8f\uff81","pref_kanji":"\u5317\u6d77\u9053","city_kanji":"\u5317\u898b\u5e02","town_kanji":"\u672c\u753a","pref_roman":"HOKKAIDO","city_roman":"KITAMI SHI","town_roman":"MOTOMACHI"},"0900037":{"code":"01208","old_zip_code":"090  ","zip_code":"0900037","pref_kana":"\uff8e\uff6f\uff76\uff72\uff84\uff9e\uff73","city_kana":"\uff77\uff80\uff90\uff7c","town_kana":"\uff94\uff8f\uff7c\uff80\uff81\uff6e\uff73","pref_kanji":"\u5317\u6d77\u9053","city_kanji":"\u5317\u898b\u5e02","town_kanji":"\u5c71\u4e0b\u753a","pref_roman":"HOKKAIDO","city_roman":"KITAMI SHI","town_roman":"YAMASHITACHO"},"0900005":{"code":"01208","old_zip_code":"090  ","zip_code":"0900005","pref_kana":"\uff8e\uff6f\uff76\uff72\uff84\uff9e\uff73","city_kana":"\uff77\uff80\uff90\uff7c","town_kana":"\uff94\uff8f\uff84","pref_kanji":"\u5317\u6d77\u9053","city_kanji":"\u5317\u898b\u5e02","town_kanji":"\u5927\u548c","pref_roman":"HOKKAIDO","city_roman":"KITAMI SHI","town_roman":"YAMATO"},"0900057":{"code":"01208","old_zip_code":"090  ","zip_code":"0900057","pref_kana":"\uff8e\uff6f\uff76\uff72\uff84\uff9e\uff73","city_kana":"\uff77\uff80\uff90\uff7c","town_kana":"\uff9c\uff76\uff8a\uff9e","pref_kanji":"\u5317\u6d77\u9053","city_kanji":"\u5317\u898b\u5e02","town_kanji":"\u82e5\u8449","pref_roman":"HOKKAIDO","city_roman":"KITAMI SHI","town_roman":"WAKABA"},"0900808":{"code":"01208","old_zip_code":"090  ","zip_code":"0900808","pref_kana":"\uff8e\uff6f\uff76\uff72\uff84\uff9e\uff73","city_kana":"\uff77\uff80\uff90\uff7c","town_kana":"\uff9c\uff76\uff8f\uff82","pref_kanji":"\u5317\u6d77\u9053","city_kanji":"\u5317\u898b\u5e02","town_kanji":"\u82e5\u677e","pref_roman":"HOKKAIDO","city_roman":"KITAMI SHI","town_roman":"WAKAMATSU"}}