{"8115100":{"zip_code":"8115100","pref_kanji":"\u9577\u5d0e\u770c","city_kanji":"\u58f1\u5c90\u5e02","town_kanji":"\u4ee5\u4e0b\u306b\u63b2\u8f09\u304c\u306a\u3044\u5834\u5408","pref_roman":"NAGASAKI KEN","city_roman":"IKI SHI","town_roman":"IKANIKEISAIGANAIBAAI","code":"42210","old_zip_code":"81151","pref_kana":"\uff85\uff76\uff9e\uff7b\uff77\uff79\uff9d","city_kana":"\uff72\uff77\uff7c","town_kana":"\uff72\uff76\uff86\uff79\uff72\uff7b\uff72\uff76\uff9e\uff85\uff72\uff8a\uff9e\uff71\uff72"},"8115301":{"zip_code":"8115301","pref_kanji":"\u9577\u5d0e\u770c","city_kanji":"\u58f1\u5c90\u5e02","town_kanji":"\u82a6\u8fba\u753a\u82a6\u8fba\u6d66","pref_roman":"NAGASAKI KEN","city_roman":"IKI SHI","town_roman":"ASHIBECHO ASHIBEURA","code":"42210","old_zip_code":"81153","pref_kana":"\uff85\uff76\uff9e\uff7b\uff77\uff79\uff9d","city_kana":"\uff72\uff77\uff7c","town_kana":"\uff71\uff7c\uff8d\uff9e\uff81\uff6e\uff73\uff71\uff7c\uff8d\uff9e\uff73\uff97"},"8115733":{"zip_code":"8115733","pref_kanji":"\u9577\u5d0e\u770c","city_kanji":"\u58f1\u5c90\u5e02","town_kanji":"\u82a6\u8fba\u753a\u56fd\u5206\u5ddd\u8fce\u89e6","pref_roman":"NAGASAKI KEN","city_roman":"IKI SHI","town_roman":"ASHIBECHO KOKUBUKAWAMUKAEFURE","code":"42210","old_zip_code":"81157","pref_kana":"\uff85\uff76\uff9e\uff7b\uff77\uff79\uff9d","city_kana":"\uff72\uff77\uff7c","town_kana":"\uff71\uff7c\uff8d\uff9e\uff81\uff6e\uff73\uff7a\uff78\uff8c\uff9e\uff76\uff9c\uff91\uff76\uff74\uff8c\uff9a"},"8115731":{"zip_code":"8115731","pref_kanji":"\u9577\u5d0e\u770c","city_kanji":"\u58f1\u5c90\u5e02","town_kanji":"\u82a6\u8fba\u753a\u56fd\u5206\u5f53\u7530\u89e6","pref_roman":"NAGASAKI KEN","city_roman":"IKI SHI","town_roman":"ASHIBECHO KOKUBUTODAFURE","code":"42210","old_zip_code":"81157","pref_kana":"\uff85\uff76\uff9e\uff7b\uff77\uff79\uff9d","city_kana":"\uff72\uff77\uff7c","town_kana":"\uff71\uff7c\uff8d\uff9e\uff81\uff6e\uff73\uff7a\uff78\uff8c\uff9e\uff84\uff73\uff80\uff9e\uff8c\uff9a"},"8115732":{"zip_code":"8115732","pref_kanji":"\u9577\u5d0e\u770c","city_kanji":"\u58f1\u5c90\u5e02","town_kanji":"\u82a6\u8fba\u753a\u56fd\u5206\u6771\u89e6","pref_roman":"NAGASAKI KEN","city_roman":"IKI SHI","town_roman":"ASHIBECHO KOKUBUHIGASHIFURE","code":"42210","old_zip_code":"81157","pref_kana":"\uff85\uff76\uff9e\uff7b\uff77\uff79\uff9d","city_kana":"\uff72\uff77\uff7c","town_kana":"\uff71\uff7c\uff8d\uff9e\uff81\uff6e\uff73\uff7a\uff78\uff8c\uff9e\uff8b\uff76\uff9e\uff7c\uff8c\uff9a"},"8115734":{"zip_code":"8115734","pref_kanji":"\u9577\u5d0e\u770c","city_kanji":"\u58f1\u5c90\u5e02","town_kanji":"\u82a6\u8fba\u753a\u56fd\u5206\u672c\u6751\u89e6","pref_roman":"NAGASAKI KEN","city_roman":"IKI SHI","town_roman":"ASHIBECHO KOKUBUHOMMURAFURE","code":"42210","old_zip_code":"81157","pref_kana":"\uff85\uff76\uff9e\uff7b\uff77\uff79\uff9d","city_kana":"\uff72\uff77\uff7c","town_kana":"\uff71\uff7c\uff8d\uff9e\uff81\uff6e\uff73\uff7a\uff78\uff8c\uff9e\uff8e\uff9d\uff91\uff97\uff8c\uff9a"},"8115744":{"zip_code":"8115744","pref_kanji":"\u9577\u5d0e\u770c","city_kanji":"\u58f1\u5c90\u5e02","town_kanji":"\u82a6\u8fba\u753a\u4f4f\u5409\u5f8c\u89e6","pref_roman":"NAGASAKI KEN","city_roman":"IKI SHI","town_roman":"ASHIBECHO SUMIYOSHIUSHIROFURE","code":"42210","old_zip_code":"81157","pref_kana":"\uff85\uff76\uff9e\uff7b\uff77\uff79\uff9d","city_kana":"\uff72\uff77\uff7c","town_kana":"\uff71\uff7c\uff8d\uff9e\uff81\uff6e\uff73\uff7d\uff90\uff96\uff7c\uff73\uff7c\uff9b\uff8c\uff9a"},"8115742":{"zip_code":"8115742","pref_kanji":"\u9577\u5d0e\u770c","city_kanji":"\u58f1\u5c90\u5e02","town_kanji":"\u82a6\u8fba\u753a\u4f4f\u5409\u6771\u89e6","pref_roman":"NAGASAKI KEN","city_roman":"IKI SHI","town_roman":"ASHIBECHO SUMIYOSHIHIGASHIFURE","code":"42210","old_zip_code":"81157","pref_kana":"\uff85\uff76\uff9e\uff7b\uff77\uff79\uff9d","city_kana":"\uff72\uff77\uff7c","town_kana":"\uff71\uff7c\uff8d\uff9e\uff81\uff6e\uff73\uff7d\uff90\uff96\uff7c\uff8b\uff76\uff9e\uff7c\uff8c\uff9a"},"8115743":{"zip_code":"8115743","pref_kanji":"\u9577\u5d0e\u770c","city_kanji":"\u58f1\u5c90\u5e02","town_kanji":"\u82a6\u8fba\u753a\u4f4f\u5409\u524d\u89e6","pref_roman":"NAGASAKI KEN","city_roman":"IKI SHI","town_roman":"ASHIBECHO SUMIYOSHIMAEFURE","code":"42210","old_zip_code":"81157","pref_kana":"\uff85\uff76\uff9e\uff7b\uff77\uff79\uff9d","city_kana":"\uff72\uff77\uff7c","town_kana":"\uff71\uff7c\uff8d\uff9e\uff81\uff6e\uff73\uff7d\uff90\uff96\uff7c\uff8f\uff74\uff8c\uff9a"},"8115741":{"zip_code":"8115741","pref_kanji":"\u9577\u5d0e\u770c","city_kanji":"\u58f1\u5c90\u5e02","town_kanji":"\u82a6\u8fba\u753a\u4f4f\u5409\u5c71\u4fe1\u89e6","pref_roman":"NAGASAKI KEN","city_roman":"IKI SHI","town_roman":"ASHIBECHO SUMIYOSHIYAMANOBUFURE","code":"42210","old_zip_code":"81157","pref_kana":"\uff85\uff76\uff9e\uff7b\uff77\uff79\uff9d","city_kana":"\uff72\uff77\uff7c","town_kana":"\uff71\uff7c\uff8d\uff9e\uff81\uff6e\uff73\uff7d\uff90\uff96\uff7c\uff94\uff8f\uff89\uff8c\uff9e\uff8c\uff9a"},"8115461":{"zip_code":"8115461","pref_kanji":"\u9577\u5d0e\u770c","city_kanji":"\u58f1\u5c90\u5e02","town_kanji":"\u82a6\u8fba\u753a\u702c\u6238\u6d66","pref_roman":"NAGASAKI KEN","city_roman":"IKI SHI","town_roman":"ASHIBECHO SETORA","code":"42210","old_zip_code":"81154","pref_kana":"\uff85\uff76\uff9e\uff7b\uff77\uff79\uff9d","city_kana":"\uff72\uff77\uff7c","town_kana":"\uff71\uff7c\uff8d\uff9e\uff81\uff6e\uff73\uff7e\uff84\uff73\uff97"},"8115751":{"zip_code":"8115751","pref_kanji":"\u9577\u5d0e\u770c","city_kanji":"\u58f1\u5c90\u5e02","town_kanji":"\u82a6\u8fba\u753a\u4e2d\u91ce\u90f7\u4ef2\u89e6","pref_roman":"NAGASAKI KEN","city_roman":"IKI SHI","town_roman":"ASHIBECHO NAKANOGONAKAFURE","code":"42210","old_zip_code":"81157","pref_kana":"\uff85\uff76\uff9e\uff7b\uff77\uff79\uff9d","city_kana":"\uff72\uff77\uff7c","town_kana":"\uff71\uff7c\uff8d\uff9e\uff81\uff6e\uff73\uff85\uff76\uff89\uff7a\uff9e\uff73\uff85\uff76\uff8c\uff9a"},"8115757":{"zip_code":"8115757","pref_kanji":"\u9577\u5d0e\u770c","city_kanji":"\u58f1\u5c90\u5e02","town_kanji":"\u82a6\u8fba\u753a\u4e2d\u91ce\u90f7\u897f\u89e6","pref_roman":"NAGASAKI KEN","city_roman":"IKI SHI","town_roman":"ASHIBECHO NAKANOGONISHIFURE","code":"42210","old_zip_code":"81157","pref_kana":"\uff85\uff76\uff9e\uff7b\uff77\uff79\uff9d","city_kana":"\uff72\uff77\uff7c","town_kana":"\uff71\uff7c\uff8d\uff9e\uff81\uff6e\uff73\uff85\uff76\uff89\uff7a\uff9e\uff73\uff86\uff7c\uff8c\uff9a"},"8115752":{"zip_code":"8115752","pref_kanji":"\u9577\u5d0e\u770c","city_kanji":"\u58f1\u5c90\u5e02","town_kanji":"\u82a6\u8fba\u753a\u4e2d\u91ce\u90f7\u6771\u89e6","pref_roman":"NAGASAKI KEN","city_roman":"IKI SHI","town_roman":"ASHIBECHO NAKANOGOHIGASHIFURE","code":"42210","old_zip_code":"81157","pref_kana":"\uff85\uff76\uff9e\uff7b\uff77\uff79\uff9d","city_kana":"\uff72\uff77\uff7c","town_kana":"\uff71\uff7c\uff8d\uff9e\uff81\uff6e\uff73\uff85\uff76\uff89\uff7a\uff9e\uff73\uff8b\uff76\uff9e\uff7c\uff8c\uff9a"},"8115756":{"zip_code":"8115756","pref_kanji":"\u9577\u5d0e\u770c","city_kanji":"\u58f1\u5c90\u5e02","town_kanji":"\u82a6\u8fba\u753a\u4e2d\u91ce\u90f7\u672c\u6751\u89e6","pref_roman":"NAGASAKI KEN","city_roman":"IKI SHI","town_roman":"ASHIBECHO NAKANOGOHOMMURAFURE","code":"42210","old_zip_code":"81157","pref_kana":"\uff85\uff76\uff9e\uff7b\uff77\uff79\uff9d","city_kana":"\uff72\uff77\uff7c","town_kana":"\uff71\uff7c\uff8d\uff9e\uff81\uff6e\uff73\uff85\uff76\uff89\uff7a\uff9e\uff73\uff8e\uff9d\uff91\uff97\uff8c\uff9a"},"8115467":{"zip_code":"8115467","pref_kanji":"\u9577\u5d0e\u770c","city_kanji":"\u58f1\u5c90\u5e02","town_kanji":"\u82a6\u8fba\u753a\u7bb1\u5d0e\u6c5f\u89d2\u89e6","pref_roman":"NAGASAKI KEN","city_roman":"IKI SHI","town_roman":"ASHIBECHO HAKOZAKIESUMIFURE","code":"42210","old_zip_code":"81154","pref_kana":"\uff85\uff76\uff9e\uff7b\uff77\uff79\uff9d","city_kana":"\uff72\uff77\uff7c","town_kana":"\uff71\uff7c\uff8d\uff9e\uff81\uff6e\uff73\uff8a\uff7a\uff7b\uff9e\uff77\uff74\uff7d\uff90\uff8c\uff9a"},"8115465":{"zip_code":"8115465","pref_kanji":"\u9577\u5d0e\u770c","city_kanji":"\u58f1\u5c90\u5e02","town_kanji":"\u82a6\u8fba\u753a\u7bb1\u5d0e\u91d8\u30ce\u5c3e\u89e6","pref_roman":"NAGASAKI KEN","city_roman":"IKI SHI","town_roman":"ASHIBECHO HAKOZAKIKUGINOFURE","code":"42210","old_zip_code":"81154","pref_kana":"\uff85\uff76\uff9e\uff7b\uff77\uff79\uff9d","city_kana":"\uff72\uff77\uff7c","town_kana":"\uff71\uff7c\uff8d\uff9e\uff81\uff6e\uff73\uff8a\uff7a\uff7b\uff9e\uff77\uff78\uff77\uff9e\uff89\uff75\uff8c\uff9a"},"8115462":{"zip_code":"8115462","pref_kanji":"\u9577\u5d0e\u770c","city_kanji":"\u58f1\u5c90\u5e02","town_kanji":"\u82a6\u8fba\u753a\u7bb1\u5d0e\u5927\u5de6\u53f3\u89e6","pref_roman":"NAGASAKI KEN","city_roman":"IKI SHI","town_roman":"ASHIBECHO HAKOZAKITAISOFURE","code":"42210","old_zip_code":"81154","pref_kana":"\uff85\uff76\uff9e\uff7b\uff77\uff79\uff9d","city_kana":"\uff72\uff77\uff7c","town_kana":"\uff71\uff7c\uff8d\uff9e\uff81\uff6e\uff73\uff8a\uff7a\uff7b\uff9e\uff77\uff80\uff72\uff7f\uff73\uff8c\uff9a"},"8115464":{"zip_code":"8115464","pref_kanji":"\u9577\u5d0e\u770c","city_kanji":"\u58f1\u5c90\u5e02","town_kanji":"\u82a6\u8fba\u753a\u7bb1\u5d0e\u8c37\u6c5f\u89e6","pref_roman":"NAGASAKI KEN","city_roman":"IKI SHI","town_roman":"ASHIBECHO HAKOZAKITANIEFURE","code":"42210","old_zip_code":"81154","pref_kana":"\uff85\uff76\uff9e\uff7b\uff77\uff79\uff9d","city_kana":"\uff72\uff77\uff7c","town_kana":"\uff71\uff7c\uff8d\uff9e\uff81\uff6e\uff73\uff8a\uff7a\uff7b\uff9e\uff77\uff80\uff86\uff74\uff8c\uff9a"},"8115463":{"zip_code":"8115463","pref_kanji":"\u9577\u5d0e\u770c","city_kanji":"\u58f1\u5c90\u5e02","town_kanji":"\u82a6\u8fba\u753a\u7bb1\u5d0e\u4e2d\u5c71\u89e6","pref_roman":"NAGASAKI KEN","city_roman":"IKI SHI","town_roman":"ASHIBECHO HAKOZAKINAKAYAMAFURE","code":"42210","old_zip_code":"81154","pref_kana":"\uff85\uff76\uff9e\uff7b\uff77\uff79\uff9d","city_kana":"\uff72\uff77\uff7c","town_kana":"\uff71\uff7c\uff8d\uff9e\uff81\uff6e\uff73\uff8a\uff7a\uff7b\uff9e\uff77\uff85\uff76\uff94\uff8f\uff8c\uff9a"},"8115466":{"zip_code":"8115466","pref_kanji":"\u9577\u5d0e\u770c","city_kanji":"\u58f1\u5c90\u5e02","town_kanji":"\u82a6\u8fba\u753a\u7bb1\u5d0e\u672c\u6751\u89e6","pref_roman":"NAGASAKI KEN","city_roman":"IKI SHI","town_roman":"ASHIBECHO HAKOZAKIHOMMURAFURE","code":"42210","old_zip_code":"81154","pref_kana":"\uff85\uff76\uff9e\uff7b\uff77\uff79\uff9d","city_kana":"\uff72\uff77\uff7c","town_kana":"\uff71\uff7c\uff8d\uff9e\uff81\uff6e\uff73\uff8a\uff7a\uff7b\uff9e\uff77\uff8e\uff9d\uff91\uff97\uff8c\uff9a"},"8115468":{"zip_code":"8115468","pref_kanji":"\u9577\u5d0e\u770c","city_kanji":"\u58f1\u5c90\u5e02","town_kanji":"\u82a6\u8fba\u753a\u7bb1\u5d0e\u8af8\u6d25\u89e6","pref_roman":"NAGASAKI KEN","city_roman":"IKI SHI","town_roman":"ASHIBECHO HAKOZAKIMOROTSUFURE","code":"42210","old_zip_code":"81154","pref_kana":"\uff85\uff76\uff9e\uff7b\uff77\uff79\uff9d","city_kana":"\uff72\uff77\uff7c","town_kana":"\uff71\uff7c\uff8d\uff9e\uff81\uff6e\uff73\uff8a\uff7a\uff7b\uff9e\uff77\uff93\uff9b\uff82\uff8c\uff9a"},"8115321":{"zip_code":"8115321","pref_kanji":"\u9577\u5d0e\u770c","city_kanji":"\u58f1\u5c90\u5e02","town_kanji":"\u82a6\u8fba\u753a\u6df1\u6c5f\u6804\u89e6","pref_roman":"NAGASAKI KEN","city_roman":"IKI SHI","town_roman":"ASHIBECHO FUKAESAKAEFURE","code":"42210","old_zip_code":"81153","pref_kana":"\uff85\uff76\uff9e\uff7b\uff77\uff79\uff9d","city_kana":"\uff72\uff77\uff7c","town_kana":"\uff71\uff7c\uff8d\uff9e\uff81\uff6e\uff73\uff8c\uff76\uff74\uff7b\uff76\uff74\uff8c\uff9a"},"8115322":{"zip_code":"8115322","pref_kanji":"\u9577\u5d0e\u770c","city_kanji":"\u58f1\u5c90\u5e02","town_kanji":"\u82a6\u8fba\u753a\u6df1\u6c5f\u9db4\u4e80\u89e6","pref_roman":"NAGASAKI KEN","city_roman":"IKI SHI","town_roman":"ASHIBECHO FUKAETSURUKIFURE","code":"42210","old_zip_code":"81153","pref_kana":"\uff85\uff76\uff9e\uff7b\uff77\uff79\uff9d","city_kana":"\uff72\uff77\uff7c","town_kana":"\uff71\uff7c\uff8d\uff9e\uff81\uff6e\uff73\uff8c\uff76\uff74\uff82\uff99\uff77\uff8c\uff9a"},"8115324":{"zip_code":"8115324","pref_kanji":"\u9577\u5d0e\u770c","city_kanji":"\u58f1\u5c90\u5e02","town_kanji":"\u82a6\u8fba\u753a\u6df1\u6c5f\u6771\u89e6","pref_roman":"NAGASAKI KEN","city_roman":"IKI SHI","town_roman":"ASHIBECHO FUKAEHIGASHIFURE","code":"42210","old_zip_code":"81153","pref_kana":"\uff85\uff76\uff9e\uff7b\uff77\uff79\uff9d","city_kana":"\uff72\uff77\uff7c","town_kana":"\uff71\uff7c\uff8d\uff9e\uff81\uff6e\uff73\uff8c\uff76\uff74\uff8b\uff76\uff9e\uff7c\uff8c\uff9a"},"8115323":{"zip_code":"8115323","pref_kanji":"\u9577\u5d0e\u770c","city_kanji":"\u58f1\u5c90\u5e02","town_kanji":"\u82a6\u8fba\u753a\u6df1\u6c5f\u5e73\u89e6","pref_roman":"NAGASAKI KEN","city_roman":"IKI SHI","town_roman":"ASHIBECHO FUKAEHIRAFURE","code":"42210","old_zip_code":"81153","pref_kana":"\uff85\uff76\uff9e\uff7b\uff77\uff79\uff9d","city_kana":"\uff72\uff77\uff7c","town_kana":"\uff71\uff7c\uff8d\uff9e\uff81\uff6e\uff73\uff8c\uff76\uff74\uff8b\uff97\uff8c\uff9a"},"8115326":{"zip_code":"8115326","pref_kanji":"\u9577\u5d0e\u770c","city_kanji":"\u58f1\u5c90\u5e02","town_kanji":"\u82a6\u8fba\u753a\u6df1\u6c5f\u672c\u6751\u89e6","pref_roman":"NAGASAKI KEN","city_roman":"IKI SHI","town_roman":"ASHIBECHO FUKAEHOMMURAFURE","code":"42210","old_zip_code":"81153","pref_kana":"\uff85\uff76\uff9e\uff7b\uff77\uff79\uff9d","city_kana":"\uff72\uff77\uff7c","town_kana":"\uff71\uff7c\uff8d\uff9e\uff81\uff6e\uff73\uff8c\uff76\uff74\uff8e\uff9d\uff91\uff97\uff8c\uff9a"},"8115325":{"zip_code":"8115325","pref_kanji":"\u9577\u5d0e\u770c","city_kanji":"\u58f1\u5c90\u5e02","town_kanji":"\u82a6\u8fba\u753a\u6df1\u6c5f\u5357\u89e6","pref_roman":"NAGASAKI KEN","city_roman":"IKI SHI","town_roman":"ASHIBECHO FUKAEMINAMIFURE","code":"42210","old_zip_code":"81153","pref_kana":"\uff85\uff76\uff9e\uff7b\uff77\uff79\uff9d","city_kana":"\uff72\uff77\uff7c","town_kana":"\uff71\uff7c\uff8d\uff9e\uff81\uff6e\uff73\uff8c\uff76\uff74\uff90\uff85\uff90\uff8c\uff9a"},"8115316":{"zip_code":"8115316","pref_kanji":"\u9577\u5d0e\u770c","city_kanji":"\u58f1\u5c90\u5e02","town_kanji":"\u82a6\u8fba\u753a\u8af8\u5409\u5927\u77f3\u89e6","pref_roman":"NAGASAKI KEN","city_roman":"IKI SHI","town_roman":"ASHIBECHO MOROYOSHIOISHIFURE","code":"42210","old_zip_code":"81153","pref_kana":"\uff85\uff76\uff9e\uff7b\uff77\uff79\uff9d","city_kana":"\uff72\uff77\uff7c","town_kana":"\uff71\uff7c\uff8d\uff9e\uff81\uff6e\uff73\uff93\uff9b\uff96\uff7c\uff75\uff75\uff72\uff7c\uff8c\uff9a"},"8115313":{"zip_code":"8115313","pref_kanji":"\u9577\u5d0e\u770c","city_kanji":"\u58f1\u5c90\u5e02","town_kanji":"\u82a6\u8fba\u753a\u8af8\u5409\u4ef2\u89e6","pref_roman":"NAGASAKI KEN","city_roman":"IKI SHI","town_roman":"ASHIBECHO MOROYOSHINAKAFURE","code":"42210","old_zip_code":"81153","pref_kana":"\uff85\uff76\uff9e\uff7b\uff77\uff79\uff9d","city_kana":"\uff72\uff77\uff7c","town_kana":"\uff71\uff7c\uff8d\uff9e\uff81\uff6e\uff73\uff93\uff9b\uff96\uff7c\uff85\uff76\uff8c\uff9a"},"8115314":{"zip_code":"8115314","pref_kanji":"\u9577\u5d0e\u770c","city_kanji":"\u58f1\u5c90\u5e02","town_kanji":"\u82a6\u8fba\u753a\u8af8\u5409\u6771\u89e6","pref_roman":"NAGASAKI KEN","city_roman":"IKI SHI","town_roman":"ASHIBECHO MOROYOSHIHIGASHIFURE","code":"42210","old_zip_code":"81153","pref_kana":"\uff85\uff76\uff9e\uff7b\uff77\uff79\uff9d","city_kana":"\uff72\uff77\uff7c","town_kana":"\uff71\uff7c\uff8d\uff9e\uff81\uff6e\uff73\uff93\uff9b\uff96\uff7c\uff8b\uff76\uff9e\uff7c\uff8c\uff9a"},"8115315":{"zip_code":"8115315","pref_kanji":"\u9577\u5d0e\u770c","city_kanji":"\u58f1\u5c90\u5e02","town_kanji":"\u82a6\u8fba\u753a\u8af8\u5409\u4e8c\u4ea6\u89e6","pref_roman":"NAGASAKI KEN","city_roman":"IKI SHI","town_roman":"ASHIBECHO MOROYOSHIFUTAMATAFURE","code":"42210","old_zip_code":"81153","pref_kana":"\uff85\uff76\uff9e\uff7b\uff77\uff79\uff9d","city_kana":"\uff72\uff77\uff7c","town_kana":"\uff71\uff7c\uff8d\uff9e\uff81\uff6e\uff73\uff93\uff9b\uff96\uff7c\uff8c\uff80\uff8f\uff80\uff8c\uff9a"},"8115311":{"zip_code":"8115311","pref_kanji":"\u9577\u5d0e\u770c","city_kanji":"\u58f1\u5c90\u5e02","town_kanji":"\u82a6\u8fba\u753a\u8af8\u5409\u672c\u6751\u89e6","pref_roman":"NAGASAKI KEN","city_roman":"IKI SHI","town_roman":"ASHIBECHO MOROYOSHIHOMMURAFURE","code":"42210","old_zip_code":"81153","pref_kana":"\uff85\uff76\uff9e\uff7b\uff77\uff79\uff9d","city_kana":"\uff72\uff77\uff7c","town_kana":"\uff71\uff7c\uff8d\uff9e\uff81\uff6e\uff73\uff93\uff9b\uff96\uff7c\uff8e\uff9d\uff91\uff97\uff8c\uff9a"},"8115312":{"zip_code":"8115312","pref_kanji":"\u9577\u5d0e\u770c","city_kanji":"\u58f1\u5c90\u5e02","town_kanji":"\u82a6\u8fba\u753a\u8af8\u5409\u5357\u89e6","pref_roman":"NAGASAKI KEN","city_roman":"IKI SHI","town_roman":"ASHIBECHO MOROYOSHIMINAMIFURE","code":"42210","old_zip_code":"81153","pref_kana":"\uff85\uff76\uff9e\uff7b\uff77\uff79\uff9d","city_kana":"\uff72\uff77\uff7c","town_kana":"\uff71\uff7c\uff8d\uff9e\uff81\uff6e\uff73\uff93\uff9b\uff96\uff7c\uff90\uff85\uff90\uff8c\uff9a"},"8115755":{"zip_code":"8115755","pref_kanji":"\u9577\u5d0e\u770c","city_kanji":"\u58f1\u5c90\u5e02","town_kanji":"\u82a6\u8fba\u753a\u6e6f\u5cb3\u8208\u89e6","pref_roman":"NAGASAKI KEN","city_roman":"IKI SHI","town_roman":"ASHIBECHO YUTAKEKOFURE","code":"42210","old_zip_code":"81157","pref_kana":"\uff85\uff76\uff9e\uff7b\uff77\uff79\uff9d","city_kana":"\uff72\uff77\uff7c","town_kana":"\uff71\uff7c\uff8d\uff9e\uff81\uff6e\uff73\uff95\uff80\uff79\uff7a\uff73\uff8c\uff9a"},"8115754":{"zip_code":"8115754","pref_kanji":"\u9577\u5d0e\u770c","city_kanji":"\u58f1\u5c90\u5e02","town_kanji":"\u82a6\u8fba\u753a\u6e6f\u5cb3\u4eca\u5742\u89e6","pref_roman":"NAGASAKI KEN","city_roman":"IKI SHI","town_roman":"ASHIBECHO YUTAKEKONZAKAFURE","code":"42210","old_zip_code":"81157","pref_kana":"\uff85\uff76\uff9e\uff7b\uff77\uff79\uff9d","city_kana":"\uff72\uff77\uff7c","town_kana":"\uff71\uff7c\uff8d\uff9e\uff81\uff6e\uff73\uff95\uff80\uff79\uff7a\uff9d\uff7b\uff9e\uff76\uff8c\uff9a"},"8115753":{"zip_code":"8115753","pref_kanji":"\u9577\u5d0e\u770c","city_kanji":"\u58f1\u5c90\u5e02","town_kanji":"\u82a6\u8fba\u753a\u6e6f\u5cb3\u672c\u6751\u89e6","pref_roman":"NAGASAKI KEN","city_roman":"IKI SHI","town_roman":"ASHIBECHO YUTAKEHOMMURAFURE","code":"42210","old_zip_code":"81157","pref_kana":"\uff85\uff76\uff9e\uff7b\uff77\uff79\uff9d","city_kana":"\uff72\uff77\uff7c","town_kana":"\uff71\uff7c\uff8d\uff9e\uff81\uff6e\uff73\uff95\uff80\uff79\uff8e\uff9d\uff91\uff97\uff8c\uff9a"},"8115222":{"zip_code":"8115222","pref_kanji":"\u9577\u5d0e\u770c","city_kanji":"\u58f1\u5c90\u5e02","town_kanji":"\u77f3\u7530\u753a\u6c60\u7530\u4ef2\u89e6","pref_roman":"NAGASAKI KEN","city_roman":"IKI SHI","town_roman":"ISHIDACHO IKEDANAKAFURE","code":"42210","old_zip_code":"81152","pref_kana":"\uff85\uff76\uff9e\uff7b\uff77\uff79\uff9d","city_kana":"\uff72\uff77\uff7c","town_kana":"\uff72\uff7c\uff80\uff9e\uff81\uff6e\uff73\uff72\uff79\uff80\uff9e\uff85\uff76\uff8c\uff9a"},"8115224":{"zip_code":"8115224","pref_kanji":"\u9577\u5d0e\u770c","city_kanji":"\u58f1\u5c90\u5e02","town_kanji":"\u77f3\u7530\u753a\u6c60\u7530\u897f\u89e6","pref_roman":"NAGASAKI KEN","city_roman":"IKI SHI","town_roman":"ISHIDACHO IKEDANISHIFURE","code":"42210","old_zip_code":"81152","pref_kana":"\uff85\uff76\uff9e\uff7b\uff77\uff79\uff9d","city_kana":"\uff72\uff77\uff7c","town_kana":"\uff72\uff7c\uff80\uff9e\uff81\uff6e\uff73\uff72\uff79\uff80\uff9e\uff86\uff7c\uff8c\uff9a"},"8115221":{"zip_code":"8115221","pref_kanji":"\u9577\u5d0e\u770c","city_kanji":"\u58f1\u5c90\u5e02","town_kanji":"\u77f3\u7530\u753a\u6c60\u7530\u6771\u89e6","pref_roman":"NAGASAKI KEN","city_roman":"IKI SHI","town_roman":"ISHIDACHO IKEDAHIGASHIFURE","code":"42210","old_zip_code":"81152","pref_kana":"\uff85\uff76\uff9e\uff7b\uff77\uff79\uff9d","city_kana":"\uff72\uff77\uff7c","town_kana":"\uff72\uff7c\uff80\uff9e\uff81\uff6e\uff73\uff72\uff79\uff80\uff9e\uff8b\uff76\uff9e\uff7c\uff8c\uff9a"},"8115215":{"zip_code":"8115215","pref_kanji":"\u9577\u5d0e\u770c","city_kanji":"\u58f1\u5c90\u5e02","town_kanji":"\u77f3\u7530\u753a\u77f3\u7530\u897f\u89e6","pref_roman":"NAGASAKI KEN","city_roman":"IKI SHI","town_roman":"ISHIDACHO ISHIDANISHIFURE","code":"42210","old_zip_code":"81152","pref_kana":"\uff85\uff76\uff9e\uff7b\uff77\uff79\uff9d","city_kana":"\uff72\uff77\uff7c","town_kana":"\uff72\uff7c\uff80\uff9e\uff81\uff6e\uff73\uff72\uff7c\uff80\uff9e\uff86\uff7c\uff8c\uff9a"},"8115211":{"zip_code":"8115211","pref_kanji":"\u9577\u5d0e\u770c","city_kanji":"\u58f1\u5c90\u5e02","town_kanji":"\u77f3\u7530\u753a\u77f3\u7530\u6771\u89e6","pref_roman":"NAGASAKI KEN","city_roman":"IKI SHI","town_roman":"ISHIDACHO ISHIDAHIGASHIFURE","code":"42210","old_zip_code":"81152","pref_kana":"\uff85\uff76\uff9e\uff7b\uff77\uff79\uff9d","city_kana":"\uff72\uff77\uff7c","town_kana":"\uff72\uff7c\uff80\uff9e\uff81\uff6e\uff73\uff72\uff7c\uff80\uff9e\uff8b\uff76\uff9e\uff7c\uff8c\uff9a"},"8115214":{"zip_code":"8115214","pref_kanji":"\u9577\u5d0e\u770c","city_kanji":"\u58f1\u5c90\u5e02","town_kanji":"\u77f3\u7530\u753a\u5370\u901a\u5bfa\u6d66","pref_roman":"NAGASAKI KEN","city_roman":"IKI SHI","town_roman":"ISHIDACHO INDOJIURA","code":"42210","old_zip_code":"81152","pref_kana":"\uff85\uff76\uff9e\uff7b\uff77\uff79\uff9d","city_kana":"\uff72\uff77\uff7c","town_kana":"\uff72\uff7c\uff80\uff9e\uff81\uff6e\uff73\uff72\uff9d\uff84\uff9e\uff75\uff7c\uff9e\uff73\uff97"},"8115223":{"zip_code":"8115223","pref_kanji":"\u9577\u5d0e\u770c","city_kanji":"\u58f1\u5c90\u5e02","town_kanji":"\u77f3\u7530\u753a\u4e45\u559c\u89e6","pref_roman":"NAGASAKI KEN","city_roman":"IKI SHI","town_roman":"ISHIDACHO KUKIFURE","code":"42210","old_zip_code":"81152","pref_kana":"\uff85\uff76\uff9e\uff7b\uff77\uff79\uff9d","city_kana":"\uff72\uff77\uff7c","town_kana":"\uff72\uff7c\uff80\uff9e\uff81\uff6e\uff73\uff78\uff77\uff8c\uff9a"},"8115202":{"zip_code":"8115202","pref_kanji":"\u9577\u5d0e\u770c","city_kanji":"\u58f1\u5c90\u5e02","town_kanji":"\u77f3\u7530\u753a\u7b52\u57ce\u4ef2\u89e6","pref_roman":"NAGASAKI KEN","city_roman":"IKI SHI","town_roman":"ISHIDACHO TSUTSUKINAKAFURE","code":"42210","old_zip_code":"81152","pref_kana":"\uff85\uff76\uff9e\uff7b\uff77\uff79\uff9d","city_kana":"\uff72\uff77\uff7c","town_kana":"\uff72\uff7c\uff80\uff9e\uff81\uff6e\uff73\uff82\uff82\uff77\uff85\uff76\uff8c\uff9a"},"8115204":{"zip_code":"8115204","pref_kanji":"\u9577\u5d0e\u770c","city_kanji":"\u58f1\u5c90\u5e02","town_kanji":"\u77f3\u7530\u753a\u7b52\u57ce\u897f\u89e6","pref_roman":"NAGASAKI KEN","city_roman":"IKI SHI","town_roman":"ISHIDACHO TSUTSUKINISHIFURE","code":"42210","old_zip_code":"81152","pref_kana":"\uff85\uff76\uff9e\uff7b\uff77\uff79\uff9d","city_kana":"\uff72\uff77\uff7c","town_kana":"\uff72\uff7c\uff80\uff9e\uff81\uff6e\uff73\uff82\uff82\uff77\uff86\uff7c\uff8c\uff9a"},"8115203":{"zip_code":"8115203","pref_kanji":"\u9577\u5d0e\u770c","city_kanji":"\u58f1\u5c90\u5e02","town_kanji":"\u77f3\u7530\u753a\u7b52\u57ce\u6771\u89e6","pref_roman":"NAGASAKI KEN","city_roman":"IKI SHI","town_roman":"ISHIDACHO TSUTSUKIHIGASHIFURE","code":"42210","old_zip_code":"81152","pref_kana":"\uff85\uff76\uff9e\uff7b\uff77\uff79\uff9d","city_kana":"\uff72\uff77\uff7c","town_kana":"\uff72\uff7c\uff80\uff9e\uff81\uff6e\uff73\uff82\uff82\uff77\uff8b\uff76\uff9e\uff7c\uff8c\uff9a"},"8115212":{"zip_code":"8115212","pref_kanji":"\u9577\u5d0e\u770c","city_kanji":"\u58f1\u5c90\u5e02","town_kanji":"\u77f3\u7530\u753a\u672c\u6751\u89e6","pref_roman":"NAGASAKI KEN","city_roman":"IKI SHI","town_roman":"ISHIDACHO HOMMURAFURE","code":"42210","old_zip_code":"81152","pref_kana":"\uff85\uff76\uff9e\uff7b\uff77\uff79\uff9d","city_kana":"\uff72\uff77\uff7c","town_kana":"\uff72\uff7c\uff80\uff9e\uff81\uff6e\uff73\uff8e\uff9d\uff91\uff97\uff8c\uff9a"},"8115213":{"zip_code":"8115213","pref_kanji":"\u9577\u5d0e\u770c","city_kanji":"\u58f1\u5c90\u5e02","town_kanji":"\u77f3\u7530\u753a\u5357\u89e6","pref_roman":"NAGASAKI KEN","city_roman":"IKI SHI","town_roman":"ISHIDACHO MINAMIFURE","code":"42210","old_zip_code":"81152","pref_kana":"\uff85\uff76\uff9e\uff7b\uff77\uff79\uff9d","city_kana":"\uff72\uff77\uff7c","town_kana":"\uff72\uff7c\uff80\uff9e\uff81\uff6e\uff73\uff90\uff85\uff90\uff8c\uff9a"},"8115201":{"zip_code":"8115201","pref_kanji":"\u9577\u5d0e\u770c","city_kanji":"\u58f1\u5c90\u5e02","town_kanji":"\u77f3\u7530\u753a\u5c71\u5d0e\u89e6","pref_roman":"NAGASAKI KEN","city_roman":"IKI SHI","town_roman":"ISHIDACHO YAMASAKIFURE","code":"42210","old_zip_code":"81152","pref_kana":"\uff85\uff76\uff9e\uff7b\uff77\uff79\uff9d","city_kana":"\uff72\uff77\uff7c","town_kana":"\uff72\uff7c\uff80\uff9e\uff81\uff6e\uff73\uff94\uff8f\uff7b\uff77\uff8c\uff9a"},"8115226":{"zip_code":"8115226","pref_kanji":"\u9577\u5d0e\u770c","city_kanji":"\u58f1\u5c90\u5e02","town_kanji":"\u77f3\u7530\u753a\u6e6f\u5cb3\u5c04\u624b\u5409\u89e6","pref_roman":"NAGASAKI KEN","city_roman":"IKI SHI","town_roman":"ISHIDACHO YUTAKEITEYOSHIFURE","code":"42210","old_zip_code":"81152","pref_kana":"\uff85\uff76\uff9e\uff7b\uff77\uff79\uff9d","city_kana":"\uff72\uff77\uff7c","town_kana":"\uff72\uff7c\uff80\uff9e\uff81\uff6e\uff73\uff95\uff80\uff79\uff72\uff83\uff96\uff7c\uff8c\uff9a"},"8115225":{"zip_code":"8115225","pref_kanji":"\u9577\u5d0e\u770c","city_kanji":"\u58f1\u5c90\u5e02","town_kanji":"\u77f3\u7530\u753a\u6e6f\u5cb3\u8208\u89e6","pref_roman":"NAGASAKI KEN","city_roman":"IKI SHI","town_roman":"ISHIDACHO YUTAKEKOFURE","code":"42210","old_zip_code":"81152","pref_kana":"\uff85\uff76\uff9e\uff7b\uff77\uff79\uff9d","city_kana":"\uff72\uff77\uff7c","town_kana":"\uff72\uff7c\uff80\uff9e\uff81\uff6e\uff73\uff95\uff80\uff79\uff7a\uff73\uff8c\uff9a"},"8115543":{"zip_code":"8115543","pref_kanji":"\u9577\u5d0e\u770c","city_kanji":"\u58f1\u5c90\u5e02","town_kanji":"\u52dd\u672c\u753a\u4e0a\u5834\u89e6","pref_roman":"NAGASAKI KEN","city_roman":"IKI SHI","town_roman":"KATSUMOTOCHO UWABAFURE","code":"42210","old_zip_code":"81155","pref_kana":"\uff85\uff76\uff9e\uff7b\uff77\uff79\uff9d","city_kana":"\uff72\uff77\uff7c","town_kana":"\uff76\uff82\uff93\uff84\uff81\uff6e\uff73\uff73\uff9c\uff8a\uff9e\uff8c\uff9a"},"8115532":{"zip_code":"8115532","pref_kanji":"\u9577\u5d0e\u770c","city_kanji":"\u58f1\u5c90\u5e02","town_kanji":"\u52dd\u672c\u753a\u5927\u4e45\u4fdd\u89e6","pref_roman":"NAGASAKI KEN","city_roman":"IKI SHI","town_roman":"KATSUMOTOCHO OKUBOFURE","code":"42210","old_zip_code":"81155","pref_kana":"\uff85\uff76\uff9e\uff7b\uff77\uff79\uff9d","city_kana":"\uff72\uff77\uff7c","town_kana":"\uff76\uff82\uff93\uff84\uff81\uff6e\uff73\uff75\uff75\uff78\uff8e\uff9e\uff8c\uff9a"},"8115523":{"zip_code":"8115523","pref_kanji":"\u9577\u5d0e\u770c","city_kanji":"\u58f1\u5c90\u5e02","town_kanji":"\u52dd\u672c\u753a\u7247\u5c71\u89e6","pref_roman":"NAGASAKI KEN","city_roman":"IKI SHI","town_roman":"KATSUMOTOCHO KATAYAMAFURE","code":"42210","old_zip_code":"81155","pref_kana":"\uff85\uff76\uff9e\uff7b\uff77\uff79\uff9d","city_kana":"\uff72\uff77\uff7c","town_kana":"\uff76\uff82\uff93\uff84\uff81\uff6e\uff73\uff76\uff80\uff94\uff8f\uff8c\uff9a"},"8115501":{"zip_code":"8115501","pref_kanji":"\u9577\u5d0e\u770c","city_kanji":"\u58f1\u5c90\u5e02","town_kanji":"\u52dd\u672c\u753a\u52dd\u672c\u6d66","pref_roman":"NAGASAKI KEN","city_roman":"IKI SHI","town_roman":"KATSUMOTOCHO KATSUMOTORA","code":"42210","old_zip_code":"81155","pref_kana":"\uff85\uff76\uff9e\uff7b\uff77\uff79\uff9d","city_kana":"\uff72\uff77\uff7c","town_kana":"\uff76\uff82\uff93\uff84\uff81\uff6e\uff73\uff76\uff82\uff93\uff84\uff73\uff97"},"8115513":{"zip_code":"8115513","pref_kanji":"\u9577\u5d0e\u770c","city_kanji":"\u58f1\u5c90\u5e02","town_kanji":"\u52dd\u672c\u753a\u5317\u89e6","pref_roman":"NAGASAKI KEN","city_roman":"IKI SHI","town_roman":"KATSUMOTOCHO KITAFURE","code":"42210","old_zip_code":"81155","pref_kana":"\uff85\uff76\uff9e\uff7b\uff77\uff79\uff9d","city_kana":"\uff72\uff77\uff7c","town_kana":"\uff76\uff82\uff93\uff84\uff81\uff6e\uff73\uff77\uff80\uff8c\uff9a"},"8115521":{"zip_code":"8115521","pref_kanji":"\u9577\u5d0e\u770c","city_kanji":"\u58f1\u5c90\u5e02","town_kanji":"\u52dd\u672c\u753a\u897f\u6238\u89e6","pref_roman":"NAGASAKI KEN","city_roman":"IKI SHI","town_roman":"KATSUMOTOCHO SAIDOFURE","code":"42210","old_zip_code":"81155","pref_kana":"\uff85\uff76\uff9e\uff7b\uff77\uff79\uff9d","city_kana":"\uff72\uff77\uff7c","town_kana":"\uff76\uff82\uff93\uff84\uff81\uff6e\uff73\uff7b\uff72\uff84\uff9e\uff8c\uff9a"},"8115531":{"zip_code":"8115531","pref_kanji":"\u9577\u5d0e\u770c","city_kanji":"\u58f1\u5c90\u5e02","town_kanji":"\u52dd\u672c\u753a\u5742\u672c\u89e6","pref_roman":"NAGASAKI KEN","city_roman":"IKI SHI","town_roman":"KATSUMOTOCHO SAKAMOTOFURE","code":"42210","old_zip_code":"81155","pref_kana":"\uff85\uff76\uff9e\uff7b\uff77\uff79\uff9d","city_kana":"\uff72\uff77\uff7c","town_kana":"\uff76\uff82\uff93\uff84\uff81\uff6e\uff73\uff7b\uff76\uff93\uff84\uff8c\uff9a"},"8115533":{"zip_code":"8115533","pref_kanji":"\u9577\u5d0e\u770c","city_kanji":"\u58f1\u5c90\u5e02","town_kanji":"\u52dd\u672c\u753a\u65b0\u57ce\u897f\u89e6","pref_roman":"NAGASAKI KEN","city_roman":"IKI SHI","town_roman":"KATSUMOTOCHO SHINJONISHIFURE","code":"42210","old_zip_code":"81155","pref_kana":"\uff85\uff76\uff9e\uff7b\uff77\uff79\uff9d","city_kana":"\uff72\uff77\uff7c","town_kana":"\uff76\uff82\uff93\uff84\uff81\uff6e\uff73\uff7c\uff9d\uff7c\uff9e\uff6e\uff73\uff86\uff7c\uff8c\uff9a"},"8115522":{"zip_code":"8115522","pref_kanji":"\u9577\u5d0e\u770c","city_kanji":"\u58f1\u5c90\u5e02","town_kanji":"\u52dd\u672c\u753a\u65b0\u57ce\u6771\u89e6","pref_roman":"NAGASAKI KEN","city_roman":"IKI SHI","town_roman":"KATSUMOTOCHO SHINJOHIGASHIFURE","code":"42210","old_zip_code":"81155","pref_kana":"\uff85\uff76\uff9e\uff7b\uff77\uff79\uff9d","city_kana":"\uff72\uff77\uff7c","town_kana":"\uff76\uff82\uff93\uff84\uff81\uff6e\uff73\uff7c\uff9d\uff7c\uff9e\uff6e\uff73\uff8b\uff76\uff9e\uff7c\uff8c\uff9a"},"8115554":{"zip_code":"8115554","pref_kanji":"\u9577\u5d0e\u770c","city_kanji":"\u58f1\u5c90\u5e02","town_kanji":"\u52dd\u672c\u753a\u7acb\u77f3\u4ef2\u89e6","pref_roman":"NAGASAKI KEN","city_roman":"IKI SHI","town_roman":"KATSUMOTOCHO TATEISHINAKAFURE","code":"42210","old_zip_code":"81155","pref_kana":"\uff85\uff76\uff9e\uff7b\uff77\uff79\uff9d","city_kana":"\uff72\uff77\uff7c","town_kana":"\uff76\uff82\uff93\uff84\uff81\uff6e\uff73\uff80\uff83\uff72\uff7c\uff85\uff76\uff8c\uff9a"},"8115556":{"zip_code":"8115556","pref_kanji":"\u9577\u5d0e\u770c","city_kanji":"\u58f1\u5c90\u5e02","town_kanji":"\u52dd\u672c\u753a\u7acb\u77f3\u897f\u89e6","pref_roman":"NAGASAKI KEN","city_roman":"IKI SHI","town_roman":"KATSUMOTOCHO TATEISHINISHIFURE","code":"42210","old_zip_code":"81155","pref_kana":"\uff85\uff76\uff9e\uff7b\uff77\uff79\uff9d","city_kana":"\uff72\uff77\uff7c","town_kana":"\uff76\uff82\uff93\uff84\uff81\uff6e\uff73\uff80\uff83\uff72\uff7c\uff86\uff7c\uff8c\uff9a"},"8115553":{"zip_code":"8115553","pref_kanji":"\u9577\u5d0e\u770c","city_kanji":"\u58f1\u5c90\u5e02","town_kanji":"\u52dd\u672c\u753a\u7acb\u77f3\u6771\u89e6","pref_roman":"NAGASAKI KEN","city_roman":"IKI SHI","town_roman":"KATSUMOTOCHO TATEISHIHIGASHIFURE","code":"42210","old_zip_code":"81155","pref_kana":"\uff85\uff76\uff9e\uff7b\uff77\uff79\uff9d","city_kana":"\uff72\uff77\uff7c","town_kana":"\uff76\uff82\uff93\uff84\uff81\uff6e\uff73\uff80\uff83\uff72\uff7c\uff8b\uff76\uff9e\uff7c\uff8c\uff9a"},"8115555":{"zip_code":"8115555","pref_kanji":"\u9577\u5d0e\u770c","city_kanji":"\u58f1\u5c90\u5e02","town_kanji":"\u52dd\u672c\u753a\u7acb\u77f3\u5357\u89e6","pref_roman":"NAGASAKI KEN","city_roman":"IKI SHI","town_roman":"KATSUMOTOCHO TATEISHIMINAMIFURE","code":"42210","old_zip_code":"81155","pref_kana":"\uff85\uff76\uff9e\uff7b\uff77\uff79\uff9d","city_kana":"\uff72\uff77\uff7c","town_kana":"\uff76\uff82\uff93\uff84\uff81\uff6e\uff73\uff80\uff83\uff72\uff7c\uff90\uff85\uff90\uff8c\uff9a"},"8115511":{"zip_code":"8115511","pref_kanji":"\u9577\u5d0e\u770c","city_kanji":"\u58f1\u5c90\u5e02","town_kanji":"\u52dd\u672c\u753a\u4ef2\u89e6","pref_roman":"NAGASAKI KEN","city_roman":"IKI SHI","town_roman":"KATSUMOTOCHO NAKAFURE","code":"42210","old_zip_code":"81155","pref_kana":"\uff85\uff76\uff9e\uff7b\uff77\uff79\uff9d","city_kana":"\uff72\uff77\uff7c","town_kana":"\uff76\uff82\uff93\uff84\uff81\uff6e\uff73\uff85\uff76\uff8c\uff9a"},"8115512":{"zip_code":"8115512","pref_kanji":"\u9577\u5d0e\u770c","city_kanji":"\u58f1\u5c90\u5e02","town_kanji":"\u52dd\u672c\u753a\u6771\u89e6","pref_roman":"NAGASAKI KEN","city_roman":"IKI SHI","town_roman":"KATSUMOTOCHO HIGASHIFURE","code":"42210","old_zip_code":"81155","pref_kana":"\uff85\uff76\uff9e\uff7b\uff77\uff79\uff9d","city_kana":"\uff72\uff77\uff7c","town_kana":"\uff76\uff82\uff93\uff84\uff81\uff6e\uff73\uff8b\uff76\uff9e\uff7c\uff8c\uff9a"},"8115544":{"zip_code":"8115544","pref_kanji":"\u9577\u5d0e\u770c","city_kanji":"\u58f1\u5c90\u5e02","town_kanji":"\u52dd\u672c\u753a\u5e03\u6c17\u89e6","pref_roman":"NAGASAKI KEN","city_roman":"IKI SHI","town_roman":"KATSUMOTOCHO FUKEFURE","code":"42210","old_zip_code":"81155","pref_kana":"\uff85\uff76\uff9e\uff7b\uff77\uff79\uff9d","city_kana":"\uff72\uff77\uff7c","town_kana":"\uff76\uff82\uff93\uff84\uff81\uff6e\uff73\uff8c\uff79\uff8c\uff9a"},"8115546":{"zip_code":"8115546","pref_kanji":"\u9577\u5d0e\u770c","city_kanji":"\u58f1\u5c90\u5e02","town_kanji":"\u52dd\u672c\u753a\u672c\u5bae\u4ef2\u89e6","pref_roman":"NAGASAKI KEN","city_roman":"IKI SHI","town_roman":"KATSUMOTOCHO HONGUNAKAFURE","code":"42210","old_zip_code":"81155","pref_kana":"\uff85\uff76\uff9e\uff7b\uff77\uff79\uff9d","city_kana":"\uff72\uff77\uff7c","town_kana":"\uff76\uff82\uff93\uff84\uff81\uff6e\uff73\uff8e\uff9d\uff78\uff9e\uff73\uff85\uff76\uff8c\uff9a"},"8115541":{"zip_code":"8115541","pref_kanji":"\u9577\u5d0e\u770c","city_kanji":"\u58f1\u5c90\u5e02","town_kanji":"\u52dd\u672c\u753a\u672c\u5bae\u897f\u89e6","pref_roman":"NAGASAKI KEN","city_roman":"IKI SHI","town_roman":"KATSUMOTOCHO HONGUNISHIFURE","code":"42210","old_zip_code":"81155","pref_kana":"\uff85\uff76\uff9e\uff7b\uff77\uff79\uff9d","city_kana":"\uff72\uff77\uff7c","town_kana":"\uff76\uff82\uff93\uff84\uff81\uff6e\uff73\uff8e\uff9d\uff78\uff9e\uff73\uff86\uff7c\uff8c\uff9a"},"8115542":{"zip_code":"8115542","pref_kanji":"\u9577\u5d0e\u770c","city_kanji":"\u58f1\u5c90\u5e02","town_kanji":"\u52dd\u672c\u753a\u672c\u5bae\u6771\u89e6","pref_roman":"NAGASAKI KEN","city_roman":"IKI SHI","town_roman":"KATSUMOTOCHO HONGUHIGASHIFURE","code":"42210","old_zip_code":"81155","pref_kana":"\uff85\uff76\uff9e\uff7b\uff77\uff79\uff9d","city_kana":"\uff72\uff77\uff7c","town_kana":"\uff76\uff82\uff93\uff84\uff81\uff6e\uff73\uff8e\uff9d\uff78\uff9e\uff73\uff8b\uff76\uff9e\uff7c\uff8c\uff9a"},"8115545":{"zip_code":"8115545","pref_kanji":"\u9577\u5d0e\u770c","city_kanji":"\u58f1\u5c90\u5e02","town_kanji":"\u52dd\u672c\u753a\u672c\u5bae\u5357\u89e6","pref_roman":"NAGASAKI KEN","city_roman":"IKI SHI","town_roman":"KATSUMOTOCHO HONGUMINAMIFURE","code":"42210","old_zip_code":"81155","pref_kana":"\uff85\uff76\uff9e\uff7b\uff77\uff79\uff9d","city_kana":"\uff72\uff77\uff7c","town_kana":"\uff76\uff82\uff93\uff84\uff81\uff6e\uff73\uff8e\uff9d\uff78\uff9e\uff73\uff90\uff85\uff90\uff8c\uff9a"},"8115551":{"zip_code":"8115551","pref_kanji":"\u9577\u5d0e\u770c","city_kanji":"\u58f1\u5c90\u5e02","town_kanji":"\u52dd\u672c\u753a\u6e6f\u672c\u6d66","pref_roman":"NAGASAKI KEN","city_roman":"IKI SHI","town_roman":"KATSUMOTOCHO YUNOMOTORA","code":"42210","old_zip_code":"81155","pref_kana":"\uff85\uff76\uff9e\uff7b\uff77\uff79\uff9d","city_kana":"\uff72\uff77\uff7c","town_kana":"\uff76\uff82\uff93\uff84\uff81\uff6e\uff73\uff95\uff89\uff93\uff84\uff73\uff97"},"8115552":{"zip_code":"8115552","pref_kanji":"\u9577\u5d0e\u770c","city_kanji":"\u58f1\u5c90\u5e02","town_kanji":"\u52dd\u672c\u753a\u767e\u5408\u7551\u89e6","pref_roman":"NAGASAKI KEN","city_roman":"IKI SHI","town_roman":"KATSUMOTOCHO YURIHATAFURE","code":"42210","old_zip_code":"81155","pref_kana":"\uff85\uff76\uff9e\uff7b\uff77\uff79\uff9d","city_kana":"\uff72\uff77\uff7c","town_kana":"\uff76\uff82\uff93\uff84\uff81\uff6e\uff73\uff95\uff98\uff8a\uff80\uff8c\uff9a"},"8115107":{"zip_code":"8115107","pref_kanji":"\u9577\u5d0e\u770c","city_kanji":"\u58f1\u5c90\u5e02","town_kanji":"\u90f7\u30ce\u6d66\u753a\u6709\u5b89\u89e6","pref_roman":"NAGASAKI KEN","city_roman":"IKI SHI","town_roman":"GONORACHO ARIYASUFURE","code":"42210","old_zip_code":"81151","pref_kana":"\uff85\uff76\uff9e\uff7b\uff77\uff79\uff9d","city_kana":"\uff72\uff77\uff7c","town_kana":"\uff7a\uff9e\uff73\uff89\uff73\uff97\uff81\uff6e\uff73\uff71\uff98\uff94\uff7d\uff8c\uff9a"},"8115113":{"zip_code":"8115113","pref_kanji":"\u9577\u5d0e\u770c","city_kanji":"\u58f1\u5c90\u5e02","town_kanji":"\u90f7\u30ce\u6d66\u753a\u725b\u65b9\u89e6","pref_roman":"NAGASAKI KEN","city_roman":"IKI SHI","town_roman":"GONORACHO USHIKATAFURE","code":"42210","old_zip_code":"81151","pref_kana":"\uff85\uff76\uff9e\uff7b\uff77\uff79\uff9d","city_kana":"\uff72\uff77\uff7c","town_kana":"\uff7a\uff9e\uff73\uff89\uff73\uff97\uff81\uff6e\uff73\uff73\uff7c\uff76\uff80\uff8c\uff9a"},"8115112":{"zip_code":"8115112","pref_kanji":"\u9577\u5d0e\u770c","city_kanji":"\u58f1\u5c90\u5e02","town_kanji":"\u90f7\u30ce\u6d66\u753a\u5927\u6d66\u89e6","pref_roman":"NAGASAKI KEN","city_roman":"IKI SHI","town_roman":"GONORACHO OURAFURE","code":"42210","old_zip_code":"81151","pref_kana":"\uff85\uff76\uff9e\uff7b\uff77\uff79\uff9d","city_kana":"\uff72\uff77\uff7c","town_kana":"\uff7a\uff9e\uff73\uff89\uff73\uff97\uff81\uff6e\uff73\uff75\uff75\uff73\uff97\uff8c\uff9a"},"8115161":{"zip_code":"8115161","pref_kanji":"\u9577\u5d0e\u770c","city_kanji":"\u58f1\u5c90\u5e02","town_kanji":"\u90f7\u30ce\u6d66\u753a\u5927\u5cf6","pref_roman":"NAGASAKI KEN","city_roman":"IKI SHI","town_roman":"GONORACHO OSHIMA","code":"42210","old_zip_code":"81151","pref_kana":"\uff85\uff76\uff9e\uff7b\uff77\uff79\uff9d","city_kana":"\uff72\uff77\uff7c","town_kana":"\uff7a\uff9e\uff73\uff89\uff73\uff97\uff81\uff6e\uff73\uff75\uff75\uff7c\uff8f"},"8115136":{"zip_code":"8115136","pref_kanji":"\u9577\u5d0e\u770c","city_kanji":"\u58f1\u5c90\u5e02","town_kanji":"\u90f7\u30ce\u6d66\u753a\u7247\u539f\u89e6","pref_roman":"NAGASAKI KEN","city_roman":"IKI SHI","town_roman":"GONORACHO KATABARUFURE","code":"42210","old_zip_code":"81151","pref_kana":"\uff85\uff76\uff9e\uff7b\uff77\uff79\uff9d","city_kana":"\uff72\uff77\uff7c","town_kana":"\uff7a\uff9e\uff73\uff89\uff73\uff97\uff81\uff6e\uff73\uff76\uff80\uff8a\uff9e\uff99\uff8c\uff9a"},"8115115":{"zip_code":"8115115","pref_kanji":"\u9577\u5d0e\u770c","city_kanji":"\u58f1\u5c90\u5e02","town_kanji":"\u90f7\u30ce\u6d66\u753a\u6728\u7530\u89e6","pref_roman":"NAGASAKI KEN","city_roman":"IKI SHI","town_roman":"GONORACHO KIDAFURE","code":"42210","old_zip_code":"81151","pref_kana":"\uff85\uff76\uff9e\uff7b\uff77\uff79\uff9d","city_kana":"\uff72\uff77\uff7c","town_kana":"\uff7a\uff9e\uff73\uff89\uff73\uff97\uff81\uff6e\uff73\uff77\uff80\uff9e\uff8c\uff9a"},"8115123":{"zip_code":"8115123","pref_kanji":"\u9577\u5d0e\u770c","city_kanji":"\u58f1\u5c90\u5e02","town_kanji":"\u90f7\u30ce\u6d66\u753a\u91d8\u5c71\u89e6","pref_roman":"NAGASAKI KEN","city_roman":"IKI SHI","town_roman":"GONORACHO KUGIYAMAFURE","code":"42210","old_zip_code":"81151","pref_kana":"\uff85\uff76\uff9e\uff7b\uff77\uff79\uff9d","city_kana":"\uff72\uff77\uff7c","town_kana":"\uff7a\uff9e\uff73\uff89\uff73\uff97\uff81\uff6e\uff73\uff78\uff77\uff9e\uff94\uff8f\uff8c\uff9a"},"8115135":{"zip_code":"8115135","pref_kanji":"\u9577\u5d0e\u770c","city_kanji":"\u58f1\u5c90\u5e02","town_kanji":"\u90f7\u30ce\u6d66\u753a\u90f7\u30ce\u6d66","pref_roman":"NAGASAKI KEN","city_roman":"IKI SHI","town_roman":"GONORACHO GONORA","code":"42210","old_zip_code":"81151","pref_kana":"\uff85\uff76\uff9e\uff7b\uff77\uff79\uff9d","city_kana":"\uff72\uff77\uff7c","town_kana":"\uff7a\uff9e\uff73\uff89\uff73\uff97\uff81\uff6e\uff73\uff7a\uff9e\uff73\uff89\uff73\uff97"},"8115105":{"zip_code":"8115105","pref_kanji":"\u9577\u5d0e\u770c","city_kanji":"\u58f1\u5c90\u5e02","town_kanji":"\u90f7\u30ce\u6d66\u753a\u5c0f\u7267\u897f\u89e6","pref_roman":"NAGASAKI KEN","city_roman":"IKI SHI","town_roman":"GONORACHO KOMAKINISHIFURE","code":"42210","old_zip_code":"81151","pref_kana":"\uff85\uff76\uff9e\uff7b\uff77\uff79\uff9d","city_kana":"\uff72\uff77\uff7c","town_kana":"\uff7a\uff9e\uff73\uff89\uff73\uff97\uff81\uff6e\uff73\uff7a\uff8f\uff77\uff86\uff7c\uff8c\uff9a"},"8115106":{"zip_code":"8115106","pref_kanji":"\u9577\u5d0e\u770c","city_kanji":"\u58f1\u5c90\u5e02","town_kanji":"\u90f7\u30ce\u6d66\u753a\u5c0f\u7267\u6771\u89e6","pref_roman":"NAGASAKI KEN","city_roman":"IKI SHI","town_roman":"GONORACHO KOMAKIHIGASHIFURE","code":"42210","old_zip_code":"81151","pref_kana":"\uff85\uff76\uff9e\uff7b\uff77\uff79\uff9d","city_kana":"\uff72\uff77\uff7c","town_kana":"\uff7a\uff9e\uff73\uff89\uff73\uff97\uff81\uff6e\uff73\uff7a\uff8f\uff77\uff8b\uff76\uff9e\uff7c\uff8c\uff9a"},"8115104":{"zip_code":"8115104","pref_kanji":"\u9577\u5d0e\u770c","city_kanji":"\u58f1\u5c90\u5e02","town_kanji":"\u90f7\u30ce\u6d66\u753a\u91cc\u89e6","pref_roman":"NAGASAKI KEN","city_roman":"IKI SHI","town_roman":"GONORACHO SATOFURE","code":"42210","old_zip_code":"81151","pref_kana":"\uff85\uff76\uff9e\uff7b\uff77\uff79\uff9d","city_kana":"\uff72\uff77\uff7c","town_kana":"\uff7a\uff9e\uff73\uff89\uff73\uff97\uff81\uff6e\uff73\uff7b\uff84\uff8c\uff9a"},"8115125":{"zip_code":"8115125","pref_kanji":"\u9577\u5d0e\u770c","city_kanji":"\u58f1\u5c90\u5e02","town_kanji":"\u90f7\u30ce\u6d66\u753a\u5fd7\u539f\u897f\u89e6","pref_roman":"NAGASAKI KEN","city_roman":"IKI SHI","town_roman":"GONORACHO SHIHARANISHIFURE","code":"42210","old_zip_code":"81151","pref_kana":"\uff85\uff76\uff9e\uff7b\uff77\uff79\uff9d","city_kana":"\uff72\uff77\uff7c","town_kana":"\uff7a\uff9e\uff73\uff89\uff73\uff97\uff81\uff6e\uff73\uff7c\uff8a\uff97\uff86\uff7c\uff8c\uff9a"},"8115124":{"zip_code":"8115124","pref_kanji":"\u9577\u5d0e\u770c","city_kanji":"\u58f1\u5c90\u5e02","town_kanji":"\u90f7\u30ce\u6d66\u753a\u5fd7\u539f\u5357\u89e6","pref_roman":"NAGASAKI KEN","city_roman":"IKI SHI","town_roman":"GONORACHO SHIHARAMINAMIFURE","code":"42210","old_zip_code":"81151","pref_kana":"\uff85\uff76\uff9e\uff7b\uff77\uff79\uff9d","city_kana":"\uff72\uff77\uff7c","town_kana":"\uff7a\uff9e\uff73\uff89\uff73\uff97\uff81\uff6e\uff73\uff7c\uff8a\uff97\uff90\uff85\uff90\uff8c\uff9a"},"8115134":{"zip_code":"8115134","pref_kanji":"\u9577\u5d0e\u770c","city_kanji":"\u58f1\u5c90\u5e02","town_kanji":"\u90f7\u30ce\u6d66\u753a\u5e84\u89e6","pref_roman":"NAGASAKI KEN","city_roman":"IKI SHI","town_roman":"GONORACHO SHOFURE","code":"42210","old_zip_code":"81151","pref_kana":"\uff85\uff76\uff9e\uff7b\uff77\uff79\uff9d","city_kana":"\uff72\uff77\uff7c","town_kana":"\uff7a\uff9e\uff73\uff89\uff73\uff97\uff81\uff6e\uff73\uff7c\uff6e\uff73\uff8c\uff9a"},"8115103":{"zip_code":"8115103","pref_kanji":"\u9577\u5d0e\u770c","city_kanji":"\u58f1\u5c90\u5e02","town_kanji":"\u90f7\u30ce\u6d66\u753a\u65b0\u7530\u89e6","pref_roman":"NAGASAKI KEN","city_roman":"IKI SHI","town_roman":"GONORACHO SHINDENFURE","code":"42210","old_zip_code":"81151","pref_kana":"\uff85\uff76\uff9e\uff7b\uff77\uff79\uff9d","city_kana":"\uff72\uff77\uff7c","town_kana":"\uff7a\uff9e\uff73\uff89\uff73\uff97\uff81\uff6e\uff73\uff7c\uff9d\uff83\uff9e\uff9d\uff8c\uff9a"},"8115122":{"zip_code":"8115122","pref_kanji":"\u9577\u5d0e\u770c","city_kanji":"\u58f1\u5c90\u5e02","town_kanji":"\u90f7\u30ce\u6d66\u753a\u5927\u539f\u89e6","pref_roman":"NAGASAKI KEN","city_roman":"IKI SHI","town_roman":"GONORACHO TAIBARUFURE","code":"42210","old_zip_code":"81151","pref_kana":"\uff85\uff76\uff9e\uff7b\uff77\uff79\uff9d","city_kana":"\uff72\uff77\uff7c","town_kana":"\uff7a\uff9e\uff73\uff89\uff73\uff97\uff81\uff6e\uff73\uff80\uff72\uff8a\uff9e\uff99\uff8c\uff9a"},"8115117":{"zip_code":"8115117","pref_kanji":"\u9577\u5d0e\u770c","city_kanji":"\u58f1\u5c90\u5e02","town_kanji":"\u90f7\u30ce\u6d66\u753a\u7530\u4e2d\u89e6","pref_roman":"NAGASAKI KEN","city_roman":"IKI SHI","town_roman":"GONORACHO TANAKAFURE","code":"42210","old_zip_code":"81151","pref_kana":"\uff85\uff76\uff9e\uff7b\uff77\uff79\uff9d","city_kana":"\uff72\uff77\uff7c","town_kana":"\uff7a\uff9e\uff73\uff89\uff73\uff97\uff81\uff6e\uff73\uff80\uff85\uff76\uff8c\uff9a"},"8115142":{"zip_code":"8115142","pref_kanji":"\u9577\u5d0e\u770c","city_kanji":"\u58f1\u5c90\u5e02","town_kanji":"\u90f7\u30ce\u6d66\u753a\u576a\u89e6","pref_roman":"NAGASAKI KEN","city_roman":"IKI SHI","town_roman":"GONORACHO TSUBOFURE","code":"42210","old_zip_code":"81151","pref_kana":"\uff85\uff76\uff9e\uff7b\uff77\uff79\uff9d","city_kana":"\uff72\uff77\uff7c","town_kana":"\uff7a\uff9e\uff73\uff89\uff73\uff97\uff81\uff6e\uff73\uff82\uff8e\uff9e\uff8c\uff9a"},"8115162":{"zip_code":"8115162","pref_kanji":"\u9577\u5d0e\u770c","city_kanji":"\u58f1\u5c90\u5e02","town_kanji":"\u90f7\u30ce\u6d66\u753a\u9577\u5cf6","pref_roman":"NAGASAKI KEN","city_roman":"IKI SHI","town_roman":"GONORACHO NAGASHIMA","code":"42210","old_zip_code":"81151","pref_kana":"\uff85\uff76\uff9e\uff7b\uff77\uff79\uff9d","city_kana":"\uff72\uff77\uff7c","town_kana":"\uff7a\uff9e\uff73\uff89\uff73\uff97\uff81\uff6e\uff73\uff85\uff76\uff9e\uff7c\uff8f"},"8115131":{"zip_code":"8115131","pref_kanji":"\u9577\u5d0e\u770c","city_kanji":"\u58f1\u5c90\u5e02","town_kanji":"\u90f7\u30ce\u6d66\u753a\u6c38\u7530\u89e6","pref_roman":"NAGASAKI KEN","city_roman":"IKI SHI","town_roman":"GONORACHO NAGATAFURE","code":"42210","old_zip_code":"81151","pref_kana":"\uff85\uff76\uff9e\uff7b\uff77\uff79\uff9d","city_kana":"\uff72\uff77\uff7c","town_kana":"\uff7a\uff9e\uff73\uff89\uff73\uff97\uff81\uff6e\uff73\uff85\uff76\uff9e\uff80\uff8c\uff9a"},"8115102":{"zip_code":"8115102","pref_kanji":"\u9577\u5d0e\u770c","city_kanji":"\u58f1\u5c90\u5e02","town_kanji":"\u90f7\u30ce\u6d66\u753a\u9577\u5cf0\u6771\u89e6","pref_roman":"NAGASAKI KEN","city_roman":"IKI SHI","town_roman":"GONORACHO NAGAMINEHIGASHIFURE","code":"42210","old_zip_code":"81151","pref_kana":"\uff85\uff76\uff9e\uff7b\uff77\uff79\uff9d","city_kana":"\uff72\uff77\uff7c","town_kana":"\uff7a\uff9e\uff73\uff89\uff73\uff97\uff81\uff6e\uff73\uff85\uff76\uff9e\uff90\uff88\uff8b\uff76\uff9e\uff7c\uff8c\uff9a"},"8115101":{"zip_code":"8115101","pref_kanji":"\u9577\u5d0e\u770c","city_kanji":"\u58f1\u5c90\u5e02","town_kanji":"\u90f7\u30ce\u6d66\u753a\u9577\u5cf0\u672c\u6751\u89e6","pref_roman":"NAGASAKI KEN","city_roman":"IKI SHI","town_roman":"GONORACHO NAGAMINEHOMMURAFURE","code":"42210","old_zip_code":"81151","pref_kana":"\uff85\uff76\uff9e\uff7b\uff77\uff79\uff9d","city_kana":"\uff72\uff77\uff7c","town_kana":"\uff7a\uff9e\uff73\uff89\uff73\uff97\uff81\uff6e\uff73\uff85\uff76\uff9e\uff90\uff88\uff8e\uff9d\uff91\uff97\uff8c\uff9a"},"8115143":{"zip_code":"8115143","pref_kanji":"\u9577\u5d0e\u770c","city_kanji":"\u58f1\u5c90\u5e02","town_kanji":"\u90f7\u30ce\u6d66\u753a\u521d\u5c71\u897f\u89e6","pref_roman":"NAGASAKI KEN","city_roman":"IKI SHI","town_roman":"GONORACHO HATSUYAMANISHIFURE","code":"42210","old_zip_code":"81151","pref_kana":"\uff85\uff76\uff9e\uff7b\uff77\uff79\uff9d","city_kana":"\uff72\uff77\uff7c","town_kana":"\uff7a\uff9e\uff73\uff89\uff73\uff97\uff81\uff6e\uff73\uff8a\uff82\uff94\uff8f\uff86\uff7c\uff8c\uff9a"},"8115144":{"zip_code":"8115144","pref_kanji":"\u9577\u5d0e\u770c","city_kanji":"\u58f1\u5c90\u5e02","town_kanji":"\u90f7\u30ce\u6d66\u753a\u521d\u5c71\u6771\u89e6","pref_roman":"NAGASAKI KEN","city_roman":"IKI SHI","town_roman":"GONORACHO HATSUYAMAHIGASHIFURE","code":"42210","old_zip_code":"81151","pref_kana":"\uff85\uff76\uff9e\uff7b\uff77\uff79\uff9d","city_kana":"\uff72\uff77\uff7c","town_kana":"\uff7a\uff9e\uff73\uff89\uff73\uff97\uff81\uff6e\uff73\uff8a\uff82\uff94\uff8f\uff8b\uff76\uff9e\uff7c\uff8c\uff9a"},"8115163":{"zip_code":"8115163","pref_kanji":"\u9577\u5d0e\u770c","city_kanji":"\u58f1\u5c90\u5e02","town_kanji":"\u90f7\u30ce\u6d66\u753a\u539f\u5cf6","pref_roman":"NAGASAKI KEN","city_roman":"IKI SHI","town_roman":"GONORACHO HARUSHIMA","code":"42210","old_zip_code":"81151","pref_kana":"\uff85\uff76\uff9e\uff7b\uff77\uff79\uff9d","city_kana":"\uff72\uff77\uff7c","town_kana":"\uff7a\uff9e\uff73\uff89\uff73\uff97\uff81\uff6e\uff73\uff8a\uff99\uff7c\uff8f"},"8115111":{"zip_code":"8115111","pref_kanji":"\u9577\u5d0e\u770c","city_kanji":"\u58f1\u5c90\u5e02","town_kanji":"\u90f7\u30ce\u6d66\u753a\u534a\u57ce\u672c\u6751\u89e6","pref_roman":"NAGASAKI KEN","city_roman":"IKI SHI","town_roman":"GONORACHO HANSEIHOMMURAFURE","code":"42210","old_zip_code":"81151","pref_kana":"\uff85\uff76\uff9e\uff7b\uff77\uff79\uff9d","city_kana":"\uff72\uff77\uff7c","town_kana":"\uff7a\uff9e\uff73\uff89\uff73\uff97\uff81\uff6e\uff73\uff8a\uff9d\uff7e\uff72\uff8e\uff9d\uff91\uff97\uff8c\uff9a"},"8115132":{"zip_code":"8115132","pref_kanji":"\u9577\u5d0e\u770c","city_kanji":"\u58f1\u5c90\u5e02","town_kanji":"\u90f7\u30ce\u6d66\u753a\u6771\u89e6","pref_roman":"NAGASAKI KEN","city_roman":"IKI SHI","town_roman":"GONORACHO HIGASHIFURE","code":"42210","old_zip_code":"81151","pref_kana":"\uff85\uff76\uff9e\uff7b\uff77\uff79\uff9d","city_kana":"\uff72\uff77\uff7c","town_kana":"\uff7a\uff9e\uff73\uff89\uff73\uff97\uff81\uff6e\uff73\uff8b\uff76\uff9e\uff7c\uff8c\uff9a"},"8115121":{"zip_code":"8115121","pref_kanji":"\u9577\u5d0e\u770c","city_kanji":"\u58f1\u5c90\u5e02","town_kanji":"\u90f7\u30ce\u6d66\u753a\u5e73\u4eba\u89e6","pref_roman":"NAGASAKI KEN","city_roman":"IKI SHI","town_roman":"GONORACHO HIROTOFURE","code":"42210","old_zip_code":"81151","pref_kana":"\uff85\uff76\uff9e\uff7b\uff77\uff79\uff9d","city_kana":"\uff72\uff77\uff7c","town_kana":"\uff7a\uff9e\uff73\uff89\uff73\uff97\uff81\uff6e\uff73\uff8b\uff9b\uff73\uff84\uff8c\uff9a"},"8115133":{"zip_code":"8115133","pref_kanji":"\u9577\u5d0e\u770c","city_kanji":"\u58f1\u5c90\u5e02","town_kanji":"\u90f7\u30ce\u6d66\u753a\u672c\u6751\u89e6","pref_roman":"NAGASAKI KEN","city_roman":"IKI SHI","town_roman":"GONORACHO HOMMURAFURE","code":"42210","old_zip_code":"81151","pref_kana":"\uff85\uff76\uff9e\uff7b\uff77\uff79\uff9d","city_kana":"\uff72\uff77\uff7c","town_kana":"\uff7a\uff9e\uff73\uff89\uff73\uff97\uff81\uff6e\uff73\uff8e\uff9d\uff91\uff97\uff8c\uff9a"},"8115155":{"zip_code":"8115155","pref_kanji":"\u9577\u5d0e\u770c","city_kanji":"\u58f1\u5c90\u5e02","town_kanji":"\u90f7\u30ce\u6d66\u753a\u9ea6\u8c37\u89e6","pref_roman":"NAGASAKI KEN","city_roman":"IKI SHI","town_roman":"GONORACHO MUGIYAFURE","code":"42210","old_zip_code":"81151","pref_kana":"\uff85\uff76\uff9e\uff7b\uff77\uff79\uff9d","city_kana":"\uff72\uff77\uff7c","town_kana":"\uff7a\uff9e\uff73\uff89\uff73\uff97\uff81\uff6e\uff73\uff91\uff77\uff9e\uff94\uff8c\uff9a"},"8115116":{"zip_code":"8115116","pref_kanji":"\u9577\u5d0e\u770c","city_kanji":"\u58f1\u5c90\u5e02","town_kanji":"\u90f7\u30ce\u6d66\u753a\u7269\u90e8\u672c\u6751\u89e6","pref_roman":"NAGASAKI KEN","city_roman":"IKI SHI","town_roman":"GONORACHO MONOBEHOMMURAFURE","code":"42210","old_zip_code":"81151","pref_kana":"\uff85\uff76\uff9e\uff7b\uff77\uff79\uff9d","city_kana":"\uff72\uff77\uff7c","town_kana":"\uff7a\uff9e\uff73\uff89\uff73\uff97\uff81\uff6e\uff73\uff93\uff89\uff8d\uff9e\uff8e\uff9d\uff91\uff97\uff8c\uff9a"},"8115114":{"zip_code":"8115114","pref_kanji":"\u9577\u5d0e\u770c","city_kanji":"\u58f1\u5c90\u5e02","town_kanji":"\u90f7\u30ce\u6d66\u753a\u67f3\u7530\u89e6","pref_roman":"NAGASAKI KEN","city_roman":"IKI SHI","town_roman":"GONORACHO YANAGIDAFURE","code":"42210","old_zip_code":"81151","pref_kana":"\uff85\uff76\uff9e\uff7b\uff77\uff79\uff9d","city_kana":"\uff72\uff77\uff7c","town_kana":"\uff7a\uff9e\uff73\uff89\uff73\uff97\uff81\uff6e\uff73\uff94\uff85\uff77\uff9e\uff80\uff9e\uff8c\uff9a"},"8115141":{"zip_code":"8115141","pref_kanji":"\u9577\u5d0e\u770c","city_kanji":"\u58f1\u5c90\u5e02","town_kanji":"\u90f7\u30ce\u6d66\u753a\u82e5\u677e\u89e6","pref_roman":"NAGASAKI KEN","city_roman":"IKI SHI","town_roman":"GONORACHO WAKAMATSUFURE","code":"42210","old_zip_code":"81151","pref_kana":"\uff85\uff76\uff9e\uff7b\uff77\uff79\uff9d","city_kana":"\uff72\uff77\uff7c","town_kana":"\uff7a\uff9e\uff73\uff89\uff73\uff97\uff81\uff6e\uff73\uff9c\uff76\uff8f\uff82\uff8c\uff9a"},"8115151":{"zip_code":"8115151","pref_kanji":"\u9577\u5d0e\u770c","city_kanji":"\u58f1\u5c90\u5e02","town_kanji":"\u90f7\u30ce\u6d66\u753a\u6e21\u826f\u6d66","pref_roman":"NAGASAKI KEN","city_roman":"IKI SHI","town_roman":"GONORACHO WATARAURA","code":"42210","old_zip_code":"81151","pref_kana":"\uff85\uff76\uff9e\uff7b\uff77\uff79\uff9d","city_kana":"\uff72\uff77\uff7c","town_kana":"\uff7a\uff9e\uff73\uff89\uff73\uff97\uff81\uff6e\uff73\uff9c\uff80\uff97\uff73\uff97"},"8115153":{"zip_code":"8115153","pref_kanji":"\u9577\u5d0e\u770c","city_kanji":"\u58f1\u5c90\u5e02","town_kanji":"\u90f7\u30ce\u6d66\u753a\u6e21\u826f\u897f\u89e6","pref_roman":"NAGASAKI KEN","city_roman":"IKI SHI","town_roman":"GONORACHO WATARANISHIFURE","code":"42210","old_zip_code":"81151","pref_kana":"\uff85\uff76\uff9e\uff7b\uff77\uff79\uff9d","city_kana":"\uff72\uff77\uff7c","town_kana":"\uff7a\uff9e\uff73\uff89\uff73\uff97\uff81\uff6e\uff73\uff9c\uff80\uff97\uff86\uff7c\uff8c\uff9a"},"8115154":{"zip_code":"8115154","pref_kanji":"\u9577\u5d0e\u770c","city_kanji":"\u58f1\u5c90\u5e02","town_kanji":"\u90f7\u30ce\u6d66\u753a\u6e21\u826f\u6771\u89e6","pref_roman":"NAGASAKI KEN","city_roman":"IKI SHI","town_roman":"GONORACHO WATARAHIGASHIFURE","code":"42210","old_zip_code":"81151","pref_kana":"\uff85\uff76\uff9e\uff7b\uff77\uff79\uff9d","city_kana":"\uff72\uff77\uff7c","town_kana":"\uff7a\uff9e\uff73\uff89\uff73\uff97\uff81\uff6e\uff73\uff9c\uff80\uff97\uff8b\uff76\uff9e\uff7c\uff8c\uff9a"},"8115152":{"zip_code":"8115152","pref_kanji":"\u9577\u5d0e\u770c","city_kanji":"\u58f1\u5c90\u5e02","town_kanji":"\u90f7\u30ce\u6d66\u753a\u6e21\u826f\u5357\u89e6","pref_roman":"NAGASAKI KEN","city_roman":"IKI SHI","town_roman":"GONORACHO WATARAMINAMIFURE","code":"42210","old_zip_code":"81151","pref_kana":"\uff85\uff76\uff9e\uff7b\uff77\uff79\uff9d","city_kana":"\uff72\uff77\uff7c","town_kana":"\uff7a\uff9e\uff73\uff89\uff73\uff97\uff81\uff6e\uff73\uff9c\uff80\uff97\uff90\uff85\uff90\uff8c\uff9a"}}